Workbook

Sheet 報酬確認シート（非表示）
B2: 【コーチの皆さんへ共有】 | T2: 切り替わったタイミングの請求金額をどうしているかを確認
B3: ①コーチング実施報告をするための集計に必要な情報を入力するシートです。セッション実施日を 「yyyy/mm/dd」の形式で入力してください。 | AA3: 統一のため1回：9000円で計算
B4: ②入力したデータを元に、セッション実施回数が「コミッション管理」のタブで自動集計されます。 | P4: 2月かどう | R4: 3月かどう | T4: 4月かどう | V4: 5月かどう | X4: 6月かどう | Z4: 7月かどう
O5: 請求回数： | P5: 1回目 | R5: 2回目 | T5: 3回目 | V5: 4回目 | X5: 5回目 | Z5: 6回目
F6: 旧カリキュラム | L6: ▼最終請求日 | O6: ▼初回セッション | P6: ▼通常セッション（セッション完了→ピンクセルに変更） | AA6: 日割り計算請求 | AB6: 請求書を見て入力・差額を算出 | AD6: 内訳
A7: no. | B7: 生徒名 | C7: ユーザーID | D7: 生徒ページ | E7: 講師 | F7: クラス名 | G7: メンター | H7: 生徒の入会日 | I7: 講義スタート日 | J7: 一次連絡 | K7: 初回通常セッション | M7: 担当コーチ | N7: アサインフィー | O7: 0 | P7: 1 | Q7: 2 | R7: 3 | S7: 4 | T7: 5 | U7: 6 | V7: 7 | W7: 8 | X7: 9 | Y7: 10 | Z7: 11 | AA7: 12 | AB7: 実際の請求金額合計 | AC7: トータル請求（税込） | AD7: 旧請求（アサインフィー込み） | AE7: 新報酬請求回数 | AF7: 新報酬満額請求 | AG7: 新報酬日割り請求回数 | AH7: 新報酬日割り請求額 | AI7: 確認列 | AJ7: 最終セッション | AK7: 最終請求月
A8: 1 | B8: おのまこと | C8: https://www.instagram.com/koji_no_chie?igsh=MTlhMjVlZWY5amRkeg== | D8: https://www.notion.so/f-737444a6e90e4062b518aa81f931d776?pvs=4 | E8: 駒居 | F8: F組 | G8: 駒居 | H8: 45242 | I8: 45255 | K8: =P8 -> 5000 | L8: - | M8: 宮田友理_1 | N8: 5000 | O8: 5000 | P8: 5000 | Q8: 5000 | R8: 5000 | S8: 5000 | T8: 5000 | U8: 休会 | AC8: =sum(N8:AA8) -> 35000 | AD8: =sum(N8:T8) -> 35000 | AE8: 0 | AF8: =18000*AE8 -> 0 | AG8: 0 | AH8: 0 | AI8: =sum(AD8,AF8,AH8) -> 35000 | AJ8: =vlookup(A8,'セッション実施状況管理'!$A:$AH,26,false) -> 45316
A9: 2 | B9: ただゆうすけ | C9: https://www.instagram.com/cya__home?igsh=NzZwaHVzcnN1bGtx | D9: https://www.notion.so/f-6bc9cdd93a074de893311d8592e4ea8f?pvs=4 | E9: 駒居 | F9: F組 | G9: 駒居 | H9: 45246 | I9: 45255 | K9: =P9 -> 5000 | L9: 45460 | M9: 中村恵理_1 | N9: 5000 | O9: 5000 | P9: 5000 | Q9: 5000 | R9: 5000 | S9: 5000 | T9: 5000 | U9: 5000 | V9: 5000 | W9: 5000 | X9: 18000 | Y9: 0 | Z9: 18000 | AA9: 0 | AC9: =sum(N9:AA9) -> 86000 | AD9: =sum(N9:W9) -> 50000 | AE9: 2 | AF9: =18000*AE9 -> 36000 | AG9: 0 | AH9: 0 | AI9: =sum(AD9,AF9,AH9) -> 86000 | AJ9: =vlookup(A9,'セッション実施状況管理'!$A:$AH,26,false) -> 45335 | AK9: 8月
A10: 3 | B10: ふじたなな | C10: https://www.instagram.com/ta_ma_diet/ | D10: https://www.notion.so/g-f905aeb65a5b41d2bd8e8e578a505b09?pvs=4 | E10: 駒居 | F10: G組 | G10: 駒居 | H10: 45258 | I10: 45271 | K10: =P10 -> 5000 | L10: 45455 | M10: 森本風花_1 | N10: 5000 | O10: 5000 | P10: 5000 | Q10: 5000 | R10: 5000 | S10: 5000 | T10: 5000 | U10: 5000 | V10: 5000 | W10: 5000 | X10: 5000 | Y10: 18000 | Z10: 0 | AA10: 9000 | AC10: =sum(N10:AA10) -> 82000 | AD10: =sum(N10:X10) -> 55000 | AE10: 1 | AF10: =18000*AE10 -> 18000 | AG10: 1 | AH10: =18000*(12/30) -> 7200 | AI10: =sum(AD10,AF10,AH10) -> 80200 | AJ10: =vlookup(A10,'セッション実施状況管理'!$A:$AH,26,false) -> 45331 | AK10: 7月
A11: 4 | B11: よしだむつみ | D11: https://www.notion.so/g-bb484bedf0da44c3a9204e56c3708820?pvs=4 | E11: 駒居 | F11: G組 | G11: 駒居 | H11: 45270 | I11: 45271 | K11: =P11 -> 5000 | L11: 45466 | M11: 野村佑佳_1 | N11: 5000 | O11: 5000 | P11: 5000 | Q11: 5000 | R11: 5000 | S11: 5000 | T11: 5000 | U11: 5000 | V11: 5000 | W11: 5000 | X11: 5000 | Y11: 5000 | Z11: 18000 | AA11: 0 | AC11: =sum(N11:AA11) -> 78000 | AD11: =sum(N11:Y11) -> 60000 | AE11: 1 | AF11: =18000*AE11 -> 18000 | AG11: 0 | AH11: 0 | AI11: =sum(AD11,AF11,AH11) -> 78000 | AJ11: =vlookup(A11,'セッション実施状況管理'!$A:$AH,26,false) -> 45321 | AK11: 7月
A12: 5 | B12: きたがわたかひろ | D12: https://www.notion.so/A-48b87799aff1416cbb3a1970912131a3?pvs=4 | E12: けい | F12: A組 | G12: けい | H12: 45298 | I12: 45310 | J12: 45298 | K12: =P12 -> 5000 | L12: 45130 | M12: 豊榮信江_1 | N12: 5000 | O12: 5000 | P12: 5000 | Q12: 5000 | R12: 5000 | S12: 5000 | T12: 5000 | U12: 5000 | V12: 5000 | W12: 18000 | X12: 0 | Y12: 18000 | Z12: 0 | AA12: 9000 | AC12: =sum(N12:AA12) -> 90000 | AD12: =sum(N12:V12) -> 45000 | AE12: 2 | AF12: =18000*AE12 -> 36000 | AG12: 1 | AH12: =18000*(23/30) -> 13800 | AI12: =sum(AD12,AF12,AH12) -> 94800 | AJ12: =vlookup(A12,'セッション実施状況管理'!$A:$AH,26,false) -> 45369 | AK12: 8月
A13: 6 | B13: ありやまゆうな | D13: https://www.notion.so/h-2df374753777409caed7a8803b749bdc | E13: 駒居 | F13: H組 | G13: 駒居 | H13: 45298 | I13: 45320 | K13: =P13 -> 5000 | L13: =K13+180 -> 5180 | M13: 野村佑佳_2 | N13: 5000 | O13: 5000 | P13: 5000 | Q13: 5000 | R13: 5000 | S13: 5000 | T13: 5000 | U13: 5000 | V13: 18000 | W13: 0 | X13: 18000 | Y13: 0 | Z13: 18000 | AA13: 0 | AC13: =SUM(N13:AA13) -> 94000
A14: 7 | B14: たけにしゆかり | C14: https://www.instagram.com/yukari_instakigyo?igsh=MWc1YWV0NHF3anIweA== | D14: https://www.notion.so/H-a94b7996758f4e3c9ddb2a8211a4098c?pvs=4 | E14: 駒居 | F14: H組 | G14: 駒居 | H14: 45299 | I14: 45320 | K14: =P14 -> 5000 | L14: 45503 | M14: 宮田友理_2 | N14: 5000 | O14: 5000 | P14: 5000 | Q14: 5000 | R14: 5000 | S14: 5000 | T14: 5000 | U14: 5000 | V14: 18000 | W14: 0 | X14: 18000 | Y14: 0 | Z14: 18000 | AA14: 0 | AC14: =sum(N14:AA14) -> 94000 | AD14: =sum(N14:U14) -> 40000 | AE14: 3 | AF14: =18000*AE14 -> 54000 | AG14: 0 | AH14: 0 | AI14: =sum(AD14,AF14,AH14) -> 94000 | AJ14: =vlookup(A14,'セッション実施状況管理'!$A:$AH,26,false) -> 45376 | AK14: 8月
A15: 8 | B15: くどうゆみこ | D15: https://www.notion.so/C-1b937693667844edb42ba0b3f91eb95a | E15: しらゆき | F15: D組 | G15: しらゆき | H15: 45313 | I15: 2月上旬 | J15: 45315 | K15: =P15 -> 5000 | L15: 45521 | M15: 野村佑佳_3 | N15: 5000 | O15: 5000 | P15: 5000 | Q15: 5000 | R15: 5000 | S15: 5000 | T15: 5000 | U15: 18000 | V15: 0 | W15: 18000 | X15: 0 | Y15: 18000 | Z15: 0 | AA15: 9000 | AC15: =sum(N15:AA15) -> 98000 | AD15: =sum(N15:T15) -> 35000 | AE15: 3 | AF15: =18000*AE15 -> 54000 | AG15: 1 | AH15: =18000*(17/30) -> 10200 | AI15: =sum(AD15,AF15,AH15) -> 99200 | AJ15: =vlookup(A15,'セッション実施状況管理'!$A:$AH,26,false) -> 45390
A16: 9 | B16: たわらかずみ | D16: https://www.notion.so/H-6c47c382fb41416bb5398a08d0efa69a?pvs=4 | E16: ソウタ | F16: H組 | G16: いとた | H16: 45314 | I16: 2月上旬 | K16: =P16 -> 5000 | L16: 45515 | M16: 中村恵理_2 | N16: 5000 | O16: 5000 | P16: 5000 | Q16: 5000 | R16: 5000 | S16: 5000 | T16: 5000 | U16: 5000 | V16: 18000 | W16: 0 | X16: 18000 | Y16: 0 | Z16: 18000 | AA16: 0 | AC16: =sum(N16:AA16) -> 94000 | AD16: =sum(N16:U16) -> 40000 | AE16: 3 | AF16: =18000*AE16 -> 54000 | AG16: 0 | AH16: 0 | AI16: =sum(AD16,AF16,AH16) -> 94000 | AJ16: =vlookup(A16,'セッション実施状況管理'!$A:$AH,26,false) -> 45387
A17: 10 | B17: やまぐちしんいちろう | D17: https://www.notion.so/h-4ee1213842f34a8abc522b1b681bf0a8?pvs=4 | E17: ソウタ | F17: H組 | G17: いとた | H17: 45317 | I17: 2月上旬 | J17: 45319 | K17: =P17 -> 5000 | L17: 45514 | M17: 森本風花_2 | N17: 5000 | O17: 5000 | P17: 5000 | Q17: 5000 | R17: 5000 | S17: 5000 | T17: 5000 | U17: 5000 | V17: 18000 | W17: 0 | X17: 18000 | Y17: 0 | Z17: 18000 | AA17: 0 | AC17: =sum(N17:AA17) -> 94000 | AD17: =sum(N17:U17) -> 40000 | AE17: 3 | AF17: =18000*AE17 -> 54000 | AG17: 0 | AH17: 0 | AI17: =sum(AD17,AF17,AH17) -> 94000 | AJ17: =vlookup(A17,'セッション実施状況管理'!$A:$AH,26,false) -> 45375 | AK17: 8月
A18: 11 | B18: かわかみまさと | D18: https://www.notion.so/C-4f2fdb58942d4be1b66b12e294a78cce | E18: しらゆき | F18: C組 | G18: しらゆき | H18: 45320 | I18: 2月上旬 | J18: 45320 | K18: =P18 -> 5000 | L18: 45520 | M18: 野村佑佳_4 | N18: 5000 | O18: 5000 | P18: 5000 | Q18: 5000 | R18: 5000 | S18: 5000 | T18: 5000 | U18: 18000 | V18: 0 | W18: 18000 | X18: 0 | Y18: 18000 | Z18: 0 | AA18: 9000 | AC18: =sum(N18:AA18) -> 98000 | AD18: =sum(N18:T18) -> 35000 | AE18: 3 | AF18: =18000*AE18 -> 54000 | AG18: 1 | AH18: =18000*(16/30) -> 9600 | AI18: =sum(AD18,AF18,AH18) -> 98600 | AJ18: =vlookup(A18,'セッション実施状況管理'!$A:$AH,26,false) -> 45389
A19: 12 | B19: すどうえり | C19: https://www.instagram.com/richan_hair?igsh=b2oxMXgybGl5NGNj&utm_source=qr | D19: https://www.notion.so/h-75b166b01bdd4a7dab2f816f840c40f6?pvs=4 | E19: ソウタ | F19: H組 | G19: いとた | H19: 45320 | I19: 2月上旬 | J19: 45320 | K19: =P19 -> 5000 | L19: 45514 | M19: 宮田友理_3 | N19: 5000 | O19: 5000 | P19: 5000 | Q19: 5000 | R19: 5000 | S19: 5000 | T19: 5000 | U19: 18000 | V19: 0 | W19: 18000 | X19: 0 | Y19: 18000 | Z19: 0 | AA19: 9000 | AC19: =sum(N19:AA19) -> 98000 | AD19: =sum(N19:T19) -> 35000 | AE19: 3 | AF19: =18000*AE19 -> 54000 | AG19: 1 | AH19: =18000*(10/30) -> 6000 | AI19: =sum(AD19,AF19,AH19) -> 95000 | AJ19: =vlookup(A19,'セッション実施状況管理'!$A:$AH,26,false) -> 45400 | AK19: 9月
A20: 13 | B20: なかのあや | D20: https://www.notion.so/C-18ef10444b5245ea9a00a9fa9f6aa26f?pvs=4 | E20: しらゆき | F20: C組 | G20: しらゆき | H20: 45325 | I20: 2月上旬 | J20: 45325 | K20: =P20 -> 5000 | L20: 45527 | M20: 清原三和子_1 | N20: 5000 | O20: 5000 | P20: 5000 | Q20: 5000 | R20: 5000 | S20: 5000 | T20: 5000 | U20: 18000 | V20: 0 | W20: 18000 | X20: 0 | Y20: 18000 | Z20: 0 | AA20: 9000 | AC20: =sum(N20:AA20) -> 98000 | AD20: =sum(N20:T20) -> 35000 | AE20: 3 | AF20: =18000*AE20 -> 54000 | AG20: 1 | AH20: =18000*(23/30) -> 13800 | AI20: =sum(AD20,AF20,AH20) -> 102800 | AJ20: =vlookup(A20,'セッション実施状況管理'!$A:$AH,26,false) -> 45388 | AK20: 8月
A21: 14 | B21: うちだあやみ | D21: https://www.notion.so/B-daf8c007896a46c19df1d51b7331b579?pvs=4 | E21: けいいち | F21: B組 | G21: けいいち | H21: 45326 | I21: 2月中旬 | J21: 45326 | K21: =P21 -> 5000 | L21: 45526 | M21: 清原三和子_2 | N21: 5000 | O21: 5000 | P21: 5000 | Q21: 5000 | R21: 5000 | S21: 5000 | T21: 5000 | U21: 18000 | V21: 0 | W21: 18000 | X21: 0 | Y21: 18000 | Z21: 0 | AA21: 9000 | AC21: =sum(N21:AA21) -> 98000 | AD21: =sum(N21:T21) -> 35000 | AE21: 3 | AF21: =18000*AE21 -> 54000 | AG21: 1 | AH21: =18000*(22/30) -> 13200 | AI21: =sum(AD21,AF21,AH21) -> 102200 | AJ21: =vlookup(A21,'セッション実施状況管理'!$A:$AH,26,false) -> 45388 | AK21: 8月
A22: 15 | B22: さかもとなみこ | D22: https://www.notion.so/A-30616aeef36d46609bace7715472cba9 | E22: ふみや | F22: A組 | G22: ふみや | H22: 45328 | I22: 45335 | J22: 45328 | K22: =P22 -> 5000 | L22: 45520 | M22: 山見阪佳子_1 | N22: 5000 | O22: 5000 | P22: 5000 | Q22: 5000 | R22: 5000 | S22: 5000 | T22: 5000 | U22: 5000 | V22: 18000 | W22: 0 | X22: 18000 | Y22: 0 | Z22: 18000 | AA22: 0 | AC22: =sum(N22:AA22) -> 94000 | AD22: =sum(N22:U22) -> 40000 | AE22: 3 | AF22: =18000*AE22 -> 54000 | AG22: 0 | AH22: 0 | AI22: =sum(AD22,AF22,AH22) -> 94000 | AJ22: =vlookup(A22,'セッション実施状況管理'!$A:$AH,26,false) -> 202403/30 | AK22: 8月
A23: 16 | B23: あいざわくみこ | D23: https://www.notion.so/A-49f636e8bc784058b509202e308d986d?pvs=4 | E23: ふみや | F23: A組 | G23: ふみや | H23: 45328 | I23: 2月中旬 | J23: 45328 | K23: =P23 -> 5000 | L23: 45531 | M23: 清原三和子_3 | N23: 5000 | O23: 5000 | P23: 5000 | Q23: 5000 | R23: 5000 | S23: 5000 | T23: 5000 | U23: 5000 | V23: 18000 | W23: 0 | X23: 18000 | Y23: 0 | Z23: 18000 | AA23: 0 | AC23: =sum(N23:AA23) -> 94000 | AD23: =sum(N23:U23) -> 40000 | AE23: 3 | AF23: =18000*AE23 -> 54000 | AG23: 0 | AH23: 0 | AI23: =sum(AD23,AF23,AH23) -> 94000 | AJ23: =vlookup(A23,'セッション実施状況管理'!$A:$AH,26,false) -> 45384 | AK23: 8月
A24: 17 | B24: よこやまあいと | E24: ふみや | F24: B組 | G24: ふみや | H24: 45330 | I24: 2月中旬 | J24: 45330 | K24: =P24 -> 5000 | L24: 45540 | M24: 福田康裕_1 | N24: 5000 | O24: 5000 | P24: 5000 | Q24: 5000 | R24: 18000 | S24: 0 | T24: 18000 | U24: 0 | V24: 18000 | W24: 0 | X24: 18000 | Y24: 0 | Z24: 18000 | AA24: 0 | AC24: =sum(N24:AA24) -> 110000 | AD24: =sum(N24:Q24) -> 20000 | AE24: 5 | AF24: =18000*AE24 -> 90000 | AG24: 0 | AH24: 0 | AI24: =sum(AD24,AF24,AH24) -> 110000 | AJ24: =vlookup(A24,'セッション実施状況管理'!$A:$AH,26,false) -> 45445
A25: 18 | B25: ふちがみあや | D25: https://www.notion.so/c7b88ab6a5674a1cb0260e9c208c019a | E25: ふみや | F25: B組 | G25: ふみや | H25: 45330 | I25: 2月中旬 | J25: 45330 | K25: =P25 -> 5000 | L25: 45530 | M25: 山見阪佳子_2 | N25: 5000 | O25: 5000 | P25: 5000 | Q25: 5000 | R25: 5000 | S25: 5000 | T25: 18000 | U25: 0 | V25: 18000 | W25: 0 | X25: 18000 | Y25: 0 | Z25: 18000 | AA25: 0 | AC25: =sum(N25:AA25) -> 102000 | AD25: =sum(N25:S25) -> 30000 | AE25: 4 | AF25: =18000*AE25 -> 72000 | AG25: 0 | AH25: 0 | AI25: =sum(AD25,AF25,AH25) -> 102000 | AJ25: =vlookup(A25,'セッション実施状況管理'!$A:$AH,26,false) -> 45397
A26: 19 | B26: おおにしちかこ | E26: ソウタ | F26: J組 | G26: ハム | H26: 45347 | I26: 3月上旬〜中旬 | J26: 45348 | K26: =P26 -> 5000 | L26: 45592 | M26: 須見浩人_1 | N26: 5000 | O26: 5000 | P26: 5000 | Q26: 18000 | R26: 0 | S26: 18000 | T26: 0 | U26: 18000 | V26: 0 | W26: 18000 | X26: 0 | Y26: 18000 | Z26: 0 | AA26: 9000 | AC26: =sum(N26:AA26) -> 114000 | AD26: =sum(N26:P26) -> 15000 | AE26: 5 | AF26: =18000*AE26 -> 90000 | AG26: 1 | AH26: =18000*(27/30) -> 16200 | AI26: =sum(AD26,AF26,AH26) -> 121200 | AJ26: =vlookup(A26,'セッション実施状況管理'!$A:$AH,26,false) -> 45481
A27: 20 | B27: すだはるき | E27: 村松 | F27: E組 | G27: 村松 | H27: 45385 | I27: 4月下旬 | J27: 45385 | K27: =P27 -> 5000 | L27: 45594 | M27: 須見浩人_2 | N27: 5000 | O27: 5000 | P27: 5000 | Q27: 18000 | R27: 0 | S27: 18000 | T27: 0 | U27: 18000 | V27: 0 | W27: 18000 | X27: 0 | Y27: 18000 | Z27: 0 | AA27: 9000 | AC27: =sum(N27:AA27) -> 114000 | AD27: =sum(N27:P27) -> 15000 | AE27: 5 | AF27: =18000*AE27 -> 90000 | AG27: 0 | AH27: =18000*(29/30) -> 17400 | AI27: =sum(AD27,AF27,AH27) -> 122400 | AJ27: =vlookup(A27,'セッション実施状況管理'!$A:$AH,26,false) -> 45477
A28: 21 | B28: かしはらせつみ | E28: ソウタ | F28: L組 | G28: 村松 | H28: 45392 | I28: 4月下旬 | J28: 45392 | K28: =P28 -> 18000 | L28: 45586 | M28: 宮田友理_4 | N28: 5000 | O28: 5000 | P28: 18000 | Q28: 0 | R28: 18000 | S28: 0 | T28: 18000 | U28: 0 | V28: 18000 | W28: 0 | X28: 18000 | Y28: 0 | Z28: 18000 | AA28: 0 | AC28: =sum(N28:AA28) -> 118000 | AD28: =sum(N28:O28) -> 10000 | AE28: 5 | AF28: =18000*AE28 -> 90000 | AG28: 0 | AI28: =sum(AD28,AF28,AH28) -> 100000 | AJ28: =vlookup(A28,'セッション実施状況管理'!$A:$AH,26,false) -> 45455 | AK28: 11月
A29: 22 | B29: ながおあみり | E29: 村松 | F29: F組 | G29: 村松 | H29: 45409 | I29: 5月中旬 | K29: =P29 -> 18000 | L29: 45615 | M29: 野村佑佳_5 | N29: - | O29: 0 | P29: 18000 | Q29: 0 | R29: 18000 | S29: 0 | T29: 18000 | U29: 0 | V29: 18000 | W29: 0 | X29: 18000 | Y29: 0 | Z29: 18000 | AA29: 0 | AC29: =sum(N29:AA29) -> 108000 | AD29: 0 | AE29: 6 | AF29: =18000*AE29 -> 108000 | AG29: 0 | AH29: 0 | AI29: =sum(AD29,AF29,AH29) -> 108000 | AJ29: =vlookup(A29,'セッション実施状況管理'!$A:$AH,26,false) -> 45491
A30: 23 | B30: こばやしはるか | E30: 村松 | F30: F組 | G30: 村松 | H30: 45411 | I30: 5月中旬 | J30: 45414 | K30: =P30 -> 18000 | L30: 45629 | M30: 清原三和子_4 | N30: - | O30: 0 | P30: 18000 | Q30: 0 | R30: 18000 | S30: 0 | T30: 18000 | U30: 0 | V30: 18000 | W30: 0 | X30: 18000 | Y30: 0 | Z30: 18000 | AA30: 0 | AC30: =sum(N30:AA30) -> 108000 | AD30: 0 | AE30: 6 | AF30: =18000*AE30 -> 108000 | AG30: 0 | AH30: 0 | AI30: =sum(AD30,AF30,AH30) -> 108000 | AJ30: =vlookup(A30,'セッション実施状況管理'!$A:$AH,26,false) -> 45491
A31: 24 | B31: じょうどじゆうき | E31: けいいち | F31: C組 | G31: けいいち | H31: 45429 | I31: 6月上旬 | K31: =P31 -> 18000 | L31: 180 | M31: 福田康裕_2 | N31: - | O31: 0 | P31: 18000 | Q31: 0 | R31: 18000 | S31: 0 | T31: 18000 | U31: 0 | V31: 18000 | W31: 0 | X31: 18000 | Y31: 0 | Z31: 18000 | AA31: 0 | AC31: =sum(N31:AA31) -> 108000 | AD31: 0 | AE31: 6 | AF31: =18000*AE31 -> 108000 | AG31: 0 | AH31: 0 | AI31: =sum(AD31,AF31,AH31) -> 108000 | AJ31: =vlookup(A31,'セッション実施状況管理'!$A:$AH,26,false)
A32: 25 | B32: たなかゆりか | E32: けいいち | F32: C組 | G32: けいいち | H32: 45430 | I32: 6月上旬 | J32: 45433 | K32: =P32 | L32: 180 | M32: 清原三和子_5 | N32: - | O32: 5000 | AC32: =sum(N32:AA32) -> 5000 | AD32: 0 | AE32: 6 | AF32: =18000*AE32 -> 108000 | AG32: 0 | AH32: 0 | AI32: =sum(AD32,AF32,AH32) -> 108000 | AJ32: =vlookup(A32,'セッション実施状況管理'!$A:$AH,26,false)
A33: 26 | B33: かわしま あらし | E33: 村松 | F33: G組 | G33: 村松 | H33: 45434 | I33: 6月上旬 | K33: =P33 -> 18000 | L33: 45634 | M33: 森本風花_3 | N33: - | O33: 0 | P33: 18000 | Q33: 0 | R33: 18000 | S33: 0 | T33: 18000 | U33: 0 | V33: 18000 | W33: 0 | X33: 18000 | Y33: 0 | Z33: 18000 | AA33: 0 | AC33: =sum(N33:AA33) -> 108000 | AD33: 0 | AE33: 6 | AF33: =18000*AE33 -> 108000 | AG33: 0 | AH33: 0 | AI33: =sum(AD33,AF33,AH33) -> 108000 | AJ33: =vlookup(A33,'セッション実施状況管理'!$A:$AH,26,false) -> 45496
A34: 27 | B34: せきおかまさき | E34: ふみや | F34: C組 | G34: ふみや | H34: 45438 | I34: 6月上旬 | K34: =P34 -> 18000 | L34: 180 | M34: 福田康裕_3 | N34: - | O34: 0 | P34: 18000 | Q34: 0 | R34: 18000 | S34: 0 | T34: 18000 | U34: 0 | V34: 18000 | W34: 0 | X34: 18000 | Y34: 0 | Z34: 18000 | AA34: 0 | AC34: =sum(N34:AA34) -> 108000 | AD34: 0 | AE34: 6 | AF34: =18000*AE34 -> 108000 | AG34: 0 | AH34: 0 | AI34: =sum(AD34,AF34,AH34) -> 108000 | AJ34: =vlookup(A34,'セッション実施状況管理'!$A:$AH,26,false)
A35: 28 | B35: しらどうさき | E35: 未定 | F35: 未定 | G35: 未定 | H35: 45440 | I35: 出産のため7月末から受講開始を希望 | K35: =P35 | L35: =K35+180 -> 180 | O35: アサイン・クラス決めは7月末生徒さんから連絡いただき次第行う。一旦保留
A36: 29 | B36: まさきちさと | E36: ふみや | F36: C組 | G36: ふみや | H36: 45440 | I36: 6月上旬 | J36: 45441 | K36: =P36 -> 18000 | L36: 45643 | M36: 宮田友理_5 | N36: - | O36: 0 | P36: 18000 | Q36: 0 | R36: 18000 | S36: 0 | T36: 18000 | U36: 0 | V36: 18000 | W36: 0 | X36: 18000 | Y36: 0 | Z36: 18000 | AA36: 0 | AC36: =sum(N36:AA36) -> 108000 | AD36: 0 | AE36: 6 | AF36: =18000*AE36 -> 108000 | AG36: 0 | AH36: 0 | AI36: =sum(AD36,AF36,AH36) -> 108000 | AJ36: =vlookup(A36,'セッション実施状況管理'!$A:$AH,26,false) -> 45511
A37: 30 | B37: みよしゆうき | E37: ふみや | F37: C組 | G37: ふみや | H37: 45441 | I37: 6月上旬 | K37: =P37 -> 18000 | L37: 45637 | M37: 清原三和子_6 | N37: - | O37: 0 | P37: 18000 | Q37: 0 | R37: 18000 | S37: 0 | T37: 18000 | U37: 0 | V37: 18000 | W37: 0 | X37: 18000 | Y37: 0 | Z37: 18000 | AA37: 0 | AC37: =sum(N37:AA37) -> 108000 | AD37: 0 | AE37: 6 | AF37: =18000*AE37 -> 108000 | AG37: 0 | AH37: 0 | AI37: =sum(AD37,AF37,AH37) -> 108000 | AJ37: =vlookup(A37,'セッション実施状況管理'!$A:$AH,26,false) -> 45498
A38: 31 | B38: すずきかおり | E38: ハマコ | F38: A組 | G38: ハマコ | H38: 45458 | I38: 7月上旬 | K38: =P38 -> 18000 | L38: 180 | M38: 野村佑佳_6 | N38: - | O38: 0 | P38: 18000 | Q38: 0 | R38: 18000 | S38: 0 | T38: 18000 | U38: 0 | V38: 18000 | W38: 0 | X38: 18000 | Y38: 0 | Z38: 18000 | AA38: 0 | AC38: =sum(N38:AA38) -> 108000 | AD38: 0 | AE38: 6 | AF38: =18000*AE38 -> 108000 | AG38: 0 | AH38: 0 | AI38: =sum(AD38,AF38,AH38) -> 108000 | AJ38: =vlookup(A38,'セッション実施状況管理'!$A:$AH,26,false) -> 45573
A39: 32 | B39: きたがわあやの | E39: 駒居 | F39: H組 | G39: 駒居 | K39: =P39 | L39: =K39+180 -> 180
A40: 33 | B40: さんのうたかひろ | E40: 村松 | F40: H組 | G40: 村松 | H40: 45510 | I40: 8月下旬 | K40: =P40 | L40: =K40+180 -> 180
A41: 34 | B41: かどたゆきこ | E41: ノア | F41: D組 | G41: ノア | H41: 45515 | I41: 8月下旬 | K41: =P41 | L41: =K41+180 -> 180 | M41: 清原三和子_7
A42: 35 | B42: まつもとたくみ | E42: ノア | F42: F組 | G42: ノア | H42: 45517 | I42: 8月下旬 | K42: =P42 | L42: =K42+180 -> 180 | M42: 中村恵理_3
A43: 36 | B43: にしむらゆうの | E43: ノア | F43: E組 | G43: ノア | H43: 45518 | I43: 45543 | J43: 45522 | K43: =P43 | L43: =K43+180 -> 180 | M43: 小針彩乃_1
A44: 37 | B44: やまもとゆり | E44: ゆう | F44: E組 | G44: ゆう | H44: 45523 | I44: 45542 | K44: =P44 | L44: =K44+180 -> 180 | M44: 山見阪佳子_3
A45: 38 | B45: おばたみずき | E45: kei | F45: A組 | G45: kei | H45: 45532 | I45: 9月下旬 | K45: =P45 | L45: =K45+180 -> 180
A46: 39 | B46: い さちよ | E46: いとた | F46: D組 | G46: いとた | H46: 45534 | I46: 9月下旬 | K46: =P46 | L46: =K46+180 -> 180 | M46: 野村佑佳_7
A47: 40 | B47: ひぐちゆき | E47: けい | F47: D組 | G47: けい | K47: =P47 | L47: =K47+180 -> 180 | M47: 清原三和子_8
A48: 41
A49: 42 | K49: =P49 | L49: =K49+180 -> 180
A50: 43 | K50: =P50 | L50: =K50+180 -> 180
A51: 44 | K51: =P51 | L51: =K51+180 -> 180
A52: 45 | K52: =P52 | L52: =K52+180 -> 180
A53: 46 | K53: =P53 | L53: =K53+180 -> 180
A54: 47 | K54: =P54 | L54: =K54+180 -> 180
A55: 48 | K55: =P55 | L55: =K55+180 -> 180
A56: 49 | K56: =P56 | L56: =K56+180 -> 180
A57: 50 | K57: =P57 | L57: =K57+180 -> 180
A58: 51 | K58: =P58 | L58: =K58+180 -> 180
A59: 52 | K59: =P59 | L59: =K59+180 -> 180
A60: 53 | K60: =P60 | L60: =K60+180 -> 180
... A84: 77 | K84: =P84 | L84: =K84+180 -> 180

Sheet セッション実施状況管理
D1: nanami_movie_streaming
H2: 【コーチの皆さんへ共有】
H3: ①コーチング実施報告をするための集計に必要な情報を入力するシートです。セッション実施日を 「yyyy/mm/dd」の形式で入力してください。
H4: ②入力したデータを元に、セッション実施回数が「コミッション管理」のタブで自動集計されます。
B5: 合計： | C5: =counta(C11:C1028) -> 300
B6: 万垢達成率： | C6: =C7/C5*100 -> 9.3333333 | I6: コミットプランライト
B7: 万垢達成数： | C7: =COUNTIF(C11:C310,1)+COUNTIF(C11:C310,2) -> 28 | I7: https://docs.google.com/spreadsheets/d/1M0bfbCkULbFtvyCbAFnaiyuW9oN4kZkqfVYrhonlE5A/edit?gid=1649866131#gid=1649866131
B8: 卒業生数： | C8: =COUNTIF(B11:B311, "卒業") -> 82 | W8: 1ヶ月目 | Y8: 2ヶ月目 | AA8: 3ヶ月目 | AC8: 4ヶ月目 | AE8: 5ヶ月目 | AG8: 6ヶ月目
B9: 在学中： | C9: =countif(B11:B1028,"在学中") -> 194 | F9: 卒業時まで更新 | J9: ƒƒ | L9: 旧カリキュラム | S9: ▼最終日報提出日 | V9: ▼初回セッション | W9: ▼通常セッション（セッション完了→ピンクセルに変更・生徒の無断キャンセル=日付を入れて、セルを青に）
A10: no. | B10: status | C10: 万垢 | D10: 合計アクション数 | E10: 投稿開始時投稿数 | F10: 表示投稿数 | G10: 投稿数 | H10: 生徒名 | I10: user ID | J10: 生徒ページ | K10: 講師 | L10: クラス名 | M10: メンター | N10: 生徒の入会日 | O10: 講義スタート日 | P10: 面談日 | Q10: SP開始日 | R10: 1回目通常セッション | S10: 最終サポート日 | T10: 担当MG名 | U10: 列 1 | V10: 0 | W10: 1 | X10: 2 | Y10: 3 | Z10: 4 | AA10: 5 | AB10: 6 | AC10: 7 | AD10: 8 | AE10: 9 | AF10: 10 | AG10: 11 | AH10: 12 | AI10: 最終サポート日数
A11: 1 | B11: 例外 | C11: 0 | D11: 0 | E11: 0 | F11: 5 | G11: =F11-E11 -> 5 | H11: おのまこと | I11: koji_no_chie | J11: https://www.notion.so/f-737444a6e90e4062b518aa81f931d776?pvs=4 | K11: 駒居 | L11: F組 | M11: 駒居 | N11: 45242 | O11: 45255 | P11: - | Q11: - | R11: =W11 -> 45273 | S11: - | T11: 宮田友理 | U11: 1 | V11: 45259 | W11: 45273 | X11: 45287 | Y11: 45302 | Z11: 45316 | AA11: 45338 | AB11: 休会 | AI11: =IF(COUNT(AH12,V12)=2, AH12-V12, "") -> 220
A12: 2 | B12: 卒業 | C12: 1 | D12: 198 | E12: 0 | F12: 123 | G12: =F12-E12 -> 123 | H12: ただゆうすけ | I12: cya_kurashi | J12: https://www.notion.so/f-6bc9cdd93a074de893311d8592e4ea8f?pvs=4 | K12: 駒居 | L12: F組 | M12: 駒居 | N12: 45246 | O12: 45255 | P12: - | Q12: - | R12: =W12 -> 45280 | S12: =R12+180 -> 45460 | T12: 中村恵理 | U12: 1 | V12: 45260 | W12: 45280 | X12: 45305 | Y12: 45326 | Z12: 45335 | AA12: 45350 | AB12: 45364 | AC12: 45392 | AD12: 45412 | AE12: 45426 | AF12: 45445 | AG12: 45459 | AH12: 45480 | AI12: =AH12-V12 -> 220
A13: 3 | B13: 卒業 | C13: 0 | D13: 41 | E13: 0 | F13: - | G13: =F13-E13 -> #VALUE! | H13: ふじたなな | I13: ta_ma_diet | J13: https://www.notion.so/g-f905aeb65a5b41d2bd8e8e578a505b09?pvs=4 | K13: 駒居 | L13: G組 | M13: 駒居 | N13: 45258 | O13: 45271 | P13: 45625 | R13: =W13 -> 45275 | S13: =R13+180 -> 45455 | T13: 森本風花 | U13: 1 | V13: 45263 | W13: 45275 | X13: 45304 | Y13: 45315 | Z13: 45331 | AA13: 45350 | AB13: 45357 | AC13: 45372 | AD13: 45385 | AE13: 45406 | AF13: 45420 | AG13: 45435 | AH13: 45449 | AI13: =AH13-V13 -> 186
A14: 4 | B14: 卒業 | C14: 0 | D14: 74 | E14: 0 | F14: 24 | G14: =F14-E14 -> 24 | H14: よしだむつみ | I14: adhd_nao | J14: https://www.notion.so/g-bb484bedf0da44c3a9204e56c3708820?pvs=4 | K14: 駒居 | L14: G組 | M14: 駒居 | N14: 45270 | O14: 45271 | P14: 45637 | R14: =W14 -> 45286 | S14: =R14+180 -> 45466 | T14: 野村佑佳 | U14: 1 | V14: 45279 | W14: 45286 | X14: 45293 | Y14: 45307 | Z14: 45321 | AA14: 45335 | AB14: 45349 | AC14: 45363 | AD14: 45377 | AE14: 45391 | AF14: 45405 | AG14: 45447 | AH14: 45461 | AI14: =AH14-V14 -> 182
A15: 5 | B15: 卒業 | C15: 0 | D15: 119 | E15: 0 | F15: 6 | G15: =F15-E15 -> 6 | H15: きたがわたかひろ | I15: kcc_0113 | J15: https://www.notion.so/A-48b87799aff1416cbb3a1970912131a3?pvs=4 | K15: けい | L15: A組 | M15: けい | N15: 45298 | O15: 45310 | P15: 45298 | R15: =W15 -> 44950 | S15: =R15+180 -> 45130 | T15: 豊榮信江 | U15: 1 | V15: 45301 | W15: 44950 | X15: 45329 | Y15: 45343 | Z15: 45369 | AA15: 45380 | AB15: 45401 | AC15: 45408 | AD15: 45422 | AE15: 45439 | AF15: 45470 | AG15: 45487 | AH15: 45492 | AI15: =AH15-V15 -> 191
A16: 6 | B16: 卒業 | C16: 2 | D16: 539 | E16: 0 | F16: 113 | G16: =F16-E16 -> 113 | H16: ありやまゆうな | I16: uni_beer_ | J16: https://www.notion.so/h-2df374753777409caed7a8803b749bdc | K16: 駒居 | L16: H組 | M16: 駒居 | N16: 45298 | O16: 45320 | P16: 45298 | R16: =W16 -> 45336 | S16: =R16+180 -> 45516 | T16: 野村佑佳 | U16: 2 | V16: 45301 | W16: 45336 | X16: 45350 | Y16: 45370 | Z16: 45384 | AA16: 45398 | AB16: 45411 | AC16: 45426 | AD16: 45442 | AE16: 45455 | AF16: 45469 | AG16: 45483 | AH16: 45588 | AI16: =AH16-V16 -> 287
A17: 7 | B17: 卒業 | C17: 0 | D17: 17 | E17: 0 | F17: - | G17: =F17-E17 -> #VALUE! | H17: たけにしゆかり | I17: yukari_dekirumon | J17: https://www.notion.so/H-a94b7996758f4e3c9ddb2a8211a4098c?pvs=4 | K17: 駒居 | L17: H組 | M17: 駒居 | N17: 45299 | O17: 45320 | P17: 45299 | R17: =W17 -> 45323 | S17: =R17+180 -> 45503 | T17: 宮田友理 | U17: 2 | V17: 45301 | W17: 45323 | X17: 45337 | Y17: 45350 | Z17: 45376 | AA17: 45390 | AB17: 45406 | AC17: 45420 | AD17: 45434 | AE17: 45448 | AF17: 45464 | AG17: 45474 | AH17: 45489 | AI17: =AH17-V17 -> 188
A18: 8 | B18: 卒業 | C18: 0 | D18: 81 | E18: 0 | F18: - | G18: =F18-E18 -> #VALUE! | H18: くどうゆみこ | I18: くどうゆみこ | J18: https://www.notion.so/C-1b937693667844edb42ba0b3f91eb95a | K18: しらゆき | L18: D組 | M18: しらゆき | N18: 45313 | O18: 2月上旬 | P18: 45315 | R18: =W18 -> 45341 | S18: =R18+180 -> 45521 | T18: 野村佑佳 | U18: 3 | V18: 45322 | W18: 45341 | X18: 45355 | Y18: 45369 | Z18: 45390 | AA18: 45404 | AB18: 45418 | AC18: 45432 | AD18: 45446 | AE18: 45460 | AF18: 45474 | AG18: 45489 | AH18: 45509 | AI18: =AH18-V18 -> 187
A19: 9 | B19: 卒業 | C19: 0 | D19: 247 | E19: 0 | F19: 51 | G19: =F19-E19 -> 51 | H19: たわらかずみ | I19: negi_mamalife | J19: https://www.notion.so/H-6c47c382fb41416bb5398a08d0efa69a?pvs=4 | K19: ソウタ | L19: H組 | M19: いとた | N19: 45314 | O19: 2月上旬 | P19: 45315 | R19: =W19 -> 45335 | S19: =R19+180 -> 45515 | T19: 中村恵理 | U19: 2 | V19: 45319 | W19: 45335 | X19: 45349 | Y19: 45373 | Z19: 45387 | AA19: 45401 | AB19: 45411 | AC19: 45425 | AD19: 45444 | AE19: 45456 | AF19: 45469 | AG19: 45483 | AH19: 45511 | AI19: =AH19-V19 -> 192
A20: 10 | B20: 卒業 | C20: 0 | D20: 276 | E20: 0 | F20: 209 | G20: 103 | H20: やまぐちしんいちろう | I20: tewofuru_woodjewelry | J20: https://www.notion.so/h-4ee1213842f34a8abc522b1b681bf0a8?pvs=4 | K20: ソウタ | L20: H組 | M20: いとた | N20: 45317 | O20: 2月上旬 | P20: 45319 | R20: =W20 -> 45334 | S20: =R20+180 -> 45514 | T20: 森本風花 | U20: 2 | V20: 45324 | W20: 45334 | X20: 45348 | Y20: 45362 | Z20: 45375 | AA20: 45389 | AB20: 45403 | AC20: 45417 | AD20: 45431 | AE20: 45445 | AF20: 45459 | AG20: 45473 | AH20: 45494 | AI20: =AH20-V20 -> 170
A21: 11 | B21: 卒業 | C21: 0 | D21: 252 | E21: 0 | F21: 24 | G21: =F21-E21 -> 24 | H21: かわかみまさと | I21: satojitan_recipe | J21: https://www.notion.so/C-4f2fdb58942d4be1b66b12e294a78cce | K21: しらゆき | L21: C組 | M21: しらゆき | N21: 45320 | O21: 2月上旬 | P21: 45320 | R21: =W21 -> 45340 | S21: =R21+180 -> 45520 | T21: 野村佑佳 | U21: 4 | V21: 45326 | W21: 45340 | X21: 45354 | Y21: 45368 | Z21: 45389 | AA21: 45408 | AB21: 45415 | AC21: 45431 | AD21: 45444 | AE21: 45459 | AF21: 45472 | AG21: 45488 | AH21: 45507 | AI21: =AH21-V21 -> 181
A22: 12 | B22: 卒業 | C22: 0 | D22: 188 | E22: 0 | F22: 84 | G22: 18 | H22: すどうえり | I22: richan_hair | J22: https://www.notion.so/h-75b166b01bdd4a7dab2f816f840c40f6?pvs=4 | K22: ソウタ | L22: H組 | M22: いとた | N22: 45320 | O22: 2月上旬 | P22: 45320 | R22: =W22 -> 45334 | S22: =R22+180 -> 45514 | T22: 宮田友理 | U22: 3 | V22: 45324 | W22: 45334 | X22: 45343 | Y22: 45369 | Z22: 45400 | AA22: 45411 | AB22: 45441 | AC22: 45460 | AD22: 45471 | AE22: 45485 | AF22: 45504 | AG22: 45526 | AH22: 45539 | AI22: =AH22-V22 -> 215
A23: 13 | B23: 卒業 | C23: 0 | D23: 116 | E23: 0 | F23: 24 | G23: =F23-E23 -> 24 | H23: なかのあや | I23: aya_travel_europe | J23: https://www.notion.so/C-18ef10444b5245ea9a00a9fa9f6aa26f?pvs=4 | K23: しらゆき | L23: C組 | M23: しらゆき | N23: 45325 | O23: 2月上旬 | P23: 45325 | R23: =W23 -> 45347 | S23: =R23+180 -> 45527 | T23: 清原三和子 | U23: 1 | V23: 45332 | W23: 45347 | X23: 45361 | Y23: 45374 | Z23: 45388 | AA23: 45403 | AB23: 45416 | AC23: 45430 | AD23: 45444 | AE23: 45458 | AF23: 45486 | AG23: 45507 | AH23: 45519 | AI23: =AH23-V23 -> 187
A24: 14 | B24: 卒業 | C24: 1 | D24: 285 | E24: 0 | F24: 100 | G24: =F24-E24 -> 100 | H24: うちだあやみ | I24: uchiko_gohan | J24: https://www.notion.so/B-daf8c007896a46c19df1d51b7331b579?pvs=4 | K24: けいいち | L24: B組 | M24: けいいち | N24: 45326 | O24: 2月中旬 | P24: 45326 | R24: =W24 -> 45346 | S24: =R24+180 -> 45526 | T24: 清原三和子 | U24: 2 | V24: 45332 | W24: 45346 | X24: 45360 | Y24: 45374 | Z24: 45388 | AA24: 45403 | AB24: 45416 | AC24: 45434 | AD24: 45444 | AE24: 45458 | AF24: 45472 | AG24: 45484 | AH24: 45500 | AI24: =AH24-V24 -> 168
A25: 15 | B25: 卒業 | C25: 0 | D25: 250 | E25: 0 | F25: 99 | G25: =F25-E25 -> 99 | H25: さかもとなみこ | I25: hiroyukichan_renai | J25: https://www.notion.so/A-30616aeef36d46609bace7715472cba9 | K25: ふみや | L25: A組 | M25: ふみや | N25: 45328 | O25: 45335 | P25: 45328 | R25: =W25 -> 45340 | S25: =R25+180 -> 45520 | T25: 山見阪佳子 | U25: 1 | V25: 45333 | W25: 45340 | X25: 45353 | Y25: 45371 | Z25: 202403/30 | AA25: 45403 | AB25: 45409 | AC25: 45431 | AD25: 45444 | AE25: 45456 | AF25: 45472 | AG25: 45487 | AH25: 45494 | AI25: =AH25-V25 -> 161
A26: 16 | B26: 卒業 | C26: 0 | D26: 211 | E26: 0 | F26: 138 | G26: 64 | H26: あいざわくみこ | I26: okumi_mind | J26: https://www.notion.so/A-49f636e8bc784058b509202e308d986d?pvs=4 | K26: ふみや | L26: A組 | M26: ふみや | N26: 45328 | O26: 2月中旬 | P26: 45328 | R26: =W26 -> 45351 | S26: =R26+180 -> 45531 | T26: 清原三和子 | U26: 3 | V26: 45337 | W26: 45351 | X26: 45353 | Y26: 45372 | Z26: 45384 | AA26: 2024/0416 | AB26: 45412 | AC26: 45429 | AD26: 45440 | AE26: 45454 | AF26: 45467 | AG26: 45481 | AH26: 45496 | AI26: =AH26-V26 -> 159
A27: 17 | B27: 卒業 | C27: 0 | D27: 0 | E27: 0 | F27: 78 | G27: =F27-E27 -> 78 | H27: よこやまあいと | I27: satousanni_kokuhaku | J27: https://www.notion.so/B-53dabe8f44d94a4cb15a265041355304?pvs=4 | K27: ふみや | L27: B組 | M27: ふみや | N27: 45330 | O27: 2月中旬 | P27: 45330 | R27: =W27 -> 45360 | S27: =R27+180 -> 45540 | T27: 福田康裕 | U27: 1 | V27: 45335 | W27: 45360 | X27: 45381 | Y27: 45423 | Z27: 45445 | AA27: 45459 | AB27: 45473 | AC27: 45487 | AD27: 45508 | AE27: 45522 | AF27: 45536 | AG27: 45550 | AH27: 45560 | AI27: =AH27-V27 -> 225
A28: 18 | B28: 卒業 | C28: 0 | D28: 0 | E28: 0 | F28: 14 | G28: =F28-E28 -> 14 | H28: ふちがみあや | I28: aya_zubora | J28: https://www.notion.so/c7b88ab6a5674a1cb0260e9c208c019a | K28: ふみや | L28: B組 | M28: ふみや | N28: 45330 | O28: 2月中旬 | P28: 45330 | R28: =W28 -> 45350 | S28: =R28+180 -> 45530 | T28: 山見阪佳子 | U28: 2 | V28: 45336 | W28: 45350 | X28: 45366 | Y28: 45379 | Z28: 45397 | AA28: 45413 | AB28: 45441 | AC28: 45455 | AD28: 45468 | AE28: 45480 | AF28: 45495 | AG28: 45510 | AH28: 45525 | AI28: =AH28-V28 -> 189
A29: 19 | B29: 卒業 | C29: 0 | D29: 0 | E29: 154 | F29: 166 | H29: おおにしちかこ | I29: ginza_arch | J29: https://www.notion.so/J-87189eeb81284fd2af9b7cedea12687b?pvs=4 | K29: ソウタ | L29: J組 | M29: ハム | N29: 45347 | O29: 3月上旬〜中旬 | P29: 45348 | R29: =W29 -> 45412 | S29: =R29+180 -> 45592 | T29: 須見浩人 | U29: 1 | V29: 45353 | W29: 45412 | X29: 45435 | Y29: 45461 | Z29: 45481 | AA29: 45495 | AB29: 45505 | AC29: 45519 | AD29: 45543 | AE29: 45561 | AF29: 45575 | AG29: 45613 | AH29: 45630 | AI29: =AH29-V29 -> 277
A30: 20 | B30: 卒業 | C30: 1 | D30: 212 | E30: 0 | F30: 37 | H30: すだはるき | I30: haru_room100 | J30: https://www.notion.so/E-8f23d32f1f464421991d9ed8f6f8752d?pvs=4 | K30: 村松 | L30: E組 | M30: 村松 | N30: 45385 | O30: 4月下旬 | P30: 45385 | R30: =W30 -> 45414 | S30: =R30+180 -> 45594 | T30: 須見浩人 | U30: 2 | V30: 45402 | W30: 45414 | X30: 45443 | Y30: 45456 | Z30: 45477 | AA30: 45491 | AB30: 45513 | AC30: 45527 | AD30: 45541 | AE30: 45556 | AF30: 45572 | AG30: 45587 | AH30: 45602 | AI30: =AH30-V30 -> 200
A31: 21 | B31: 卒業 | C31: 0 | D31: 532 | E31: 0 | F31: 86 | H31: かしはらせつみ | I31: sena_bilife | J31: https://www.notion.so/L-b1b7515bcbb645c391931bdc154d8154?pvs=4 | K31: ソウタ | L31: L組 | M31: 村松 | N31: 45392 | O31: 4月下旬 | P31: 45392 | R31: =W31 -> 45406 | S31: =R31+180 -> 45586 | T31: 宮田友理 | U31: 4 | V31: 45398 | W31: 45406 | X31: 45420 | Y31: 45434 | Z31: 45455 | AA31: 45462 | AB31: 45485 | AC31: 45491 | AD31: 45505 | AE31: 45520 | AF31: 45532 | AG31: 45553 | AH31: 音信不通 | AI31: =AH31-V31 -> #VALUE!
A32: 22 | B32: 卒業 | C32: 1 | D32: 529 | E32: 0 | F32: 193 | H32: ながおあみり | I32: amiri_instastory | J32: https://www.notion.so/f-0cccca78988d43189901752f176bbefb | K32: 村松 | L32: F組 | M32: 村松 | N32: 45409 | O32: 5月中旬 | P32: 45410 | R32: =W32 -> 45435 | S32: =R32+180 -> 45615 | T32: 野村佑佳 | U32: 5 | V32: 45420 | W32: 45435 | X32: 45463 | Y32: 45477 | Z32: 45491 | AA32: 45512 | AB32: 45525 | AC32: 45540 | AD32: 45554 | AE32: 45568 | AF32: 45582 | AG32: 45602 | AH32: 45625 | AI32: =AH32-V32 -> 205
A33: 23 | B33: 卒業 | C33: 1 | D33: 422 | E33: 0 | F33: 76 | H33: こばやしはるか | I33: elu_excel.teiji | J33: https://www.instagram.com/elu_excel.teiji?utm_source=ig_web_button_share_sheet&igsh=ZDNlZDc0MzIxNw== | K33: 村松 | L33: F組 | M33: 村松 | N33: 45411 | O33: 5月中旬 | P33: 45414 | R33: =W33 -> 45449 | S33: =R33+180 -> 45629 | T33: 清原三和子 | U33: 4 | V33: 45423 | W33: 45449 | X33: 45463 | Y33: 45477 | Z33: 45491 | AA33: 45506 | AB33: 45526 | AC33: 45539 | AD33: 45554 | AE33: 45568 | AF33: 45580 | AG33: 45608 | AH33: 45625 | AI33: =AH33-V33 -> 202
A34: 24 | B34: 音不 | C34: 0 | D34: 0 | E34: 0 | H34: じょうどじゆうき | I34: じょうどじゆうき | K34: けいいち | L34: C組 | M34: けいいち | N34: 45429 | O34: 6月上旬 | P34: 45429 | R34: =W34 -> 45459 | S34: =R34+180 -> 45639 | T34: 福田康裕 | U34: 2 | V34: 45436 | W34: 45459 | X34: 45511 | AI34: =AH34-V34 -> -45436
A35: 25 | B35: 例外 | C35: 0 | D35: 0 | E35: 0 | H35: たなかゆりか | I35: たなかゆりか | K35: けいいち | L35: C組 | M35: けいいち | N35: 45430 | O35: 6月上旬 | P35: 45433 | R35: =W35 -> 45437 | S35: =R35+180 -> 45617 | T35: 清原三和子 | U35: 5 | V35: 45437 | W35: 45437 | AI35: =AH35-V35 -> -45437
A36: 26 | B36: 卒業 | C36: 0 | D36: 296 | E36: 0 | F36: 15 | H36: かわしま あらし | I36: fuui_guitar | J36: https://www.notion.so/_-G-8a956a5fe49943a582abe0647e358088?pvs=4 | K36: 村松 | L36: G組 | M36: 村松 | N36: 45434 | O36: 6月上旬 | P36: 45435 | R36: =W36 -> 45454 | S36: =R36+180 -> 45634 | T36: 森本風花 | U36: 3 | V36: 45441 | W36: 45454 | X36: 45469 | Y36: 45483 | Z36: 45496 | AA36: 45509 | AB36: 45525 | AC36: 45539 | AD36: 45553 | AE36: 45567 | AF36: 45581 | AG36: 45595 | AH36: 45623 | AI36: =AH36-V36 -> 182
A37: 27 | B37: 音不 | C37: 0 | D37: 0 | E37: 0 | H37: せきおかまさき | I37: せきおかまさき | J37: https://www.instagram.com/maxa.san1012?utm_source=ig_web_button_share_sheet&igsh=ZDNlZDc0MzIxNw== | K37: ふみや | L37: C組 | M37: ふみや | N37: 45438 | O37: 6月上旬 | P37: 45439 | R37: =W37 -> 45445 | S37: =R37+180 -> 45625 | T37: 福田康裕 | U37: 3 | V37: 45445 | W37: 45445 | AI37: =AH37-V37 -> -45445
A38: 28 | B38: 卒業 | C38: 0 | D38: 201 | E38: 0 | F38: 1 | H38: しらどうさき | I38: shirasaki_happylife | J38: https://www.notion.so/H-e9118b5dfb1f457190e1445e8dd95a10?pvs=4 | K38: 村松 | L38: H組 | M38: ゆり | N38: 45440 | O38: 45526 | P38: 45511 | R38: =W38 -> 45527 | S38: =R38+180 -> 45707 | T38: 宮田友理 | U38: 6 | V38: 45517 | W38: 45527 | X38: 45539 | Y38: 45568 | Z38: 45582 | AA38: 45596 | AB38: 45610 | AC38: 45625 | AD38: 45638 | AE38: 45653 | AF38: 45670 | AG38: 45680 | AH38: 45702 | AI38: =AH38-V38 -> 185
A39: 29 | B39: 卒業 | C39: 1 | D39: 443 | E39: 0 | F39: 79 | H39: まさきちさと | I39: hachi.footcare | J39: https://www.notion.so/C-bea817e079364bfca66194d09a437660?pvs=4 | K39: ふみや | L39: C組 | M39: ふみや | N39: 45440 | O39: 6月上旬 | P39: 45441 | R39: =W39 -> 45463 | S39: =R39+180 -> 45643 | T39: 宮田友理 | U39: 5 | V39: 45447 | W39: 45463 | X39: 45481 | Y39: 45495 | Z39: 45511 | AA39: 45526 | AB39: 45540 | AC39: 45554 | AD39: 45569 | AE39: 45593 | AF39: 45610 | AG39: 45622 | AH39: 45636 | AI39: =AH39-V39 -> 189
A40: 30 | B40: 卒業 | C40: 0 | D40: 301 | E40: 0 | F40: 110 | G40: 9 | H40: みよしゆうき | I40: yupi_nariagaru | J40: https://www.instagram.com/yupi_nariagaru?utm_source=ig_web_button_share_sheet&igsh=ZDNlZDc0MzIxNw== | K40: ふみや | L40: C組 | M40: ふみや | N40: 45441 | O40: 6月上旬 | P40: 45442 | R40: =W40 -> 45457 | S40: =R40+180 -> 45637 | T40: 清原三和子 | U40: 6 | V40: 45449 | W40: 45457 | X40: 45468 | Y40: 45481 | Z40: 45498 | AA40: 45511 | AB40: 45525 | AC40: 45537 | AD40: 45553 | AE40: 45582 | AF40: 45593 | AG40: 45610 | AH40: 45624 | AI40: =AH40-V40 -> 175
A41: 31 | B41: 卒業 | C41: 0 | D41: 308 | E41: 0 | H41: すずきかおり | I41: ryo_life_reset | J41: https://www.notion.so/A-25281dca07c446008215c786f962bce8 | K41: ハマコ | L41: A組 | M41: ハマコ | N41: 45458 | O41: 7月上旬 | P41: 45458 | R41: =W41 -> 45496 | S41: =R41+180 -> 45676 | T41: 野村佑佳 | U41: 6 | V41: 45468 | W41: 45496 | X41: 45538 | Y41: 45559 | Z41: 45573 | AA41: 45587 | AB41: 45601 | AC41: 45629 | AD41: 45643 | AE41: 45664 | AF41: 45685 | AG41: 45700 | AH41: 45714 | AI41: =AH41-V41 -> 246
A42: 32 | B42: 卒業 | C42: 0 | D42: 70 | E42: 0 | F42: 57 | H42: きたがわあやの | I42: balabo_style_40 | J42: https://www.notion.so/_-h-35951262685743398d81dfd46366359d?pvs=4 | K42: 駒居 | L42: H組 | M42: 駒居 | P42: 45484 | R42: =W42 -> 45482 | S42: =R42+60 -> 45542 | T42: 森本風花 | U42: 4 | V42: 45482 | W42: 45482 | X42: 45496 | Y42: 45498 | Z42: 45509 | AA42: 45527 | AI42: =AH42-V42 -> -45482
A43: 33 | B43: 例外 | C43: 0 | D43: 9 | E43: 0 | F43: - | H43: さんのうたかひろ | I43: さんのうたかひろ | J43: https://www.notion.so/_-h-b9b593723c3d4ec0af9d76f2b7402c27?pvs=4 | K43: 村松 | L43: H組 | M43: 村松 | N43: 45510 | O43: 8月下旬 | P43: 45511 | R43: 45511 | S43: =R43+180 -> 45691 | T43: 森本風花 | U43: 5 | V43: 45518 | W43: 45532 | X43: 45547 | Y43: 45561 | AI43: =AH43-V43 -> -45518
A44: 34 | B44: 音不 | C44: 0 | D44: 43 | E44: 0 | H44: かどたゆきこ | I44: katherine_kadota | J44: https://www.instagram.com/katherine_kadota/ | K44: ノア | L44: D組 | M44: ノア | N44: 45515 | O44: 8月下旬 | P44: 45517 | R44: 45537 | S44: =R44+180 -> 45717 | T44: 清原三和子 | U44: 7 | V44: 45523 | W44: 45537 | X44: 45558 | Y44: 45572 | Z44: 45586 | AA44: 45600 | AB44: 45614 | AC44: 45628 | AD44: 45642 | AE44: 45670 | AF44: 45684 | AG44: 45698 | AH44: 45712 | AI44: =AH44-V44 -> 189
A45: 35 | B45: 卒業 | C45: 0 | D45: 139 | E45: 0 | H45: まつもとたくみ | I45: まつもとたくみ | J45: https://www.notion.so/F-10b62de8b68741299406e4152569f7b7?pvs=4 | K45: ノア | L45: F組 | M45: ノア | N45: 45517 | O45: 8月下旬 | P45: 45518 | R45: 45518 | S45: =R45+180 -> 45698 | T45: 中村恵理 | U45: 3 | V45: 45528 | W45: 45544 | X45: 45563 | Y45: 45577 | Z45: 45595 | AA45: 45605 | AB45: 45619 | AC45: 45633 | AD45: 46012 | AE45: 45665 | AF45: 2025/01/19無断欠席1回消化ご本人に連絡済み | AI45: =AH45-V45 -> -45528
A46: 36 | B46: 卒業 | C46: 0 | D46: 89 | E46: 0 | H46: にしむらゆうの | I46: nomuuno_kurashi | J46: https://www.notion.so/E-da1c3a3c12ac4fed8eedeb5cdba4e3af?pvs=4 | K46: ノア | L46: E組 | M46: ノア | N46: 45518 | O46: 45543 | P46: 45522 | R46: 45544 | S46: =R46+180 -> 45724 | T46: 小針彩乃 | U46: 1 | V46: 45531 | W46: 45544 | X46: 45558 | Y46: 45572 | Z46: 45586 | AA46: 45596 | AB46: 45614 | AC46: 45627 | AD46: 45283 | AE46: 45663 | AF46: 45677 | AG46: 45691 | AH46: 45708 | AI46: =AH46-V46 -> 177
A47: 37 | B47: 卒業 | C47: 2 | D47: 96 | E47: 0 | H47: やまもとゆり | I47: yururi_ikuji | J47: https://www.notion.so/E-ccdda3541c9f4dcd9854543e2a2e7db5 | K47: ゆう | L47: E組 | M47: ゆう | N47: 45523 | O47: 45542 | P47: 45525 | R47: 45525 | S47: =R47+180 -> 45705 | T47: 山見阪佳子 | U47: 3 | V47: 45532 | W47: 45546 | X47: 45560 | Y47: 45573 | Z47: 45588 | AA47: 45602 | AB47: 45618 | AC47: 45630 | AD47: 45644 | AE47: 45665 | AF47: 45679 | AG47: 45693 | AH47: 45705 | AI47: =AH47-V47 -> 173
A48: 38 | B48: 卒業 | C48: 0 | D48: 54 | E48: 594 | F48: 594 | H48: おばたみずき | I48: hanako_okane | J48: https://www.notion.so/b515c503c3d34c819f31ec49ac36b6cb | K48: kei | L48: A組 | M48: kei | N48: 45532 | O48: 45554 | P48: 45534 | R48: =W48 -> 45559 | S48: =R48+180 -> 45739 | T48: 多田祐輔 | U48: 1 | V48: 45545 | W48: 45559 | X48: 45573 | Y48: 45587 | Z48: 45601 | AA48: 45615 | AB48: 45630 | AC48: 45643 | AD48: 45664 | AE48: 45681 | AF48: 45695 | AG48: 45708 | AH48: 45727 | AI48: =AH48-V48 -> 182
A49: 39 | B49: 卒業 | C49: 1 | D49: 81 | E49: 0 | H49: い さちよ | I49: sachi_marathon | J49: https://www.notion.so/5f6422771ad04d888beaf27df2e1b58d | K49: いとた | L49: D組 | M49: いとた | N49: 45534 | O49: 9月下旬 | P49: 45534 | R49: =W49 -> 45575 | S49: =R49+180 -> 45755 | T49: 野村佑佳 | U49: 7 | V49: 45548 | W49: 45575 | X49: 45586 | Y49: 45601 | Z49: 45610 | AA49: 45624 | AB49: 45638 | AC49: 46017 | AD49: 45666 | AE49: 45680 | AF49: 45694 | AG49: 45708 | AH49: 45743 | AI49: =AH49-V49 -> 195
A50: 40 | B50: 音不 | C50: 0 | D50: 64 | E50: 0 | H50: ひぐちゆき | I50: snow_kango | J50: https://www.notion.so/D-a2e1f37881bf4c309573caa5e56d0995?pvs=4 | K50: けい | L50: D組 | M50: けい | N50: 45542 | O50: 9月下旬 | P50: 45542 | R50: =W50 -> 45584 | S50: =R50+180 -> 45764 | T50: 清原三和子 | U50: 8 | V50: 45546 | W50: 45584 | X50: 45598 | Y50: 45612 | Z50: 45626 | AA50: 45640 | AB50: 45654 | AC50: 45668 | AD50: 45682 | AE50: 45696 | AF50: 45710 | AG50: 45724 | AH50: 45738 | AI50: =AH50-V50 -> 192
A51: 41 | B51: 音不 | C51: 0 | D51: 0 | E51: 0 | H51: つかだひさえ | I51: つかだひさえ | J51: https://www.notion.so/d-8d2da91b7a224ca08b5d234d9cffea00?pvs=4 | K51: けい | L51: D組 | M51: けい | N51: 45553 | O51: 9月下旬 | P51: 45554 | R51: =W51 -> 45615 | S51: =R51+180 -> 45795 | T51: 須見浩人 | U51: 3 | V51: 45565 | W51: 45615 | X51: 45640 | Y51: 45650 | Z51: 45668 | AA51: 45682 | AB51: 45696 | AI51: =AH51-V51 -> -45565
A52: 42 | B52: 卒業 | C52: 1 | D52: 0 | E52: 0 | H52: すがわらようこ | I52: Daily_Bag_Storie | J52: https://www.notion.so/D-dc713793f1db47eea9b66d169086ed12 | K52: フミヤ | L52: D組 | M52: フミヤ | N52: 45564 | O52: 10月中旬 | P52: 45564 | R52: =W52 -> 45591 | S52: =R52+180 -> 45771 | T52: 福田康裕 | U52: 4 | V52: 45568 | W52: 45591 | X52: 45626 | Y52: 45640 | Z52: 45672 | AA52: 45686 | AB52: 45700 | AC52: 45714 | AD52: 45728 | AE52: 45742 | AF52: 45756 | AG52: 45770 | AH52: 45784 | AI52: =AH52-V52 -> 216
A53: 43 | B53: 音不 | C53: 0 | D53: 0 | E53: 0 | H53: さかがみけいた | I53: tedori19.men | J53: https://www.notion.so/d301c23b9c184206a85c5b20793208aa | K53: フミヤ | L53: D組 | M53: フミヤ | N53: 45567 | O53: 45601 | P53: 45567 | R53: =W53 -> 45606 | S53: =R53+180 -> 45786 | T53: 多田祐輔 | U53: 2 | V53: 45585 | W53: 45606 | X53: 45622 | Y53: 45634 | Z53: 45648 | AA53: 45669 | AB53: 45691 | AC53: 45697 | AD53: 45714 | AE53: 45725 | AF53: 45752 | AI53: =AH53-V53 -> -45585
A54: 44 | B54: 卒業 | C54: 1 | D54: 0 | E54: 0 | H54: いけぐちはるか | I54: haru_bodymake_ | J54: https://www.notion.so/_-d-65e5c04ab54b40189649253e4df2d881?pvs=4 | K54: はむ | L54: D組 | M54: はむ | N54: 45568 | O54: 10月下旬 | P54: 45568 | R54: =W54 -> 45580 | S54: =R54+180 -> 45760 | T54: 森本風花 | U54: 6 | V54: 45571 | W54: 45580 | X54: 45633 | Y54: 45647 | Z54: 45664 | AA54: 45679 | AB54: 45691 | AC54: 45705 | AD54: 45719 | AE54: 45735 | AF54: 45750 | AG54: 45771 | AH54: 45792 | AI54: =AH54-V54 -> 221
A55: 45 | B55: 卒業 | C55: 0 | D55: 0 | E55: 0 | H55: ふじためぐみ | I55: megu_study_ | J55: https://www.notion.so/b-641d9434223d419db98f1d496c3a679e?pvs=4 | K55: マイ | L55: B組 | M55: マイ | N55: 45572 | O55: 11月上旬 | P55: 45574 | R55: =W55 -> 45615 | S55: =R55+180 -> 45795 | T55: 森本風花 | U55: 7 | V55: 45579 | W55: 45615 | X55: 45629 | Y55: 45643 | Z55: 45657 | AA55: 45671 | AB55: 45685 | AC55: 45702 | AD55: 45716 | AE55: 45733 | AF55: 45761 | AG55: 45775 | AH55: 45789 | AI55: =AH55-V55 -> 210
A56: 46 | B56: 卒業 | C56: 0 | D56: 0 | E56: 0 | H56: いしかわまい | I56: rio_kurahi_ | J56: https://www.notion.so/I-9c0078522d0748c788341ec5dea7be0b?pvs=4 | K56: 村松 | L56: I組 | M56: 村松 | N56: 45583 | O56: 11月上旬 | P56: 45584 | R56: =W56 -> 45609 | S56: =R56+180 -> 45789 | T56: 清原三和子 | U56: 9 | V56: 45590 | W56: 45609 | X56: 45623 | Y56: 45637 | Z56: 45650 | AA56: 45672 | AB56: 45685 | AC56: 45699 | AD56: 45712 | AE56: 45728 | AF56: 45740 | AG56: 45756 | AH56: 45769 | AI56: =AH56-V56 -> 179
A57: 47 | B57: 卒業 | C57: 0 | D57: 0 | E57: 0 | H57: なかじまえみ | I57: なかじまえみ | J57: https://www.notion.so/i-1bc07179157547f4b9d702972af2b48a?pvs=4 | K57: 村松 | L57: I組 | M57: 村松 | N57: 45586 | O57: 11月上旬 | P57: 45587 | R57: =W57 -> 45621 | S57: =R57+180 -> 45801 | T57: 須見浩人 | U57: 4 | V57: 45600 | W57: 45621 | X57: 45641 | Y57: 45655 | Z57: 45672 | AA57: 45686 | AB57: 45706 | AC57: 45720 | AD57: 45732 | AE57: 45746 | AF57: 45763 | AG57: 45767 | AH57: 45787 | AI57: =AH57-V57 -> 187
A58: 48 | B58: 卒業 | C58: 0 | E58: 35 | H58: やまだつかさ | I58: cbd_bao | J58: https://www.notion.so/D-3b6c59df4b114d669b74db023107cc72?pvs=4 | K58: フミヤ | L58: D組 | M58: フミヤ | N58: 45590 | O58: 45601 | P58: 45594 | R58: 45601 | S58: =R58+180 -> 45781 | T58: 小針彩乃 | U58: 2 | V58: 45601 | W58: 45617 | X58: 45628 | Y58: 45642 | Z58: 45670 | AA58: 45684 | AB58: 45698 | AC58: 45712 | AD58: 45726 | AE58: 45741 | AF58: 45754 | AG58: 45768 | AH58: 45784 | AI58: =AH58-V58 -> 183
A59: 49 | B59: 例外 | C59: 0 | E59: 0 | F59: 236 | H59: ななやまたえこ | I59: ななやまたえこ | J59: https://www.notion.so/B-ed1eed969194445d86ad8022dceb95ae?pvs=4 | K59: うちこ | L59: B組 | M59: うちこ | N59: 45597 | O59: 11月中旬 | P59: 45597 | R59: =W59 -> 45603 | S59: =R59+180 -> 45783 | T59: 清原三和子 | U59: 10 | V59: 45603 | W59: 45603 | AI59: =AH59-V59 -> -45603
A60: 50 | B60: 卒業 | C60: 0 | E60: 0 | H60: しもたかたにかな | I60: kana_and_english | J60: https://www.notion.so/B-6f377f96e51a485596554ec65ba68152 | K60: ハマコ | L60: B組 | M60: ハマコ | N60: 45597 | O60: 11月中旬 | P60: 45598 | R60: =W60 -> 45626 | S60: =R60+180 -> 45806 | T60: 山見阪佳子 | U60: 4 | V60: 45610 | W60: 45626 | X60: 45638 | Y60: 45652 | Z60: 45666 | AA60: 45682 | AB60: 2025//02/10 | AC60: 45708 | AD60: 45721 | AE60: 45736 | AF60: 45750 | AG60: 45768 | AH60: 45799 | AI60: =AH60-V60 -> 189
A61: 51 | B61: 卒業 | C61: 0 | E61: 0 | H61: たなかゆみこ | I61: yumimama_gohan | J61: https://www.notion.so/d-52958dcf551f4d548ed1d9b7801add0a | K61: りょう | L61: D組 | M61: りょう | N61: 45603 | O61: 11月中旬 | P61: 45601 | R61: =W61 -> 45622 | S61: =R61+180 -> 45802 | T61: 野村佑佳 | U61: 8 | V61: 45608 | W61: 45622 | X61: 45636 | Y61: 46015 | Z61: 45667 | AA61: 45681 | AB61: 45698 | AC61: 45713 | AD61: 45727 | AE61: 45741 | AF61: 45754 | AG61: 45769 | AH61: 45803 | AI61: =AH61-V61 -> 195
A62: 52 | B62: 卒業 | C62: 0 | E62: 0 | H62: こせきあゆみ | I62: nabeko_kurashi | J62: https://www.notion.so/C-4934cc32f16246bf9c17f61d608aced9?pvs=4 | K62: ボム | L62: C組 | M62: ボム | N62: 45603 | O62: 11月中旬 | P62: 45602 | R62: =W62 -> 45626 | S62: =R62+180 -> 45806 | T62: 森本風花 | U62: 8 | V62: 45612 | W62: 45626 | X62: 45640 | Y62: 45655 | Z62: 45668 | AA62: 45683 | AB62: 45696 | AC62: 45711 | AD62: 45724 | AE62: 45738 | AF62: 45753 | AG62: 45766 | AH62: 45788 | AI62: =AH62-V62 -> 176
A63: 53 | B63: 卒業 | C63: 1 | H63: わだよしろう | I63: dr.sora_ped | J63: https://www.notion.so/05b0670a8fef46ad929c317a19cd8f15 | K63: ボム | L63: B組 | M63: ボム | N63: 45605 | O63: 12月下旬 | P63: 45635 | R63: =W63 -> 45631 | S63: =R63+180 -> 45811 | T63: 野村佑佳 | U63: 9 | V63: 45617 | W63: 45631 | X63: 45645 | Y63: 45666 | Z63: 45683 | AA63: 45694 | AB63: 45709 | AC63: 45729 | AD63: 45744 | AE63: 45757 | AF63: 45771 | AG63: 45785 | AH63: 45799 | AI63: =AH63-V63 -> 182
A64: 54 | B64: 卒業 | C64: 1 | H64: こもりみちこ | I64: shiia_zubora_gohan | J64: https://www.notion.so/B-7835c0c6e57c470e9d51d28858d0347e | K64: はる | L64: B組 | M64: はる | N64: 45635 | O64: 12月下旬 | P64: 45635 | R64: =W64 -> 45656 | S64: =R64+180 -> 45836 | T64: 有山友菜 | U64: 1 | V64: 45644 | W64: 45656 | X64: 45671 | Y64: 45685 | Z64: 45698 | AA64: 45713 | AB64: 45727 | AC64: 45741 | AD64: 45757 | AE64: 45775 | AF64: 45791 | AG64: 45805 | AH64: 45825 | AI64: =AH64-V64 -> 181
A65: 55 | B65: 卒業 | C65: 0 | H65: にしじまなおこ | I65: nao_mamadiet_39 | J65: https://www.notion.so/B-c2536f991d444a9aa30b852520a2f3c6 | K65: まろ | L65: B組 | M65: まろ | N65: 45635 | O65: 12月下旬 | P65: 45635 | R65: =W65 -> 45667 | S65: =R65+180 -> 45847 | T65: 福田康裕 | U65: 5 | V65: 45647 | W65: 45667 | X65: 45679 | Y65: 45693 | Z65: 45707 | AA65: 45721 | AB65: 45735 | AC65: 45749 | AD65: 45763 | AE65: 45777 | AF65: 45791 | AG65: 45805 | AH65: 45819 | AI65: =AH65-V65 -> 172
A66: 56 | B66: 卒業 | C66: 2 | H66: あらききみえ | I66: aki157_diet | J66: https://www.notion.so/B-4792ce1202f14baabc2e903852c7c75b | K66: はる | L66: B組 | M66: はる | N66: 45638 | O66: 12月下旬 | P66: 45638 | R66: =W66 -> 45663 | S66: =R66+180 -> 45843 | T66: 鈴木久美子 | U66: 1 | V66: 45645 | W66: 45663 | X66: 45673 | Y66: =X66+14 -> 45687 | Z66: 45701 | AA66: =Z66+14 -> 45715 | AB66: =AA66+14 -> 45729 | AC66: =AB66+14 -> 45743 | AD66: 45757 | AE66: 45775 | AF66: 45790 | AG66: 45804 | AH66: 45818 | AI66: =AH66-V66 -> 173
A67: 57 | B67: 卒業 | C67: 0 | H67: しがあかね | I67: shiga_chan_diet | J67: https://www.notion.so/E-f1946969b0c449b7be3560171afcdf8b | K67: ゆな | L67: E組 | M67: ゆな | N67: 45637 | O67: 12月下旬 | P67: 45637 | R67: =W67 -> 45666 | S67: =R67+180 -> 45846 | T67: 有山友菜 | U67: 2 | V67: 45649 | W67: 45666 | X67: 45686 | Y67: 45700 | Z67: 45716 | AA67: 45729 | AB67: =AA67+14 -> 45743 | AC67: 45755 | AD67: 45771 | AE67: =AD67+14 -> 45785 | AF67: 45805 | AG67: =AF67+14 -> 45819 | AH67: 45839 | AI67: =AH67-V67 -> 190
A68: 58 | B68: 卒業 | C68: 2 | H68: ねもとみさ | I68: misa_sweets_diet | J68: https://www.notion.so/d-2d82f0e95316486a99c070cd6448447f?pvs=4 | K68: はる | L68: D組 | M68: はる | N68: 45665 | O68: 1月中旬 | P68: 45666 | R68: =W68 -> 45688 | S68: =R68+180 -> 45868 | T68: 長尾あみり | U68: 1 | V68: 45685 | W68: 45688 | X68: 45706 | Y68: 45720 | Z68: 45734 | AA68: 45748 | AB68: 45762 | AC68: 45777 | AD68: 45790 | AE68: 45804 | AF68: 45818 | AG68: 45833 | AH68: 45847 | AI68: =AH68-V68 -> 162
A69: 59 | B69: 卒業 | C69: 2 | H69: ふかくさゆか | I69: hana_diet.recipe | J69: https://www.notion.so/kenta-C-0e2a29fae6634e70b7d508fd67867a45?pvs=4 | K69: kenta | L69: C組 | M69: kenta | N69: 45962 | O69: 1月下旬 | P69: 45669 | R69: =W69 -> 45690 | S69: =R69+180 -> 45870 | T69: 須見浩人 | U69: 5 | V69: 45676 | W69: 45690 | X69: 45704 | Y69: 45718 | Z69: 45732 | AA69: 45746 | AB69: 45760 | AC69: 45774 | AD69: 45790 | AE69: 45803 | AF69: 45819 | AG69: 45840 | AH69: 45864 | AI69: =AH69-V69 -> 188
A70: 60 | B70: 卒業 | C70: 2 | H70: ごとうしんじ | I70: justin_inuformation | J70: https://www.notion.so/A-2a6aa8f57bc8456a9ff35efdf37a93a6?pvs=4 | K70: すい | L70: A組 | M70: すい | N70: 45675 | O70: 2月上旬 | P70: 45679 | R70: =W70 -> 45709 | S70: =R70+180 -> 45889 | T70: 森本風花 | U70: 9 | V70: 45690 | W70: 45709 | X70: 45722 | Y70: 45741 | Z70: 45755 | AA70: 45768 | AB70: 45790 | AC70: 45804 | AD70: 45817 | AE70: 45831 | AF70: 45845 | AG70: 45859 | AH70: 45875 | AI70: =AH70-V70 -> 185
A71: 61 | B71: 卒業 | C71: 0 | H71: こまつゆか | I71: yukappe_room | J71: https://www.notion.so/C-c5765b90ac81462e920e2c30395dacf3?pvs=4 | K71: えび | L71: C組 | M71: えび | N71: 45675 | O71: 2月上旬 | P71: 45678 | R71: =W71 -> 45714 | S71: =R71+180 -> 45894 | T71: 森本風花 | U71: 10 | V71: 45687 | W71: 45714 | X71: 45734 | Y71: 45748 | Z71: 45762 | AA71: 45775 | AB71: 45790 | AC71: 45804 | AD71: 45818 | AE71: 45832 | AF71: 45846 | AG71: 45859 | AH71: 45884 | AI71: =AH71-V71 -> 197
A72: 62 | B72: 卒業 | C72: 0 | H72: すがの ゆうた | I72: kuroko_book | J72: https://www.notion.so/f-f953cdc79bf246e9979c29f981ec677c?pvs=4 | K72: ふみや | L72: F組 | M72: ふみや | N72: 45679 | O72: 2月上旬 | P72: 45679 | R72: =W72 -> 45696 | S72: =R72+180 -> 45876 | T72: 森本風花 | U72: 11 | V72: 45685 | W72: 45696 | X72: 45710 | Y72: 45725 | Z72: 45746 | AA72: 45767 | AB72: 45781 | AC72: 45795 | AD72: 45809 | AE72: 45823 | AF72: 45844 | AG72: 45858 | AH72: 45879 | AI72: =AH72-V72 -> 194
A73: 63 | B73: 音不 | C73: 0 | H73: おかひろし | I73: passion_okatyan | J73: https://www.notion.so/g-51a2126bef13487b92fd05386bdd67d2?pvs=4 | K73: ふみや | L73: G組 | M73: ふみや | N73: 45679 | O73: 2月中旬 | P73: 45679 | R73: =W73 -> 45703 | S73: =R73+180 -> 45883 | T73: 森本風花 | U73: 12 | V73: 45685 | W73: 45703 | X73: 45722 | Y73: 45736 | Z73: 45752 | AA73: 45766 | AB73: 45781 | AC73: 45795 | AD73: 45800 | AE73: 6/5で停止 | AI73: =AH73-V73 -> -45685
A74: 64 | B74: 卒業 | C74: 1 | H74: てらもとまさゆき | I74: tera.security | J74: https://www.notion.so/E-19bf3b0fba85809da5fdc7ce76a7636f | K74: タク | L74: B組 | M74: タク | N74: 45687 | O74: 2月中旬 | P74: 45688 | R74: =W74 -> 45724 | S74: =R74+180 -> 45904 | T74: 山見阪佳子 | U74: 5 | V74: 45703 | W74: 45724 | X74: 45738 | Y74: 45752 | Z74: 45766 | AA74: 45780 | AB74: 45795 | AC74: 45815 | AD74: 45830 | AE74: 45844 | AF74: 45859 | AG74: 45879 | AH74: 45898 | AI74: =AH74-V74 -> 195
A75: 65 | B75: 卒業 | C75: 0 | H75: いけうちさや | I75: pan_chan0380 | J75: https://www.notion.so/a-19df3b0fba85806f8841f870fd7bcb43?pvs=4 | K75: うちこ | L75: C組 | M75: ゆき | N75: 45694 | O75: 2月中旬 | P75: 45694 | R75: =W75 -> 45720 | S75: =R75+180 -> 45900 | T75: 正木千智 | U75: 1 | V75: 45708 | W75: 45720 | X75: 45742 | Y75: 45754 | Z75: 45768 | AA75: 45784 | AB75: 45803 | AC75: 45817 | AD75: 45838 | AE75: 45860 | AF75: 45873 | AG75: 45894 | AH75: 45908 | AI75: =AH75-V75 -> 200
A76: 66 | B76: 卒業 | C76: 0 | H76: しまむらまりな | I76: english_no_maria | J76: https://www.notion.so/H-19af3b0fba85808fab66f27f0f29cab9 | K76: ふみや | L76: H組 | M76: ふみや | N76: 45694 | O76: 2月中旬 | P76: 45694 | R76: =W76 -> 45727 | S76: =R76+180 -> 45907 | T76: 鈴木久美子 | U76: 2 | V76: 45705 | W76: 45727 | X76: 45740 | Y76: 45748 | Z76: 45762 | AA76: 45792 | AB76: 45808 | AC76: 45824 | AD76: 45838 | AE76: 45848 | AF76: 45862 | AG76: 45874 | AH76: 45897 | AI76: =AH76-V76 -> 192
A77: 67 | B77: 卒業 | C77: 0 | H77: いしいるりな | I77: amopi_asd | J77: https://www.notion.so/a-196f3b0fba858021abffe914d10c5023 | K77: ゆきへい | L77: A組 | M77: ゆきへい | N77: 45694 | O77: 2月中旬 | P77: 45693 | R77: =W77 -> 45716 | S77: =R77+180 -> 45896 | T77: 有山友菜 | U77: 3 | V77: 45700 | W77: 45716 | X77: 45730 | Y77: 45741 | Z77: 45748 | AA77: =Z77+14 -> 45762 | AB77: 45778 | AC77: 45792 | AD77: 45810 | AE77: 45828 | AF77: 45840 | AG77: 45853 | AH77: 45882 | AI77: =AH77-V77 -> 182
A78: 68 | B78: 卒業 | C78: 0 | H78: かわさきちあき | I78: chi.wankogohan | J78: https://www.notion.so/C-1b2f3b0fba8580e5b430dece15f9128f?pvs=4 | K78: うちこ | L78: C組 | M78: うちこ | N78: 45718 | O78: 3月中旬〜下旬スタート | P78: 45719 | R78: =W78 -> 45744 | S78: =R78+180 -> 45924 | T78: 小針彩乃 | U78: 3 | V78: 45730 | W78: 45744 | X78: 45757 | Y78: 45772 | Z78: 45786 | AA78: 45800 | AB78: 45813 | AC78: 45827 | AD78: 45841 | AE78: 45855 | AF78: 45876 | AG78: 45887 | AH78: 45911 | AI78: =AH78-V78 -> 181
A79: 69 | B79: 音不 | C79: 0 | H79: くろだまさあき | J79: https://www.notion.so/I-1a6f3b0fba858038a120d7c11b1c7bc1 | K79: ゆう | L79: I組 | M79: ゆう | N79: 45743 | P79: 45743 | R79: =W79 -> 45772 | S79: =R79+180 -> 45952 | T79: 野村佑佳 | U79: 10 | V79: 45758 | W79: 45772 | X79: 45786 | Y79: 45800 | Z79: 45814 | AA79: 45828 | AB79: 45842 | AC79: 7/10で停止 | AI79: =AH79-V79 -> -45758
A80: 70 | B80: 卒業 | C80: 0 | H80: きべまき | I80: tsumako_gohan | J80: https://www.notion.so/B-1def3b0fba85801f8816cd4d0915ff1d?pvs=4 | K80: フミ | L80: B組 | M80: フミ | N80: 45754 | O80: 4月下旬ごろ | P80: 45758 | R80: =W80 -> 45784 | S80: =R80+180 -> 45964 | T80: 久保山菜々恵 | U80: 1 | V80: 45770 | W80: 45784 | X80: 45798 | Y80: 45812 | Z80: 45833 | AA80: 45847 | AB80: 45861 | AC80: 45875 | AD80: 45889 | AE80: 45903 | AF80: 45924 | AG80: 45952 | AH80: 45959 | AI80: =AH80-V80 -> 189
A81: 71 | B81: 卒業 | C81: 0 | H81: きくちことの | I81: pino.couple.dirt | J81: https://www.notion.so/A-1ddf3b0fba85800fb77feb9bd585270e?pvs=4 | K81: もぐ | L81: A組 | M81: もぐ | N81: 45755 | O81: 4月下旬ごろ | P81: 45758 | R81: =W81 -> 45783 | S81: =R81+180 -> 45963 | T81: 須見浩人 | U81: 6 | V81: 45769 | W81: 45783 | X81: 45797 | Y81: 45813 | Z81: 45832 | AA81: 45849 | AB81: 45863 | AC81: 45876 | AD81: 45897 | AE81: 45912 | AF81: 45926 | AG81: 45944 | AH81: 45958 | AI81: =AH81-V81 -> 189
A82: 72 | B82: 休会 | C82: 0 | H82: さえきもえか（かぶしきがいしゃりんくさぽーと） | I82: myariku.suke | J82: https://www.notion.so/A-1e0f3b0fba85803b905beb10661b85d3?pvs=4 | K82: にに夫婦 | L82: A組 | M82: にに夫婦 | N82: 45761 | O82: 25年4月中旬〜下旬 | P82: 45772 | R82: =W82 -> 45786 | S82: =R82+180 -> 45966 | T82: 宮田友理 | U82: 7 | V82: 45777 | W82: 45786 | X82: 45811 | Y82: 45845 | Z82: 45853 | AA82: 45863 | AB82: 45877 | AC82: 45887 | AI82: =AH82-V82 -> -45777
A83: 73 | B83: 音不 | C83: 0 | H83: いわぶちあゆか | J83: https://www.notion.so/E-1ecf3b0fba858022ab36daa529505321?pvs=4 | K83: まろ | L83: E組 | M83: まろ | N83: 45759 | O83: 25年4月下旬 | P83: 45781 | R83: =W83 -> 45801 | S83: =R83+180 -> 45981 | T83: 宮田友理 | U83: 8 | V83: 45787 | W83: 45801 | X83: 45817 | Y83: 6/19で停止 | AI83: =AH83-V83 -> -45787
A84: 74 | B84: 卒業 | C84: 0 | H84: かとうともか | I84: sazae_ryoushiyome | J84: https://www.notion.so/C-1ecf3b0fba8580978ddde5d8aff23665?pvs=4 | K84: とと | L84: C組 | M84: とと | N84: 45694 | O84: 25年4月下旬 | P84: 45781 | R84: =W84 -> 45799 | S84: =R84+180 -> 45979 | T84: 今立なつみ | U84: 1 | V84: 45785 | W84: 45799 | X84: 45813 | Y84: 45831 | Z84: 45852 | AA84: 45867 | AB84: 45877 | AC84: 45894 | AD84: 45909 | AE84: 45929 | AF84: 45947 | AG84: 45960 | AH84: 45971 | AI84: =AH84-V84 -> 186
A85: 75 | B85: 卒業 | C85: 0 | H85: ひらやまみか | I85: mimi_kaigo | J85: https://www.notion.so/d-200f3b0fba8580aba4abcfd7026df832?v=fe41848ef8d642c6b1c0988a174dc89b&source=copy_link | K85: きたごはん | L85: D組 | M85: きたごはん | N85: 45770 | O85: 25年4月下旬 | P85: 45772 | R85: =W85 -> 45820 | S85: =R85+180 -> 46000 | T85: 久保山菜々恵 | U85: 2 | V85: 45804 | W85: 45820 | X85: 45834 | Y85: 45848 | Z85: 45856 | AA85: 45874 | AB85: 45890 | AC85: 45904 | AD85: 45926 | AE85: 45946 | AF85: 45950 | AG85: 45966 | AH85: 45968 | AI85: =AH85-V85 -> 164
A86: 76 | B86: 卒業 | C86: 0 | H86: おおしろにいな | I86: nina_diet_recipe | J86: https://www.notion.so/e-1e6f3b0fba8580e2bfe1e23adc548dfc?pvs=4 | K86: まろ | L86: E組 | M86: まろ | N86: 45771 | O86: 25年4月下旬 | P86: 45772 | R86: =W86 -> 45792 | S86: =R86+180 -> 45972 | T86: 久保山菜々恵 | U86: 3 | V86: 45778 | W86: 45792 | X86: 45806 | Y86: 45820 | Z86: 45834 | AA86: 45848 | AB86: 45862 | AC86: 45890 | AD86: 45898 | AE86: 45904 | AF86: 45918 | AG86: 45932 | AH86: 45953 | AI86: =AH86-V86 -> 175
A87: 77 | B87: 卒業 | C87: 0 | H87: ひろたはるな | I87: hiiro_no_hibi | J87: https://www.notion.so/K-1eaf3b0fba858022b461e5800a6e6a68?pvs=4 | K87: ゆな | L87: K組 | M87: ゆな | N87: 45775 | O87: 25年4月下旬 | P87: 45776 | R87: =W87 -> 45797 | S87: =R87+180 -> 45977 | T87: 正木千智 | U87: 2 | V87: 45787 | W87: 45797 | X87: 45811 | Y87: 45827 | Z87: 45842 | AA87: 45853 | AB87: 45872 | AC87: 45892 | AD87: 45905 | AE87: 45921 | AF87: 45935 | AG87: 45960 | AH87: 45998 | AI87: =AH87-V87 -> 211
A88: 78 | B88: 卒業 | C88: 1 | H88: たかぎみさき | I88: takami_15recipe | J88: https://www.notion.so/L-1f0f3b0fba858033a196d9df32ff760b | K88: ゆな | L88: L組 | M88: ゆな | N88: 45781 | O88: 25年5月上旬 | P88: 45781 | R88: =W88 -> 45807 | S88: =R88+180 -> 45987 | T88: 山見阪佳子 | U88: 6 | V88: 45793 | W88: 45807 | X88: 45821 | Y88: 45835 | Z88: 45856 | AA88: 45866 | AB88: 45884 | AC88: 45898 | AD88: 45922 | AE88: 45925 | AF88: 45936 | AG88: 45954 | AH88: 45982 | AI88: =AH88-V88 -> 189
A89: 79 | B89: 卒業 | C89: 0 | H89: しむらまなぶ | J89: https://www.notion.so/201f3b0fba858059a978fa2a57e4b701?source=copy_link | K89: ゆうと | L89: B組 | M89: =K89 -> ゆうと | O89: 25年5月上旬 | P89: 45782 | R89: =W89 -> 45814 | S89: =R89+180 -> 45994 | T89: 須見浩人 | U89: 7 | V89: 45800 | W89: 45814 | X89: 45829 | Y89: 45848 | Z89: 45864 | AA89: 45878 | AB89: 45899 | AC89: 45915 | AD89: 45928 | AE89: 45942 | AF89: 45958 | AG89: 45973 | AH89: 45987 | AI89: =AH89-V89 -> 187
A90: 80 | B90: 卒業 | C90: 0 | H90: ふじおかみすず | I90: mirin_room_ | J90: https://www.notion.so/K-1f4f3b0fba8580bbb245e14942edd85e | K90: ゆう | L90: K組 | M90: =K90 -> ゆう | O90: 45795 | P90: 45784 | R90: 45806 | S90: =R90+180 -> 45986 | T90: 野村佑佳 | U90: 11 | V90: 45796 | W90: 45806 | X90: 45817 | Y90: 45831 | Z90: 45840 | AA90: 45860 | AB90: 45873 | AC90: 45887 | AD90: 45901 | AE90: 45915 | AF90: 45936 | AG90: 45956 | AH90: 45987 | AI90: =AH90-V90 -> 191
A91: 81 | B91: 卒業 | C91: 0 | H91: やまぐちちづる | I91: odoru_ryokoumama40 | J91: https://www.notion.so/J-204f3b0fba85805daea8c189fec3ed68 | K91: はむ | L91: J組 | M91: =K91 -> はむ | N91: 45797 | O91: 25年5月下旬〜6月 | P91: 45798 | R91: =W91 -> 45827 | S91: =R91+180 -> 46007 | T91: 青木千奈 | U91: 1 | V91: 45813 | W91: 45827 | X91: 45845 | Y91: 45860 | Z91: 45874 | AA91: 45891 | AB91: 45905 | AC91: 45923 | AD91: 45938 | AE91: 45952 | AF91: 45966 | AG91: 45980 | AH91: 46379 | AI91: =AH91-V91 -> 566
A92: 83 | B92: 卒業 | C92: 0 | H92: のぶとうまさこ | I92: mskn.christmas | J92: https://www.notion.so/205f3b0fba85809e817cd35f54db27bc?source=copy_link | K92: ふみや | L92: I組 | M92: =K92 -> ふみや | O92: 25年5月下旬 | P92: 45806 | R92: =W92 -> 45824 | S92: =R92+180 -> 46004 | T92: 高木千鶴 | U92: 1 | V92: 45810 | W92: 45824 | X92: 45845 | Y92: 45859 | Z92: 45873 | AA92: 45887 | AB92: 45901 | AC92: 45915 | AD92: 45934 | AE92: 45945 | AF92: 45957 | AG92: 45971 | AH92: 45985 | AI92: =AH92-V92 -> 175
A93: 84 | B93: 卒業 | C93: 0 | H93: かげやまこゆき | I93: yukiko_sologram koyuki_viewmap | J93: https://www.notion.so/TakuyaB-20ef3b0fba858073ae2bcc885f982750 | K93: Takuya | L93: B組 | M93: =K93 -> Takuya | O93: 25年5月下旬〜6月上旬 | P93: 45806 | R93: =W93 -> 45831 | S93: =R93+180 -> 46011 | T93: 青木千奈 | U93: 2 | V93: 45818 | W93: 45831 | X93: 45845 | Y93: 45859 | Z93: 45873 | AA93: 45887 | AB93: 45903 | AC93: 45915 | AD93: 45932 | AE93: 45950 | AF93: 45966 | AG93: 45981 | AH93: 45994 | AI93: =AH93-V93 -> 176
A94: 85 | B94: 卒業 | C94: 0 | H94: こうごたかひろ | I94: piro_yaseuma | J94: https://www.notion.so/A-20af3b0fba85804a97ccf6e5ecf512e9?source=copy_link | K94: コトカナ | L94: A組 | M94: =K94 -> コトカナ | O94: 25年6月上旬 | P94: 45807 | R94: =W94 -> 45831 | S94: =R94+180 -> 46011 | T94: 中富智弘 | U94: 1 | V94: 45816 | W94: 45831 | X94: 45847 | Y94: 45861 | AI94: =AH94-V94 -> -45816
A95: 86 | B95: 卒業 | C95: 0 | H95: かきのきまゆみ | I95: mimi_kojirecipe | J95: https://www.notion.so/F-216f3b0fba85805fbe7bc87967cbb17a?source=copy_link | K95: はる | L95: F組 | M95: =K95 -> はる | O95: 25年6月上旬〜中旬 | P95: 45812 | R95: =W95 -> 45867 | S95: =R95+180 -> 46047 | T95: 今立なつみ | U95: 2 | V95: 45846 | W95: 45867 | X95: 45880 | Y95: 45893 | Z95: 45906 | AA95: 45920 | AB95: 45934 | AC95: 45961 | AD95: 45982 | AE95: 45994 | AF95: 46007 | AG95: 46028 | AH95: 46037 | AI95: =AH95-V95 -> 191
A96: 87 | B96: 卒業 | C96: 0 | H96: らぶひとみ | I96: rabu_english | J96: https://www.notion.so/4937f3153e0d45508b66fd2057aa74b3?v=6619d382b9104ae7b9f12baf3cc810b9&p=1f4f3b0fba8581f3aa38ec01cf0093fa&pm=s | K96: おとパパ | L96: A組 | M96: =K96 -> おとパパ | O96: 25年6月上旬 | P96: 45812 | R96: =W96 -> 45834 | S96: =R96+180 -> 46014 | T96: 宮田友理 | U96: 9 | V96: 45820 | W96: 45834 | X96: 45848 | Y96: 45863 | Z96: 45877 | AA96: 45891 | AB96: 45905 | AC96: 45919 | AD96: 45939 | AE96: 45953 | AF96: 45967 | AG96: 45981 | AH96: 46015 | AI96: =AH96-V96 -> 195
A97: 88 | B97: 卒業 | C97: 0 | H97: かわらまき | I97: maayan_animal | J97: https://docs.google.com/spreadsheets/d/1CyJDPWktOgavBfGobiSkpXzB-hfGZZOHnO7fzpFydTI/edit?usp=sharing | K97: おとパパ | L97: B組 | M97: =K97 -> おとパパ | O97: 25年6月上旬〜中旬 | P97: 45813 | R97: =W97 -> 45838 | S97: =R97+180 -> 46018 | T97: 森淳子 | U97: 1 | V97: 45824 | W97: 45838 | X97: 45852 | Y97: 45873 | Z97: 45896 | AA97: 45908 | AB97: 45922 | AC97: 45933 | AD97: 45947 | AE97: 45961 | AF97: 45979 | AG97: 45993 | AH97: 46003 | AI97: =AH97-V97 -> 179
A98: 89 | B98: 卒業 | C98: 0 | H98: ながいけいこ | I98: core_gohan | J98: https://www.notion.so/20ff3b0fba85805f8981d7fad2be5842?source=copy_link | K98: ミク | L98: A組 | M98: =K98 -> ミク | O98: 25年6月上旬〜中旬 | P98: 45813 | R98: =W98 -> 45850 | S98: =R98+180 -> 46030 | T98: 高木千鶴 | U98: 2 | V98: 45819 | W98: 45850 | X98: 45861 | Y98: 45875 | Z98: 45889 | AA98: 45903 | AB98: 45917 | AC98: 45938 | AD98: 45952 | AE98: 45966 | AF98: 45980 | AG98: 45994 | AH98: 46015 | AI98: =AH98-V98 -> 196
A99: 90 | B99: 卒業 | C99: 0 | H99: ろばーつあゆみ | I99: mama.no.camera.jikan | J99: https://www.notion.so/B-21cf3b0fba858089b7eef341cd0a0037?source=copy_link | K99: コトカナ | L99: B組 | M99: =K99 -> コトカナ | O99: 25年6月中旬 | P99: 45823 | R99: =W99 -> 45845 | S99: =R99+180 -> 46025 | T99: 森本風花 | U99: 13 | V99: 45832 | W99: 45845 | X99: 45866 | Y99: 45880 | Z99: 45895 | AA99: 45908 | AB99: 45922 | AC99: 45936 | AD99: 45950 | AE99: 45971 | AF99: 45986 | AG99: 46000 | AI99: =AH99-V99 -> -45832
A100: 91 | B100: 卒業 | C100: 0 | H100: じくまるみほ | I100: mippori | J100: https://www.notion.so/4937f3153e0d45508b66fd2057aa74b3?v=6619d382b9104ae7b9f12baf3cc810b9&p=209f3b0fba858148a9e7e10d9140932b&pm=s | K100: yuri | L100: B組 | M100: =K100 -> yuri | O100: 25年6月中旬〜下旬 | P100: 45823 | R100: =W100 -> 45865 | S100: =R100+180 -> 46045 | T100: 多田萌子 | U100: 1 | V100: 45837 | W100: 45865 | X100: 45879 | Y100: 45893 | Z100: 45911 | AA100: 45921 | AB100: 45935 | AC100: 45948 | AD100: 45962 | AE100: 45976 | AF100: 45996 | AG100: 46011 | AH100: 46032 | AI100: =AH100-V100 -> 195
...

Sheet 目標値集計シート
C1: 生徒名 | D1: 在学・卒業合計 | E1: 在学中 | F1: 卒業生 | G1: 万垢達成 | H1: 期間中万垢 | I1: 卒業後万垢 | J1: 音信不通 | K1: 例外 | L1: クーリングオフ | S1: 目標値メモ | T1: アクション数評価 全体平均0.0pt以上（全体のアクション数が、300アクション以上） 投稿数評価 全体平均0.0pt以上（全体の卒業時投稿数平均が、60投稿以上）
C2: コミットプラン契約者数 | D2: =COUNTA('セッション実施状況管理'!H11:H663)-L2-J2-K2 -> 242 | E2: =COUNTIFS(C19:C437, "<>", I19:I437, "在学中") -> 158 | F2: =COUNTIFS(C19:C437, "<>", I19:I437, "卒業") -> 82 | G2: =IFERROR(__xludf.DUMMYFUNCTION("COUNTA( FILTER( C:C, COUNTIFS( 'セッション実施状況管理'!H:H, C:C, 'セッション実施状況管理'!C:C, "">=1"" )>0 ) )"),28.0) -> 28 | H2: =IFERROR(__xludf.DUMMYFUNCTION("COUNTA( FILTER( C:C, COUNTIFS( 'セッション実施状況管理'!H:H, C:C, 'セッション実施状況管理'!C:C, 1 )>0 ) )"),22.0) -> 22 | I2: =IFERROR(__xludf.DUMMYFUNCTION("COUNTA( FILTER( C:C, COUNTIFS( 'セッション実施状況管理'!H:H, C:C, 'セッション実施状況管理'!C:C, 2 )>0 ) )"),6.0) -> 6 | J2: =COUNTIFS(C19:C437, "<>", I19:I437, "音不") -> 10 | K2: =COUNTIFS(C19:C437, "<>", I19:I437, "例外") -> 6 | L2: =COUNTIFS(C19:C437, "<>", I19:I437, "クーリングオフ") -> 6
D3: 1 | E3: =E2/$D$2*100 -> 65.289256 | F3: =F2/$D$2*100 -> 33.884298 | G3: =G2/D2*100 -> 11.570248 | H3: =H2/D2*100 -> 9.0909091 | I3: =I2/D2*100 -> 2.4793388 | J3: =J2/$D$2*100 -> 4.1322314 | K3: =K2/$D$2*100 -> 2.4793388 | L3: =L2/$D$2*100 -> 2.4793388
F4: ⇧投稿数 | G4: ⇧投稿数
T8: =IFERROR(__xludf.DUMMYFUNCTION("AVERAGE( FILTER( T63:T200, ($I$63:$I$200=""在学中"") * ($S$63:$S$200=0) * (T63:T200<>"""") ) )"),"#DIV/0!") -> #DIV/0! | U8: =IFERROR(__xludf.DUMMYFUNCTION("AVERAGE( FILTER( U63:U200, ($I$63:$I$200=""在学中"") * ($S$63:$S$200=1) * (U63:U200<>"""") ) )"),"#N/A") -> #N/A | V8: =IFERROR(__xludf.DUMMYFUNCTION("AVERAGE( FILTER( V63:V200, ($I$63:$I$200=""在学中"") * ($S$63:$S$200=2) * (V63:V200<>"""") ) )"),134.0) -> 134 | W8: =IFERROR(__xludf.DUMMYFUNCTION("AVERAGE( FILTER( W63:W200, ($I$63:$I$200=""在学中"") * ($S$63:$S$200=3) * (W63:W200<>"""") ) )"),73.33333333333333) -> 73.333333 | X8: =IFERROR(__xludf.DUMMYFUNCTION("AVERAGE( FILTER( X63:X200, ($I$63:$I$200=""在学中"") * ($S$63:$S$200=4) * (X63:X200<>"""") ) )"),"#DIV/0!") -> #DIV/0! | Y8: =IFERROR(__xludf.DUMMYFUNCTION("AVERAGE( FILTER( Y63:Y200, ($I$63:$I$200=""在学中"") * ($S$63:$S$200=5) * (Y63:Y200<>"""") ) )"),"#DIV/0!") -> #DIV/0! | Z8: =IFERROR(__xludf.DUMMYFUNCTION("AVERAGE( FILTER( Z63:Z200, ($I$63:$I$200=""在学中"") * ($S$63:$S$200=6) * (Z63:Z200<>"""") ) )"),"#DIV/0!") -> #DIV/0!
F9: 120メンバー目標達成率(599) | P9: =IF(P16=0, "", P10 / P16 * 100) -> 46.432944 | Q9: =IF(Q16=0, "", Q10 / Q16 * 100) -> 68.555688 | R9: =IF(R16=0, "", R10 / R16 * 100) -> 81.062469 | T9: =IF(T16=0, "", T10 / T16 * 100) -> 72.579365 | U9: =IF(U16=0, "", U10 / U16 * 100) -> 85.044179 | V9: =IF(V16=0, "", V10 / V16 * 100) -> 82.637363 | W9: =IF(W16=0, "", W10 / W16 * 100) -> 73.855311 | X9: =IF(X16=0, "", X10 / X16 * 100) -> 62.474562 | Y9: =IF(Y16=0, "", Y10 / Y16 * 100) -> 61.538462 | Z9: =IF(Z16=0, "", Z10 / Z16 * 100) -> 102.82486
F10: 平均アクション数（120メンバーのみ） | J10: =IFERROR(__xludf.DUMMYFUNCTION("AVERAGE(FILTER(J63:J200, ($I$63:$I$200=""在学中"") * (J63:J200<>"""")))"),0.0) -> 0 | K10: =IFERROR(__xludf.DUMMYFUNCTION("AVERAGE(FILTER(K63:K200, ($I$63:$I$200=""在学中"") * (K63:K200<>"""")))"),0.8) -> 0.8 | L10: =IFERROR(__xludf.DUMMYFUNCTION("AVERAGE(FILTER(L63:L200, ($I$63:$I$200=""在学中"") * (L63:L200<>"""")))"),27.547169811320753) -> 27.54717 | M10: =IFERROR(__xludf.DUMMYFUNCTION("AVERAGE(FILTER(M63:M200, ($I$63:$I$200=""在学中"") * (M63:M200<>"""")))"),0.4) -> 0.4 | N10: =IFERROR(__xludf.DUMMYFUNCTION("AVERAGE(FILTER(N63:N200, ($I$63:$I$200=""在学中"") * (N63:N200<>"""")))"),1.1866666666666668) -> 1.1866667 | O10: =IFERROR(__xludf.DUMMYFUNCTION("AVERAGE(FILTER(O63:O200, ($I$63:$I$200=""在学中"") * (O63:O200<>"""")))"),-0.41333333333333333) -> -0.41333333 | P10: =IFERROR(__xludf.DUMMYFUNCTION("AVERAGE(FILTER(P63:P200, ($I$63:$I$200=""在学中"") * (P63:P200<>"""")))"),278.1333333333333) -> 278.13333 | Q10: =IFERROR(__xludf.DUMMYFUNCTION("AVERAGE(FILTER(Q63:Q200, ($I$63:$I$200=""在学中"") * (Q63:Q200<>"""")))"),410.6485714285715) -> 410.64857 | R10: =IFERROR(__xludf.DUMMYFUNCTION("AVERAGE(FILTER(R63:R200, ($I$63:$I$200=""在学中"") * (R63:R200<>"""")))"),69.36631274131274) -> 69.366313 | T10: =IFERROR(__xludf.DUMMYFUNCTION("AVERAGE(FILTER(T63:T200, ($I$63:$I$200=""在学中"") * (T63:T200<>"""")))"),52.25714285714286) -> 52.257143 | U10: =IFERROR(__xludf.DUMMYFUNCTION("AVERAGE(FILTER(U63:U200, ($I$63:$I$200=""在学中"") * (U63:U200<>"""")))"),88.44594594594595) -> 88.445946 | V10: =IFERROR(__xludf.DUMMYFUNCTION("AVERAGE(FILTER(V63:V200, ($I$63:$I$200=""在学中"") * (V63:V200<>"""")))"),75.2) -> 75.2 | W10: =IFERROR(__xludf.DUMMYFUNCTION("AVERAGE(FILTER(W63:W200, ($I$63:$I$200=""在学中"") * (W63:W200<>"""")))"),67.20833333333333) -> 67.208333 | X10: =IFERROR(__xludf.DUMMYFUNCTION("AVERAGE(FILTER(X63:X200, ($I$63:$I$200=""在学中"") * (X63:X200<>"""")))"),56.851851851851855) -> 56.851852 | Y10: =IFERROR(__xludf.DUMMYFUNCTION("AVERAGE(FILTER(Y63:Y200, ($I$63:$I$200=""在学中"") * (Y63:Y200<>"""")))"),56.0) -> 56 | Z10: =IFERROR(__xludf.DUMMYFUNCTION("AVERAGE(FILTER(Z63:Z200, ($I$63:$I$200=""在学中"") * (Z63:Z200<>"""")))"),60.666666666666664) -> 60.666667
F11: 120-在学生 差 | J11: =J10-J12 -> 0 | K11: =K10-K12 -> 0 | L11: =L10-L12 -> 0 | M11: =M10-M12 -> 0.0052631579 | N11: =N10-N12 -> -0.010701754 | O11: =O10-O12 -> 0.020877193 | P11: =P10-P12 -> 0.64649123 | Q11: =Q10-Q12 -> -0.62304511 | R11: =R10-R12 -> -0.092893608 | T11: =T10-T12 -> 0.7360161 | U11: =U10-U12 -> -0.90072072 | V11: =V10-V12 -> 0.030985915 | W11: =W10-W12 -> 0 | X11: =X10-X12 -> 0 | Y11: =Y10-Y12 -> 0 | Z11: =Z10-Z12 -> 0
F12: 平均アクション数（在学生全体） | J12: =IFERROR(__xludf.DUMMYFUNCTION("AVERAGE(FILTER(J40:J201, ($I40:$I$201=""在学中"") * (J40:J201<>"""")))"),0.0) -> 0 | K12: =IFERROR(__xludf.DUMMYFUNCTION("AVERAGE(FILTER(K40:K201, ($I40:$I$201=""在学中"") * (K40:K201<>"""")))"),0.8) -> 0.8 | L12: =IFERROR(__xludf.DUMMYFUNCTION("AVERAGE(FILTER(L40:L201, ($I40:$I$201=""在学中"") * (L40:L201<>"""")))"),27.547169811320753) -> 27.54717 | M12: =IFERROR(__xludf.DUMMYFUNCTION("AVERAGE(FILTER(M40:M201, ($I40:$I$201=""在学中"") * (M40:M201<>"""")))"),0.39473684210526316) -> 0.39473684 | N12: =IFERROR(__xludf.DUMMYFUNCTION("AVERAGE(FILTER(N40:N201, ($I40:$I$201=""在学中"") * (N40:N201<>"""")))"),1.1973684210526316) -> 1.1973684 | O12: =IFERROR(__xludf.DUMMYFUNCTION("AVERAGE(FILTER(O40:O201, ($I40:$I$201=""在学中"") * (O40:O201<>"""")))"),-0.4342105263157895) -> -0.43421053 | P12: =IFERROR(__xludf.DUMMYFUNCTION("AVERAGE(FILTER(P40:P201, ($I40:$I$201=""在学中"") * (P40:P201<>"""")))"),277.4868421052632) -> 277.48684 | Q12: =IFERROR(__xludf.DUMMYFUNCTION("AVERAGE(FILTER(Q40:Q201, ($I40:$I$201=""在学中"") * (Q40:Q201<>"""")))"),411.2716165413534) -> 411.27162 | R12: =IFERROR(__xludf.DUMMYFUNCTION("AVERAGE(FILTER(R40:R201, ($I40:$I$201=""在学中"") * (R40:R201<>"""")))"),69.45920634920635) -> 69.459206 | T12: =IFERROR(__xludf.DUMMYFUNCTION("AVERAGE(FILTER(T40:T201, ($I40:$I$201=""在学中"") * (T40:T201<>"""")))"),51.521126760563384) -> 51.521127 | U12: =IFERROR(__xludf.DUMMYFUNCTION("AVERAGE(FILTER(U40:U201, ($I40:$I$201=""在学中"") * (U40:U201<>"""")))"),89.34666666666666) -> 89.346667 | V12: =IFERROR(__xludf.DUMMYFUNCTION("AVERAGE(FILTER(V40:V201, ($I40:$I$201=""在学中"") * (V40:V201<>"""")))"),75.16901408450704) -> 75.169014 | W12: =IFERROR(__xludf.DUMMYFUNCTION("AVERAGE(FILTER(W40:W201, ($I40:$I$201=""在学中"") * (W40:W201<>"""")))"),67.20833333333333) -> 67.208333 | X12: =IFERROR(__xludf.DUMMYFUNCTION("AVERAGE(FILTER(X40:X201, ($I40:$I$201=""在学中"") * (X40:X201<>"""")))"),56.851851851851855) -> 56.851852 | Y12: =IFERROR(__xludf.DUMMYFUNCTION("AVERAGE(FILTER(Y40:Y201, ($I40:$I$201=""在学中"") * (Y40:Y201<>"""")))"),56.0) -> 56 | Z12: =IFERROR(__xludf.DUMMYFUNCTION("AVERAGE(FILTER(Z40:Z201, ($I40:$I$201=""在学中"") * (Z40:Z201<>"""")))"),60.666666666666664) -> 60.666667
F13: 平均アクション数（120投稿以外） | J13: =IFERROR(__xludf.DUMMYFUNCTION("AVERAGE(FILTER(J19:J39, (($I19:$I$39=""在学中"") + ($I19:$I$39=""卒業"")) * (J19:J39<>"""")))"),0.0) -> 0 | K13: =IFERROR(__xludf.DUMMYFUNCTION("AVERAGE(FILTER(K19:K39, (($I19:$I$39=""在学中"") + ($I19:$I$39=""卒業"")) * (K19:K39<>"""")))"),0.4) -> 0.4 | L13: =IFERROR(__xludf.DUMMYFUNCTION("AVERAGE(FILTER(L19:L39, (($I19:$I$39=""在学中"") + ($I19:$I$39=""卒業"")) * (L19:L39<>"""")))"),48.45) -> 48.45 | M13: =IFERROR(__xludf.DUMMYFUNCTION("AVERAGE(FILTER(M19:M39, (($I19:$I$39=""在学中"") + ($I19:$I$39=""卒業"")) * (M19:M39<>"""")))"),-1.0) -> -1 | N13: =IFERROR(__xludf.DUMMYFUNCTION("AVERAGE(FILTER(N19:N39, (($I19:$I$39=""在学中"") + ($I19:$I$39=""卒業"")) * (N19:N39<>"""")))"),0.6) -> 0.6 | O13: =IFERROR(__xludf.DUMMYFUNCTION("AVERAGE(FILTER(O19:O39, (($I19:$I$39=""在学中"") + ($I19:$I$39=""卒業"")) * (O19:O39<>"""")))"),-0.55) -> -0.55 | P13: =IFERROR(__xludf.DUMMYFUNCTION("AVERAGE(FILTER(P19:P39, (($I19:$I$39=""在学中"") + ($I19:$I$39=""卒業"")) * (P19:P39<>"""")))"),256.5) -> 256.5 | Q13: =IFERROR(__xludf.DUMMYFUNCTION("AVERAGE(FILTER(Q19:Q39, (($I19:$I$39=""在学中"") + ($I19:$I$39=""卒業"")) * (Q19:Q39<>"""")))"),365.5664285714286) -> 365.56643 | R13: =IFERROR(__xludf.DUMMYFUNCTION("AVERAGE(FILTER(R19:R39, (($I19:$I$39=""在学中"") + ($I19:$I$39=""卒業"")) * (R19:R39<>"""")))"),64.13446115288221) -> 64.134461 | T13: =IFERROR(__xludf.DUMMYFUNCTION("AVERAGE(FILTER(T19:T39, (($I19:$I$39=""在学中"") + ($I19:$I$39=""卒業"")) * (T19:T39<>"""")))"),1.6666666666666667) -> 1.6666667 | U13: =IFERROR(__xludf.DUMMYFUNCTION("AVERAGE(FILTER(U19:U39, (($I19:$I$39=""在学中"") + ($I19:$I$39=""卒業"")) * (U19:U39<>"""")))"),50.666666666666664) -> 50.666667 | V13: =IFERROR(__xludf.DUMMYFUNCTION("AVERAGE(FILTER(V19:V39, (($I19:$I$39=""在学中"") + ($I19:$I$39=""卒業"")) * (V19:V39<>"""")))"),41.77777777777778) -> 41.777778 | W13: =IFERROR(__xludf.DUMMYFUNCTION("AVERAGE(FILTER(W19:W39, (($I19:$I$39=""在学中"") + ($I19:$I$39=""卒業"")) * (W19:W39<>"""")))"),68.3076923076923) -> 68.307692 | X13: =IFERROR(__xludf.DUMMYFUNCTION("AVERAGE(FILTER(X19:X39, (($I19:$I$39=""在学中"") + ($I19:$I$39=""卒業"")) * (X19:X39<>"""")))"),74.22222222222223) -> 74.222222 | Y13: =IFERROR(__xludf.DUMMYFUNCTION("AVERAGE(FILTER(Y19:Y39, (($I19:$I$39=""在学中"") + ($I19:$I$39=""卒業"")) * (Y19:Y39<>"""")))"),80.57894736842105) -> 80.578947 | Z13: =IFERROR(__xludf.DUMMYFUNCTION("AVERAGE(FILTER(Z19:Z39, (($I19:$I$39=""在学中"") + ($I19:$I$39=""卒業"")) * (Z19:Z39<>"""")))"),36.31578947368421) -> 36.315789
U14: =IFERROR(__xludf.DUMMYFUNCTION("COUNT( FILTER( U63:U200, ($I$63:$I$200=""在学中"") * (U63:U200<>"""") ) )"),74.0) -> 74 | V14: =IFERROR(__xludf.DUMMYFUNCTION("COUNT( FILTER( V63:V200, ($I$63:$I$200=""在学中"") * (V63:V200<>"""") ) )"),70.0) -> 70 | W14: =IFERROR(__xludf.DUMMYFUNCTION("COUNT( FILTER( W63:W200, ($I$63:$I$200=""在学中"") * (W63:W200<>"""") ) )"),48.0) -> 48 | X14: =IFERROR(__xludf.DUMMYFUNCTION("COUNT( FILTER( X63:X200, ($I$63:$I$200=""在学中"") * (X63:X200<>"""") ) )"),27.0) -> 27 | Y14: =IFERROR(__xludf.DUMMYFUNCTION("COUNT( FILTER( Y63:Y200, ($I$63:$I$200=""在学中"") * (Y63:Y200<>"""") ) )"),11.0) -> 11 | Z14: =IFERROR(__xludf.DUMMYFUNCTION("COUNT( FILTER( Z63:Z200, ($I$63:$I$200=""在学中"") * (Z63:Z200<>"""") ) )"),3.0) -> 3
F15: 累計 | T15: =SUM(T16) -> 72 | U15: =SUM(T15,U16) -> 176 | V15: =SUM(U15,V16) -> 267 | W15: =SUM(V15,W16) -> 358 | X15: =SUM(W15,X16) -> 449 | Y15: =SUM(X15,Y16) -> 540 | Z15: =SUM(Y15,Z16) -> 599
E16: =average(G16:M16) -> 54.75 | F16: 単月目標（599） | J16: 72 | K16: 72 | L16: 72 | M16: 3 | N16: 4 | O16: 4 | P16: 599 | Q16: 599 | R16: =AVERAGE(T16:Z16) -> 85.571429 | T16: 72 | U16: 104 | V16: 91 | W16: 91 | X16: 91 | Y16: 91 | Z16: 59
C17: 関数 | D17: 関数 | E17: 手動入力 | F17: 関数 | G17: 関数 | H17: ▼MAX13 | I17: 関数 | J17: 手動入力 | K17: 手動入力 | M17: 関数 | N17: 関数 | O17: 関数 | P17: 関数 | Q17: 関数 | R17: 関数 | T17: ▼NEWアクション数算出
B18: no. | D18: user ID | E18: アクションシート | F18: 担当コーチ | H18: セッション回数 | I18: 卒業在学 | J18: MVP | K18: 万垢・音不 | L18: 投稿数 | M18: 投稿評価 | N18: 予想アクション評価 | O18: 実績 アクション評価 | P18: 合計 | Q18: 予想合計アクションpt | R18: O列調整月間平均 | S18: 提出期間 | T18: 0ヶ月目 | U18: 1ヶ月目 | V18: 2ヶ月目 | W18: 3ヶ月目 | X18: 4ヶ月目 | Y18: 5ヶ月目 | Z18: 6ヶ月目 | AA18: 通常セッション | AB18: 入会からの経過月数 | AC18: 投稿カウント対象(1)
B19: 1 | C19: =vlookup(B19,'セッション実施状況管理'!$A:$U,8,false) -> おのまこと | D19: =vlookup(B19,'セッション実施状況管理'!$A:$I,9,false) -> koji_no_chie | E19: なし | F19: =vlookup(B19,'セッション実施状況管理'!$A:$U,20,false) -> 宮田友理 | G19: =vlookup(B19,'セッション実施状況管理'!$A:$U,20,false) -> 宮田友理 | H19: ='コーチング報酬管理'!G7 -> 6 | I19: =iferror(vlookup(B19,'セッション実施状況管理'!$A:$B,2,false),"") -> 例外 | J19: 0 | K19: 0 | L19: =VLOOKUP(B19,'新 月次投稿数'!$A:$N,13,false) -> 0 | M19: =IF(L19>=120, 3, IF(L19>=100, 2, IF(L19>=80, 1, IF(L19>=60, 0, IF(L19>=40, -1, IF(L19>=20, -2, -3)))))) -> -3 | N19: =IF(Q19>=540, 4, IF(Q19>=480, 3, IF(Q19>=420, 2, IF(Q19>=360, 1, IF(Q19>=300, 0, IF(Q19>=240, -1, -2)))))) -> -2 | O19: =IF(P19>=540, 4, IF(P19>=480, 3, IF(P19>=420, 2, IF(P19>=360, 1, IF(P19>=300, 0, IF(P19>=240, -1, -2)))))) -> -2 | P19: =sum(T19:Z19) -> 0 | Q19: 0 | R19: =iferror(P19/S19,"0") -> 0 | S19: =count(T19:Z19) -> 0 | T19: ー | U19: ー | V19: ー | W19: ー | X19: ー | Y19: ー | Z19: ー | AA19: =Vlookup(B19,'セッション実施状況管理'!$A:$R,17,false) -> - | AB19: =(YEAR(TODAY()) - YEAR($AA19)) * 12 + (MONTH(TODAY()) - MONTH($AA19)) -> #VALUE! | AC19: =IF( OR(AB19=3, AB19=4, AB19=5, AB19=6), "1", "2" ) -> #VALUE!
B20: 2 | C20: =vlookup(B20,'セッション実施状況管理'!$A:$U,8,false) -> ただゆうすけ | D20: =vlookup(B20,'セッション実施状況管理'!$A:$I,9,false) -> cya_kurashi | E20: https://docs.google.com/spreadsheets/d/1RQ1i_eyk31MMP-wjt5wEUlXzJWPRVCjqK3ZmtmiYJiY/edit?usp=sharing | F20: =vlookup(B20,'セッション実施状況管理'!$A:$U,20,false) -> 中村恵理 | G20: =vlookup(B20,'セッション実施状況管理'!$A:$U,20,false) -> 中村恵理 | H20: ='コーチング報酬管理'!G8 -> 13 | I20: =iferror(vlookup(B20,'セッション実施状況管理'!$A:$B,2,false),"") -> 卒業 | J20: 0 | K20: 2 | L20: =VLOOKUP(B20,'新 月次投稿数'!$A:$N,13,false) -> 89 | M20: =IF(L20>=120, 3, IF(L20>=100, 2, IF(L20>=80, 1, IF(L20>=60, 0, IF(L20>=40, -1, IF(L20>=20, -2, -3)))))) -> 1 | N20: =IF(Q20>=540, 4, IF(Q20>=480, 3, IF(Q20>=420, 2, IF(Q20>=360, 1, IF(Q20>=300, 0, IF(Q20>=240, -1, -2)))))) -> 4 | O20: =IF(P20>=540, 4, IF(P20>=480, 3, IF(P20>=420, 2, IF(P20>=360, 1, IF(P20>=300, 0, IF(P20>=240, -1, -2)))))) -> -1 | P20: =sum(T20:Z20) -> 289 | Q20: =R20*6 -> 867 | R20: =iferror(P20/S20,"0") -> 144.5 | S20: =count(T20:Z20) -> 2 | T20: ー | U20: ー | V20: ー | W20: ー | X20: ー | Y20: 190 | Z20: 99 | AA20: =Vlookup(B20,'セッション実施状況管理'!$A:$R,17,false) -> - | AB20: =(YEAR(TODAY()) - YEAR($AA20)) * 12 + (MONTH(TODAY()) - MONTH($AA20)) -> #VALUE! | AC20: =IF( OR(AB20=3, AB20=4, AB20=5, AB20=6), "1", "2" ) -> #VALUE!
B21: 3 | C21: =vlookup(B21,'セッション実施状況管理'!$A:$U,8,false) -> ふじたなな | D21: =vlookup(B21,'セッション実施状況管理'!$A:$I,9,false) -> ta_ma_diet | E21: https://docs.google.com/spreadsheets/d/13WYWfgJBL9cRnrDfXGMTMyu-O1Oo2N6x-99iOo9amV0/edit#gid=159884613 | F21: =vlookup(B21,'セッション実施状況管理'!$A:$U,20,false) -> 森本風花 | G21: =vlookup(B21,'セッション実施状況管理'!$A:$U,20,false) -> 森本風花 | H21: ='コーチング報酬管理'!G9 -> 13 | I21: =iferror(vlookup(B21,'セッション実施状況管理'!$A:$B,2,false),"") -> 卒業 | J21: 0 | K21: 0 | L21: =VLOOKUP(B21,'新 月次投稿数'!$A:$N,13,false) -> 0 | M21: =IF(L21>=120, 3, IF(L21>=100, 2, IF(L21>=80, 1, IF(L21>=60, 0, IF(L21>=40, -1, IF(L21>=20, -2, -3)))))) -> -3 | N21: =IF(Q21>=540, 4, IF(Q21>=480, 3, IF(Q21>=420, 2, IF(Q21>=360, 1, IF(Q21>=300, 0, IF(Q21>=240, -1, -2)))))) -> -2 | O21: =IF(P21>=540, 4, IF(P21>=480, 3, IF(P21>=420, 2, IF(P21>=360, 1, IF(P21>=300, 0, IF(P21>=240, -1, -2)))))) -> -2 | P21: =sum(T21:Z21) -> 78 | Q21: =R21*6 -> 156 | R21: =iferror(P21/S21,"0") -> 26 | S21: =count(T21:Z21) -> 3 | T21: ー | U21: ー | V21: ー | W21: ー | X21: 18 | Y21: 41 | Z21: 19 | AA21: =Vlookup(B21,'セッション実施状況管理'!$A:$R,17,false) | AB21: =(YEAR(TODAY()) - YEAR($AA21)) * 12 + (MONTH(TODAY()) - MONTH($AA21)) -> 1514 | AC21: =IF( OR(AB21=3, AB21=4, AB21=5, AB21=6), "1", "2" ) -> 2
B22: 4 | C22: =vlookup(B22,'セッション実施状況管理'!$A:$U,8,false) -> よしだむつみ | D22: =vlookup(B22,'セッション実施状況管理'!$A:$I,9,false) -> adhd_nao | E22: https://docs.google.com/spreadsheets/d/1P7lV1jvZjxbK1uZ7NM7uhW3LAsP0PYvQKrq7aPBsOk4/edit?usp=sharing | F22: =vlookup(B22,'セッション実施状況管理'!$A:$U,20,false) -> 野村佑佳 | G22: =vlookup(B22,'セッション実施状況管理'!$A:$U,20,false) -> 野村佑佳 | H22: ='コーチング報酬管理'!G10 -> 13 | I22: =iferror(vlookup(B22,'セッション実施状況管理'!$A:$B,2,false),"") -> 卒業 | J22: 0 | K22: 0 | L22: =VLOOKUP(B22,'新 月次投稿数'!$A:$N,13,false) -> 0 | M22: =IF(L22>=120, 3, IF(L22>=100, 2, IF(L22>=80, 1, IF(L22>=60, 0, IF(L22>=40, -1, IF(L22>=20, -2, -3)))))) -> -3 | N22: =IF(Q22>=540, 4, IF(Q22>=480, 3, IF(Q22>=420, 2, IF(Q22>=360, 1, IF(Q22>=300, 0, IF(Q22>=240, -1, -2)))))) -> -2 | O22: =IF(P22>=540, 4, IF(P22>=480, 3, IF(P22>=420, 2, IF(P22>=360, 1, IF(P22>=300, 0, IF(P22>=240, -1, -2)))))) -> -2 | P22: =sum(T22:Z22) -> 74 | Q22: =R22*6 -> 148 | R22: =iferror(P22/S22,"0") -> 24.666667 | S22: =count(T22:Z22) -> 3 | T22: ー | U22: ー | V22: ― | W22: ― | X22: 74 | Y22: 0 | Z22: 0 | AA22: =Vlookup(B22,'セッション実施状況管理'!$A:$R,17,false) | AB22: =(YEAR(TODAY()) - YEAR($AA22)) * 12 + (MONTH(TODAY()) - MONTH($AA22)) -> 1514 | AC22: =IF( OR(AB22=3, AB22=4, AB22=5, AB22=6), "1", "2" ) -> 2
B23: 5 | C23: =vlookup(B23,'セッション実施状況管理'!$A:$U,8,false) -> きたがわたかひろ | D23: =vlookup(B23,'セッション実施状況管理'!$A:$I,9,false) -> kcc_0113 | E23: https://docs.google.com/spreadsheets/d/1dDsldPC_LoIFAFPjNSBbpMJoKhvVhpWWe__BpOst8ig/edit | F23: =vlookup(B23,'セッション実施状況管理'!$A:$U,20,false) -> 豊榮信江 | G23: =vlookup(B23,'セッション実施状況管理'!$A:$U,20,false) -> 豊榮信江 | H23: ='コーチング報酬管理'!G11 -> 12 | I23: =iferror(vlookup(B23,'セッション実施状況管理'!$A:$B,2,false),"") -> 卒業 | J23: 0 | K23: 0 | L23: =VLOOKUP(B23,'新 月次投稿数'!$A:$N,13,false) -> 0 | M23: =IF(L23>=120, 3, IF(L23>=100, 2, IF(L23>=80, 1, IF(L23>=60, 0, IF(L23>=40, -1, IF(L23>=20, -2, -3)))))) -> -3 | N23: =IF(Q23>=540, 4, IF(Q23>=480, 3, IF(Q23>=420, 2, IF(Q23>=360, 1, IF(Q23>=300, 0, IF(Q23>=240, -1, -2)))))) -> -2 | O23: =IF(P23>=540, 4, IF(P23>=480, 3, IF(P23>=420, 2, IF(P23>=360, 1, IF(P23>=300, 0, IF(P23>=240, -1, -2)))))) -> -2 | P23: =sum(T23:Z23) -> 136 | Q23: =R23*6 -> 204 | R23: =iferror(P23/S23,"0") -> 34 | S23: =count(T23:Z23) -> 4 | T23: ー | U23: ー | V23: ー | W23: 3 | X23: 73 | Y23: 44 | Z23: 16 | AA23: =Vlookup(B23,'セッション実施状況管理'!$A:$R,17,false) | AB23: =(YEAR(TODAY()) - YEAR($AA23)) * 12 + (MONTH(TODAY()) - MONTH($AA23)) -> 1514 | AC23: =IF( OR(AB23=3, AB23=4, AB23=5, AB23=6), "1", "2" ) -> 2
B24: 6 | C24: =vlookup(B24,'セッション実施状況管理'!$A:$U,8,false) -> ありやまゆうな | D24: =vlookup(B24,'セッション実施状況管理'!$A:$I,9,false) -> uni_beer_ | E24: https://docs.google.com/spreadsheets/d/1VF6-P-SWrjPNTkdevk6pBPF7_eKqo9Y4HqFzaHa75IY/edit?usp=sharing | F24: =vlookup(B24,'セッション実施状況管理'!$A:$U,20,false) -> 野村佑佳 | G24: =vlookup(B24,'セッション実施状況管理'!$A:$U,20,false) -> 野村佑佳 | H24: ='コーチング報酬管理'!G13 -> 13 | I24: =iferror(vlookup(B24,'セッション実施状況管理'!$A:$B,2,false),"") -> 卒業 | J24: 0 | K24: 2 | L24: =VLOOKUP(B24,'新 月次投稿数'!$A:$N,13,false) -> 102 | M24: =IF(L24>=120, 3, IF(L24>=100, 2, IF(L24>=80, 1, IF(L24>=60, 0, IF(L24>=40, -1, IF(L24>=20, -2, -3)))))) -> 2 | N24: =IF(Q24>=540, 4, IF(Q24>=480, 3, IF(Q24>=420, 2, IF(Q24>=360, 1, IF(Q24>=300, 0, IF(Q24>=240, -1, -2)))))) -> 4 | O24: =IF(P24>=540, 4, IF(P24>=480, 3, IF(P24>=420, 2, IF(P24>=360, 1, IF(P24>=300, 0, IF(P24>=240, -1, -2)))))) -> 4 | P24: =sum(T24:Z24) -> 829 | Q24: =R24*6 -> 829 | R24: =iferror(P24/S24,"0") -> 138.16667 | S24: =count(T24:Z24) -> 6 | T24: ー | U24: 195 | V24: 186 | W24: 189 | X24: 101 | Y24: 95 | Z24: 63 | AA24: =Vlookup(B24,'セッション実施状況管理'!$A:$R,17,false) | AB24: =(YEAR(TODAY()) - YEAR($AA24)) * 12 + (MONTH(TODAY()) - MONTH($AA24)) -> 1514 | AC24: =IF( OR(AB24=3, AB24=4, AB24=5, AB24=6), "1", "2" ) -> 2
B25: 7 | C25: =vlookup(B25,'セッション実施状況管理'!$A:$U,8,false) -> たけにしゆかり | D25: =vlookup(B25,'セッション実施状況管理'!$A:$I,9,false) -> yukari_dekirumon | E25: https://docs.google.com/spreadsheets/d/1FDgWv1TaU7NONEzy8isYhtlzxGj8bpfooK0xi56QQQI/edit?usp=sharing | F25: =vlookup(B25,'セッション実施状況管理'!$A:$U,20,false) -> 宮田友理 | G25: =vlookup(B25,'セッション実施状況管理'!$A:$U,20,false) -> 宮田友理 | H25: ='コーチング報酬管理'!G14 -> 13 | I25: =iferror(vlookup(B25,'セッション実施状況管理'!$A:$B,2,false),"") -> 卒業 | J25: 0 | K25: 0 | L25: =VLOOKUP(B25,'新 月次投稿数'!$A:$N,13,false) -> 6 | M25: =IF(L25>=120, 3, IF(L25>=100, 2, IF(L25>=80, 1, IF(L25>=60, 0, IF(L25>=40, -1, IF(L25>=20, -2, -3)))))) -> -3 | N25: =IF(Q25>=540, 4, IF(Q25>=480, 3, IF(Q25>=420, 2, IF(Q25>=360, 1, IF(Q25>=300, 0, IF(Q25>=240, -1, -2)))))) -> -2 | O25: =IF(P25>=540, 4, IF(P25>=480, 3, IF(P25>=420, 2, IF(P25>=360, 1, IF(P25>=300, 0, IF(P25>=240, -1, -2)))))) -> -2 | P25: =sum(T25:Z25) -> 18 | Q25: =R25*6 -> 18 | R25: =iferror(P25/S25,"0") -> 3 | S25: =count(T25:Z25) -> 6 | T25: ー | U25: 17 | V25: 1 | W25: 0 | X25: 0 | Y25: 0 | Z25: 0 | AA25: =Vlookup(B25,'セッション実施状況管理'!$A:$R,17,false) | AB25: =(YEAR(TODAY()) - YEAR($AA25)) * 12 + (MONTH(TODAY()) - MONTH($AA25)) -> 1514 | AC25: =IF( OR(AB25=3, AB25=4, AB25=5, AB25=6), "1", "2" ) -> 2
B26: 8 | C26: =vlookup(B26,'セッション実施状況管理'!$A:$U,8,false) -> くどうゆみこ | D26: =vlookup(B26,'セッション実施状況管理'!$A:$I,9,false) -> くどうゆみこ | E26: https://docs.google.com/spreadsheets/d/16gm19l8AK-WT0DiGdwsvCSYJyap52t5KdnlJ7ASvaSQ/edit?usp=sharing | F26: =vlookup(B26,'セッション実施状況管理'!$A:$U,20,false) -> 野村佑佳 | G26: =vlookup(B26,'セッション実施状況管理'!$A:$U,20,false) -> 野村佑佳 | H26: ='コーチング報酬管理'!G15 -> 13 | I26: =iferror(vlookup(B26,'セッション実施状況管理'!$A:$B,2,false),"") -> 卒業 | J26: 0 | K26: 0 | L26: =VLOOKUP(B26,'新 月次投稿数'!$A:$N,13,false) -> 45 | M26: =IF(L26>=120, 3, IF(L26>=100, 2, IF(L26>=80, 1, IF(L26>=60, 0, IF(L26>=40, -1, IF(L26>=20, -2, -3)))))) -> -1 | N26: =IF(Q26>=540, 4, IF(Q26>=480, 3, IF(Q26>=420, 2, IF(Q26>=360, 1, IF(Q26>=300, 0, IF(Q26>=240, -1, -2)))))) -> -2 | O26: =IF(P26>=540, 4, IF(P26>=480, 3, IF(P26>=420, 2, IF(P26>=360, 1, IF(P26>=300, 0, IF(P26>=240, -1, -2)))))) -> -2 | P26: =sum(T26:Z26) -> 0 | Q26: =R26*6 -> 0 | R26: =iferror(P26/S26,"0") -> 0 | S26: =count(T26:Z26) -> 0 | T26: ー | U26: ー | V26: ー | W26: ー | X26: ー | Y26: ー | Z26: ー | AA26: =Vlookup(B26,'セッション実施状況管理'!$A:$R,17,false) | AB26: =(YEAR(TODAY()) - YEAR($AA26)) * 12 + (MONTH(TODAY()) - MONTH($AA26)) -> 1514 | AC26: =IF( OR(AB26=3, AB26=4, AB26=5, AB26=6), "1", "2" ) -> 2
B27: 9 | C27: =vlookup(B27,'セッション実施状況管理'!$A:$U,8,false) -> たわらかずみ | D27: =vlookup(B27,'セッション実施状況管理'!$A:$I,9,false) -> negi_mamalife | E27: https://docs.google.com/spreadsheets/d/1VcZW6sZO5CzEjG-LGvBO6r1yQjJicqYLWUDbBD9Pw2E/edit | F27: =vlookup(B27,'セッション実施状況管理'!$A:$U,20,false) -> 中村恵理 | G27: =vlookup(B27,'セッション実施状況管理'!$A:$U,20,false) -> 中村恵理 | H27: ='コーチング報酬管理'!G16 -> 13 | I27: =iferror(vlookup(B27,'セッション実施状況管理'!$A:$B,2,false),"") -> 卒業 | J27: 0 | K27: 0 | L27: =VLOOKUP(B27,'新 月次投稿数'!$A:$N,13,false) -> 109 | M27: =IF(L27>=120, 3, IF(L27>=100, 2, IF(L27>=80, 1, IF(L27>=60, 0, IF(L27>=40, -1, IF(L27>=20, -2, -3)))))) -> 2 | N27: =IF(Q27>=540, 4, IF(Q27>=480, 3, IF(Q27>=420, 2, IF(Q27>=360, 1, IF(Q27>=300, 0, IF(Q27>=240, -1, -2)))))) -> 3 | O27: =IF(P27>=540, 4, IF(P27>=480, 3, IF(P27>=420, 2, IF(P27>=360, 1, IF(P27>=300, 0, IF(P27>=240, -1, -2)))))) -> -1 | P27: =sum(T27:Z27) -> 247 | Q27: =R27*6 -> 494 | R27: =iferror(P27/S27,"0") -> 82.333333 | S27: =count(T27:Z27) -> 3 | T27: ー | U27: ー | V27: ー | W27: ー | X27: 112 | Y27: 102 | Z27: 33 | AA27: =Vlookup(B27,'セッション実施状況管理'!$A:$R,17,false) | AB27: =(YEAR(TODAY()) - YEAR($AA27)) * 12 + (MONTH(TODAY()) - MONTH($AA27)) -> 1514 | AC27: =IF( OR(AB27=3, AB27=4, AB27=5, AB27=6), "1", "2" ) -> 2
B28: 10 | C28: =vlookup(B28,'セッション実施状況管理'!$A:$U,8,false) -> やまぐちしんいちろう | D28: =vlookup(B28,'セッション実施状況管理'!$A:$I,9,false) -> tewofuru_woodjewelry | E28: https://docs.google.com/spreadsheets/d/1HGYcq04YAsY7AfEQsu6pG2qTM6XEKBkaugZcBIDQ6MI/edit#gid=159884613 | F28: =vlookup(B28,'セッション実施状況管理'!$A:$U,20,false) -> 森本風花 | G28: =vlookup(B28,'セッション実施状況管理'!$A:$U,20,false) -> 森本風花 | H28: ='コーチング報酬管理'!G17 -> 13 | I28: =iferror(vlookup(B28,'セッション実施状況管理'!$A:$B,2,false),"") -> 卒業 | J28: 0 | K28: 0 | L28: =VLOOKUP(B28,'新 月次投稿数'!$A:$N,13,false) -> 128 | M28: =IF(L28>=120, 3, IF(L28>=100, 2, IF(L28>=80, 1, IF(L28>=60, 0, IF(L28>=40, -1, IF(L28>=20, -2, -3)))))) -> 3 | N28: =IF(Q28>=540, 4, IF(Q28>=480, 3, IF(Q28>=420, 2, IF(Q28>=360, 1, IF(Q28>=300, 0, IF(Q28>=240, -1, -2)))))) -> 4 | O28: =IF(P28>=540, 4, IF(P28>=480, 3, IF(P28>=420, 2, IF(P28>=360, 1, IF(P28>=300, 0, IF(P28>=240, -1, -2)))))) -> 1 | P28: =sum(T28:Z28) -> 388 | Q28: =R28*6 -> 776 | R28: =iferror(P28/S28,"0") -> 129.33333 | S28: =count(T28:Z28) -> 3 | T28: ー | U28: ー | V28: ー | W28: ー | X28: 138 | Y28: 176 | Z28: 74 | AA28: =Vlookup(B28,'セッション実施状況管理'!$A:$R,17,false) | AB28: =(YEAR(TODAY()) - YEAR($AA28)) * 12 + (MONTH(TODAY()) - MONTH($AA28)) -> 1514 | AC28: =IF( OR(AB28=3, AB28=4, AB28=5, AB28=6), "1", "2" ) -> 2
B29: 11 | C29: =vlookup(B29,'セッション実施状況管理'!$A:$U,8,false) -> かわかみまさと | D29: =vlookup(B29,'セッション実施状況管理'!$A:$I,9,false) -> satojitan_recipe | E29: https://docs.google.com/spreadsheets/d/1CJI2fnbP3Vn3MKDn_UAnEjJBoPYa8N4JiLFiYx3GYSs/edit?usp=sharing | F29: =vlookup(B29,'セッション実施状況管理'!$A:$U,20,false) -> 野村佑佳 | G29: =vlookup(B29,'セッション実施状況管理'!$A:$U,20,false) -> 野村佑佳 | H29: ='コーチング報酬管理'!G18 -> 13 | I29: =iferror(vlookup(B29,'セッション実施状況管理'!$A:$B,2,false),"") -> 卒業 | J29: 0 | K29: 0 | L29: =VLOOKUP(B29,'新 月次投稿数'!$A:$N,13,false) -> 14 | M29: =IF(L29>=120, 3, IF(L29>=100, 2, IF(L29>=80, 1, IF(L29>=60, 0, IF(L29>=40, -1, IF(L29>=20, -2, -3)))))) -> -3 | N29: =IF(Q29>=540, 4, IF(Q29>=480, 3, IF(Q29>=420, 2, IF(Q29>=360, 1, IF(Q29>=300, 0, IF(Q29>=240, -1, -2)))))) -> 1 | O29: =IF(P29>=540, 4, IF(P29>=480, 3, IF(P29>=420, 2, IF(P29>=360, 1, IF(P29>=300, 0, IF(P29>=240, -1, -2)))))) -> -1 | P29: =sum(T29:Z29) -> 252 | Q29: =R29*6 -> 378 | R29: =iferror(P29/S29,"0") -> 63 | S29: =count(T29:Z29) -> 4 | T29: ー | U29: ー | V29: ー | W29: 83 | X29: 79 | Y29: 90 | Z29: 0 | AA29: =Vlookup(B29,'セッション実施状況管理'!$A:$R,17,false) | AB29: =(YEAR(TODAY()) - YEAR($AA29)) * 12 + (MONTH(TODAY()) - MONTH($AA29)) -> 1514 | AC29: =IF( OR(AB29=3, AB29=4, AB29=5, AB29=6), "1", "2" ) -> 2
B30: 12 | C30: =vlookup(B30,'セッション実施状況管理'!$A:$U,8,false) -> すどうえり | D30: =vlookup(B30,'セッション実施状況管理'!$A:$I,9,false) -> richan_hair | E30: https://docs.google.com/spreadsheets/d/1R0rLpzIT3lOxy9m047XlKioLu3_bwzVy7h6N7-L9qhg/edit?usp=sharing | F30: =vlookup(B30,'セッション実施状況管理'!$A:$U,20,false) -> 宮田友理 | G30: =vlookup(B30,'セッション実施状況管理'!$A:$U,20,false) -> 宮田友理 | H30: ='コーチング報酬管理'!G19 -> 13 | I30: =iferror(vlookup(B30,'セッション実施状況管理'!$A:$B,2,false),"") -> 卒業 | J30: 0 | K30: 0 | L30: =VLOOKUP(B30,'新 月次投稿数'!$A:$N,13,false) -> 0 | M30: =IF(L30>=120, 3, IF(L30>=100, 2, IF(L30>=80, 1, IF(L30>=60, 0, IF(L30>=40, -1, IF(L30>=20, -2, -3)))))) -> -3 | N30: =IF(Q30>=540, 4, IF(Q30>=480, 3, IF(Q30>=420, 2, IF(Q30>=360, 1, IF(Q30>=300, 0, IF(Q30>=240, -1, -2)))))) -> -1 | O30: =IF(P30>=540, 4, IF(P30>=480, 3, IF(P30>=420, 2, IF(P30>=360, 1, IF(P30>=300, 0, IF(P30>=240, -1, -2)))))) -> -2 | P30: =sum(T30:Z30) -> 224 | Q30: =R30*6 -> 268.8 | R30: =iferror(P30/S30,"0") -> 44.8 | S30: =count(T30:Z30) -> 5 | T30: ー | U30: ー | V30: 11 | W30: 59 | X30: 77 | Y30: 71 | Z30: 6 | AA30: =Vlookup(B30,'セッション実施状況管理'!$A:$R,17,false) | AB30: =(YEAR(TODAY()) - YEAR($AA30)) * 12 + (MONTH(TODAY()) - MONTH($AA30)) -> 1514 | AC30: =IF( OR(AB30=3, AB30=4, AB30=5, AB30=6), "1", "2" ) -> 2
B31: 13 | C31: =vlookup(B31,'セッション実施状況管理'!$A:$U,8,false) -> なかのあや | D31: =vlookup(B31,'セッション実施状況管理'!$A:$I,9,false) -> aya_travel_europe | E31: https://docs.google.com/spreadsheets/d/1iiVwBPeuCtVinoSA2fND9peuWwfCzWoX3eywaLQp80s/edit?usp=sharing | F31: =vlookup(B31,'セッション実施状況管理'!$A:$U,20,false) -> 清原三和子 | G31: =vlookup(B31,'セッション実施状況管理'!$A:$U,20,false) -> 清原三和子 | H31: ='コーチング報酬管理'!G20 -> 13 | I31: =iferror(vlookup(B31,'セッション実施状況管理'!$A:$B,2,false),"") -> 卒業 | J31: 0 | K31: 0 | L31: =VLOOKUP(B31,'新 月次投稿数'!$A:$N,13,false) -> 19 | M31: =IF(L31>=120, 3, IF(L31>=100, 2, IF(L31>=80, 1, IF(L31>=60, 0, IF(L31>=40, -1, IF(L31>=20, -2, -3)))))) -> -3 | N31: =IF(Q31>=540, 4, IF(Q31>=480, 3, IF(Q31>=420, 2, IF(Q31>=360, 1, IF(Q31>=300, 0, IF(Q31>=240, -1, -2)))))) -> -2 | O31: =IF(P31>=540, 4, IF(P31>=480, 3, IF(P31>=420, 2, IF(P31>=360, 1, IF(P31>=300, 0, IF(P31>=240, -1, -2)))))) -> -2 | P31: =sum(T31:Z31) -> 152 | Q31: =R31*6 -> 182.4 | R31: =iferror(P31/S31,"0") -> 30.4 | S31: =count(T31:Z31) -> 5 | T31: ー | U31: ー | V31: 1 | W31: 83 | X31: 61 | Y31: 2 | Z31: 5 | AA31: =Vlookup(B31,'セッション実施状況管理'!$A:$R,17,false) | AB31: =(YEAR(TODAY()) - YEAR($AA31)) * 12 + (MONTH(TODAY()) - MONTH($AA31)) -> 1514 | AC31: =IF( OR(AB31=3, AB31=4, AB31=5, AB31=6), "1", "2" ) -> 2
B32: 14 | C32: =vlookup(B32,'セッション実施状況管理'!$A:$U,8,false) -> うちだあやみ | D32: =vlookup(B32,'セッション実施状況管理'!$A:$I,9,false) -> uchiko_gohan | E32: https://docs.google.com/spreadsheets/d/1HmZ5bY36oJDddcl9k45VoZMs7Ee2FgjZedYnnPCEWyg/edit?usp=sharing | F32: =vlookup(B32,'セッション実施状況管理'!$A:$U,20,false) -> 清原三和子 | G32: =vlookup(B32,'セッション実施状況管理'!$A:$U,20,false) -> 清原三和子 | H32: ='コーチング報酬管理'!G21 -> 13 | I32: =iferror(vlookup(B32,'セッション実施状況管理'!$A:$B,2,false),"") -> 卒業 | J32: 0 | K32: 2 | L32: =VLOOKUP(B32,'新 月次投稿数'!$A:$N,13,false) -> 63 | M32: =IF(L32>=120, 3, IF(L32>=100, 2, IF(L32>=80, 1, IF(L32>=60, 0, IF(L32>=40, -1, IF(L32>=20, -2, -3)))))) -> 0 | N32: =IF(Q32>=540, 4, IF(Q32>=480, 3, IF(Q32>=420, 2, IF(Q32>=360, 1, IF(Q32>=300, 0, IF(Q32>=240, -1, -2)))))) -> 4 | O32: =IF(P32>=540, 4, IF(P32>=480, 3, IF(P32>=420, 2, IF(P32>=360, 1, IF(P32>=300, 0, IF(P32>=240, -1, -2)))))) -> 3 | P32: =sum(T32:Z32) -> 511 | Q32: =R32*6 -> 613.2 | R32: =iferror(P32/S32,"0") -> 102.2 | S32: =count(T32:Z32) -> 5 | T32: ー | U32: ー | V32: 18 | W32: 70 | X32: 113 | Y32: 190 | Z32: 120 | AA32: =Vlookup(B32,'セッション実施状況管理'!$A:$R,17,false) | AB32: =(YEAR(TODAY()) - YEAR($AA32)) * 12 + (MONTH(TODAY()) - MONTH($AA32)) -> 1514 | AC32: =IF( OR(AB32=3, AB32=4, AB32=5, AB32=6), "1", "2" ) -> 2
B33: 15 | C33: =vlookup(B33,'セッション実施状況管理'!$A:$U,8,false) -> さかもとなみこ | D33: =vlookup(B33,'セッション実施状況管理'!$A:$I,9,false) -> hiroyukichan_renai | E33: https://docs.google.com/spreadsheets/d/1zfFRF0yMhvb2WXHz1HWEfZslrgg0zfEeBfQRp2QCk5g/edit#gid=1519876919 | F33: =vlookup(B33,'セッション実施状況管理'!$A:$U,20,false) -> 山見阪佳子 | G33: =vlookup(B33,'セッション実施状況管理'!$A:$U,20,false) -> 山見阪佳子 | H33: ='コーチング報酬管理'!G22 -> 12 | I33: =iferror(vlookup(B33,'セッション実施状況管理'!$A:$B,2,false),"") -> 卒業 | J33: 0 | K33: 0 | L33: =VLOOKUP(B33,'新 月次投稿数'!$A:$N,13,false) -> 108 | M33: =IF(L33>=120, 3, IF(L33>=100, 2, IF(L33>=80, 1, IF(L33>=60, 0, IF(L33>=40, -1, IF(L33>=20, -2, -3)))))) -> 2 | N33: =IF(Q33>=540, 4, IF(Q33>=480, 3, IF(Q33>=420, 2, IF(Q33>=360, 1, IF(Q33>=300, 0, IF(Q33>=240, -1, -2)))))) -> 4 | O33: =IF(P33>=540, 4, IF(P33>=480, 3, IF(P33>=420, 2, IF(P33>=360, 1, IF(P33>=300, 0, IF(P33>=240, -1, -2)))))) -> 3 | P33: =sum(T33:Z33) -> 492 | Q33: =R33*6 -> 738 | R33: =iferror(P33/S33,"0") -> 123 | S33: =count(T33:Z33) -> 4 | T33: ー | U33: ー | V33: ー | W33: 24 | X33: 171 | Y33: 197 | Z33: 100 | AA33: =Vlookup(B33,'セッション実施状況管理'!$A:$R,17,false) | AB33: =(YEAR(TODAY()) - YEAR($AA33)) * 12 + (MONTH(TODAY()) - MONTH($AA33)) -> 1514 | AC33: =IF( OR(AB33=3, AB33=4, AB33=5, AB33=6), "1", "2" ) -> 2
B34: 16 | C34: =vlookup(B34,'セッション実施状況管理'!$A:$U,8,false) -> あいざわくみこ | D34: =vlookup(B34,'セッション実施状況管理'!$A:$I,9,false) -> okumi_mind | E34: https://docs.google.com/spreadsheets/d/1eYeCKwGOsr3UdyrLNCD3X4OjKsTIJY_ai0fbcC5upAs/edit?usp=sharing | F34: =vlookup(B34,'セッション実施状況管理'!$A:$U,20,false) -> 清原三和子 | G34: =vlookup(B34,'セッション実施状況管理'!$A:$U,20,false) -> 清原三和子 | H34: ='コーチング報酬管理'!G23 -> 12 | I34: =iferror(vlookup(B34,'セッション実施状況管理'!$A:$B,2,false),"") -> 卒業 | J34: 0 | K34: 0 | L34: =VLOOKUP(B34,'新 月次投稿数'!$A:$N,13,false) -> 57 | M34: =IF(L34>=120, 3, IF(L34>=100, 2, IF(L34>=80, 1, IF(L34>=60, 0, IF(L34>=40, -1, IF(L34>=20, -2, -3)))))) -> -1 | N34: =IF(Q34>=540, 4, IF(Q34>=480, 3, IF(Q34>=420, 2, IF(Q34>=360, 1, IF(Q34>=300, 0, IF(Q34>=240, -1, -2)))))) -> 2 | O34: =IF(P34>=540, 4, IF(P34>=480, 3, IF(P34>=420, 2, IF(P34>=360, 1, IF(P34>=300, 0, IF(P34>=240, -1, -2)))))) -> -2 | P34: =sum(T34:Z34) -> 211 | Q34: =R34*6 -> 422 | R34: =iferror(P34/S34,"0") -> 70.333333 | S34: =count(T34:Z34) -> 3 | T34: ー | U34: ー | V34: ー | W34: ー | X34: 98 | Y34: 98 | Z34: 15 | AA34: =Vlookup(B34,'セッション実施状況管理'!$A:$R,17,false) | AB34: =(YEAR(TODAY()) - YEAR($AA34)) * 12 + (MONTH(TODAY()) - MONTH($AA34)) -> 1514 | AC34: =IF( OR(AB34=3, AB34=4, AB34=5, AB34=6), "1", "2" ) -> 2
B35: 17 | C35: =vlookup(B35,'セッション実施状況管理'!$A:$U,8,false) -> よこやまあいと | D35: =vlookup(B35,'セッション実施状況管理'!$A:$I,9,false) -> satousanni_kokuhaku | E35: https://docs.google.com/spreadsheets/d/1YdNzqMy28X-4Ca9gLPF9a2ClrGb8sZP0ZUJPbnIPOJc/edit?gid=0#gid=0 | F35: =vlookup(B35,'セッション実施状況管理'!$A:$U,20,false) -> 福田康裕 | G35: =vlookup(B35,'セッション実施状況管理'!$A:$U,20,false) -> 福田康裕 | H35: ='コーチング報酬管理'!G24 -> 13 | I35: =iferror(vlookup(B35,'セッション実施状況管理'!$A:$B,2,false),"") -> 卒業 | J35: 0 | K35: 0 | L35: =VLOOKUP(B35,'新 月次投稿数'!$A:$N,13,false) -> 52 | M35: =IF(L35>=120, 3, IF(L35>=100, 2, IF(L35>=80, 1, IF(L35>=60, 0, IF(L35>=40, -1, IF(L35>=20, -2, -3)))))) -> -1 | N35: =IF(Q35>=540, 4, IF(Q35>=480, 3, IF(Q35>=420, 2, IF(Q35>=360, 1, IF(Q35>=300, 0, IF(Q35>=240, -1, -2)))))) -> 1 | O35: =IF(P35>=540, 4, IF(P35>=480, 3, IF(P35>=420, 2, IF(P35>=360, 1, IF(P35>=300, 0, IF(P35>=240, -1, -2)))))) -> -1 | P35: =sum(T35:Z35) -> 243 | Q35: =R35*6 -> 364.5 | R35: =iferror(P35/S35,"0") -> 60.75 | S35: =count(T35:Z35) -> 4 | T35: ー | U35: ー | V35: ー | W35: 203 | X35: 40 | Y35: 0 | Z35: 0 | AA35: =Vlookup(B35,'セッション実施状況管理'!$A:$R,17,false) | AB35: =(YEAR(TODAY()) - YEAR($AA35)) * 12 + (MONTH(TODAY()) - MONTH($AA35)) -> 1514 | AC35: =IF( OR(AB35=3, AB35=4, AB35=5, AB35=6), "1", "2" ) -> 2
B36: 18 | C36: =vlookup(B36,'セッション実施状況管理'!$A:$U,8,false) -> ふちがみあや | D36: =vlookup(B36,'セッション実施状況管理'!$A:$I,9,false) -> aya_zubora | E36: https://docs.google.com/spreadsheets/d/1P3zoWs4wk923BxN-pxOOJCmM7T9U9KCwSopcluoqnls/edit?gid=0#gid=0 | F36: =vlookup(B36,'セッション実施状況管理'!$A:$U,20,false) -> 山見阪佳子 | G36: =vlookup(B36,'セッション実施状況管理'!$A:$U,20,false) -> 山見阪佳子 | H36: ='コーチング報酬管理'!G25 -> 13 | I36: =iferror(vlookup(B36,'セッション実施状況管理'!$A:$B,2,false),"") -> 卒業 | J36: 0 | K36: 0 | L36: =VLOOKUP(B36,'新 月次投稿数'!$A:$N,13,false) -> 14 | M36: =IF(L36>=120, 3, IF(L36>=100, 2, IF(L36>=80, 1, IF(L36>=60, 0, IF(L36>=40, -1, IF(L36>=20, -2, -3)))))) -> -3 | N36: =IF(Q36>=540, 4, IF(Q36>=480, 3, IF(Q36>=420, 2, IF(Q36>=360, 1, IF(Q36>=300, 0, IF(Q36>=240, -1, -2)))))) -> -2 | O36: =IF(P36>=540, 4, IF(P36>=480, 3, IF(P36>=420, 2, IF(P36>=360, 1, IF(P36>=300, 0, IF(P36>=240, -1, -2)))))) -> -2 | P36: =sum(T36:Z36) -> 51 | Q36: =R36*6 -> 51 | R36: =iferror(P36/S36,"0") -> 8.5 | S36: =count(T36:Z36) -> 6 | T36: ー | U36: 40 | V36: 11 | W36: 0 | X36: 0 | Y36: 0 | Z36: 0 | AA36: =Vlookup(B36,'セッション実施状況管理'!$A:$R,17,false) | AB36: =(YEAR(TODAY()) - YEAR($AA36)) * 12 + (MONTH(TODAY()) - MONTH($AA36)) -> 1514 | AC36: =IF( OR(AB36=3, AB36=4, AB36=5, AB36=6), "1", "2" ) -> 2
B37: 19 | C37: =vlookup(B37,'セッション実施状況管理'!$A:$U,8,false) -> おおにしちかこ | D37: =vlookup(B37,'セッション実施状況管理'!$A:$I,9,false) -> ginza_arch | E37: https://docs.google.com/spreadsheets/d/1XatV0nRbZnvl1QKJ6wXlGpdTKpzOQ7rcEl887_pX_-c/edit?usp=sharing | F37: =vlookup(B37,'セッション実施状況管理'!$A:$U,20,false) -> 須見浩人 | G37: =vlookup(B37,'セッション実施状況管理'!$A:$U,20,false) -> 須見浩人 | H37: ='コーチング報酬管理'!G26 -> 13 | I37: =iferror(vlookup(B37,'セッション実施状況管理'!$A:$B,2,false),"") -> 卒業 | J37: 0 | K37: 0 | L37: =VLOOKUP(B37,'新 月次投稿数'!$A:$N,13,false) -> 13 | M37: =IF(L37>=120, 3, IF(L37>=100, 2, IF(L37>=80, 1, IF(L37>=60, 0, IF(L37>=40, -1, IF(L37>=20, -2, -3)))))) -> -3 | N37: =IF(Q37>=540, 4, IF(Q37>=480, 3, IF(Q37>=420, 2, IF(Q37>=360, 1, IF(Q37>=300, 0, IF(Q37>=240, -1, -2)))))) -> -2 | O37: =IF(P37>=540, 4, IF(P37>=480, 3, IF(P37>=420, 2, IF(P37>=360, 1, IF(P37>=300, 0, IF(P37>=240, -1, -2)))))) -> -2 | P37: =sum(T37:Z37) -> 5 | Q37: =R37*6 -> 4.2857143 | R37: =iferror(P37/S37,"0") -> 0.71428571 | S37: =count(T37:Z37) -> 7 | T37: 5 | U37: 0 | V37: 0 | W37: 0 | X37: 0 | Y37: 0 | Z37: 0 | AA37: =Vlookup(B37,'セッション実施状況管理'!$A:$R,17,false) | AB37: =(YEAR(TODAY()) - YEAR($AA37)) * 12 + (MONTH(TODAY()) - MONTH($AA37)) -> 1514 | AC37: =IF( OR(AB37=3, AB37=4, AB37=5, AB37=6), "1", "2" ) -> 2
B38: 20 | C38: =vlookup(B38,'セッション実施状況管理'!$A:$U,8,false) -> すだはるき | D38: =vlookup(B38,'セッション実施状況管理'!$A:$I,9,false) -> haru_room100 | E38: https://docs.google.com/spreadsheets/d/1lsfeuqbKMTpSp1QjH9bAMAeuybHwaj2ewjj1etJI1JA/edit?usp=sharing | F38: =vlookup(B38,'セッション実施状況管理'!$A:$U,20,false) -> 須見浩人 | G38: =vlookup(B38,'セッション実施状況管理'!$A:$U,20,false) -> 須見浩人 | H38: ='コーチング報酬管理'!G27 -> 13 | I38: =iferror(vlookup(B38,'セッション実施状況管理'!$A:$B,2,false),"") -> 卒業 | J38: 0 | K38: 2 | L38: =VLOOKUP(B38,'新 月次投稿数'!$A:$N,13,false) -> 53 | M38: =IF(L38>=120, 3, IF(L38>=100, 2, IF(L38>=80, 1, IF(L38>=60, 0, IF(L38>=40, -1, IF(L38>=20, -2, -3)))))) -> -1 | N38: =IF(Q38>=540, 4, IF(Q38>=480, 3, IF(Q38>=420, 2, IF(Q38>=360, 1, IF(Q38>=300, 0, IF(Q38>=240, -1, -2)))))) -> -2 | O38: =IF(P38>=540, 4, IF(P38>=480, 3, IF(P38>=420, 2, IF(P38>=360, 1, IF(P38>=300, 0, IF(P38>=240, -1, -2)))))) -> -2 | P38: =sum(T38:Z38) -> 194 | Q38: =R38*6 -> 166.28571 | R38: =iferror(P38/S38,"0") -> 27.714286 | S38: =count(T38:Z38) -> 7 | T38: 0 | U38: 0 | V38: 0 | W38: 64 | X38: 66 | Y38: 64 | Z38: 0 | AA38: =Vlookup(B38,'セッション実施状況管理'!$A:$R,17,false) | AB38: =(YEAR(TODAY()) - YEAR($AA38)) * 12 + (MONTH(TODAY()) - MONTH($AA38)) -> 1514 | AC38: =IF( OR(AB38=3, AB38=4, AB38=5, AB38=6), "1", "2" ) -> 2
B39: 21 | C39: =vlookup(B39,'セッション実施状況管理'!$A:$U,8,false) -> かしはらせつみ | D39: =vlookup(B39,'セッション実施状況管理'!$A:$I,9,false) -> sena_bilife | E39: https://docs.google.com/spreadsheets/d/1_sorqfBgBOIUJSQc8BV-I7n8u25Q-wJ_-7InjjC2Y9U/edit#gid=159884613 | F39: =vlookup(B39,'セッション実施状況管理'!$A:$U,20,false) -> 宮田友理 | G39: =vlookup(B39,'セッション実施状況管理'!$A:$U,20,false) -> 宮田友理 | H39: ='コーチング報酬管理'!G28 -> 12 | I39: =iferror(vlookup(B39,'セッション実施状況管理'!$A:$B,2,false),"") -> 卒業 | J39: 0 | K39: 0 | L39: =VLOOKUP(B39,'新 月次投稿数'!$A:$N,13,false) -> 97 | M39: =IF(L39>=120, 3, IF(L39>=100, 2, IF(L39>=80, 1, IF(L39>=60, 0, IF(L39>=40, -1, IF(L39>=20, -2, -3)))))) -> 1 | N39: =IF(Q39>=540, 4, IF(Q39>=480, 3, IF(Q39>=420, 2, IF(Q39>=360, 1, IF(Q39>=300, 0, IF(Q39>=240, -1, -2)))))) -> 4 | O39: =IF(P39>=540, 4, IF(P39>=480, 3, IF(P39>=420, 2, IF(P39>=360, 1, IF(P39>=300, 0, IF(P39>=240, -1, -2)))))) -> 4 | P39: =sum(T39:Z39) -> 736 | Q39: =R39*6 -> 630.85714 | R39: =iferror(P39/S39,"0") -> 105.14286 | S39: =count(T39:Z39) -> 7 | T39: 0 | U39: 52 | V39: 148 | W39: 110 | X39: 115 | Y39: 171 | Z39: 140 | AA39: =Vlookup(B39,'セッション実施状況管理'!$A:$R,17,false) | AB39: =(YEAR(TODAY()) - YEAR($AA39)) * 12 + (MONTH(TODAY()) - MONTH($AA39)) -> 1514 | AC39: =IF( OR(AB39=3, AB39=4, AB39=5, AB39=6), "1", "2" ) -> 2
B40: 22 | C40: =vlookup(B40,'セッション実施状況管理'!$A:$U,8,false) -> ながおあみり | D40: =vlookup(B40,'セッション実施状況管理'!$A:$I,9,false) -> amiri_instastory | E40: https://docs.google.com/spreadsheets/d/1mLPCfMplb1pxA08rBjE6hym2dksQlMm05CYjXSIF0Gk/edit#gid=0 | F40: =vlookup(B40,'セッション実施状況管理'!$A:$U,20,false) -> 野村佑佳 | G40: =vlookup(B40,'セッション実施状況管理'!$A:$U,20,false) -> 野村佑佳 | H40: ='コーチング報酬管理'!G29 -> 13 | I40: =iferror(vlookup(B40,'セッション実施状況管理'!$A:$B,2,false),"") -> 卒業 | J40: 3 | K40: 2 | L40: =VLOOKUP(B40,'新 月次投稿数'!$A:$N,13,false) -> 59 | M40: =IF(L40>=120, 3, IF(L40>=100, 2, IF(L40>=80, 1, IF(L40>=60, 0, IF(L40>=40, -1, IF(L40>=20, -2, -3)))))) -> -1 | N40: =IF(Q40>=540, 4, IF(Q40>=480, 3, IF(Q40>=420, 2, IF(Q40>=360, 1, IF(Q40>=300, 0, IF(Q40>=240, -1, -2)))))) -> 4 | O40: =IF(P40>=540, 4, IF(P40>=480, 3, IF(P40>=420, 2, IF(P40>=360, 1, IF(P40>=300, 0, IF(P40>=240, -1, -2)))))) -> 4 | P40: =sum(T40:Z40) -> 768 | Q40: =R40*6 -> 658.28571 | R40: =iferror(P40/S40,"0") -> 109.71429 | S40: =count(T40:Z40) -> 7 | T40: 0 | U40: 152 | V40: 168 | W40: 121 | X40: 122 | Y40: 148 | Z40: 57 | AA40: =Vlookup(B40,'セッション実施状況管理'!$A:$R,17,false) | AB40: =(YEAR(TODAY()) - YEAR($AA40)) * 12 + (MONTH(TODAY()) - MONTH($AA40)) -> 1514 | AC40: =IF( OR(AB40=3, AB40=4, AB40=5, AB40=6), "1", "2" ) -> 2
B41: 23 | C41: =vlookup(B41,'セッション実施状況管理'!$A:$U,8,false) -> こばやしはるか | D41: =vlookup(B41,'セッション実施状況管理'!$A:$I,9,false) -> elu_excel.teiji | E41: https://docs.google.com/spreadsheets/d/1TLF48muTLxNSP-22O7ME6vthSYqfxDlYBYCiGGznaJc/edit?usp=sharing | F41: =vlookup(B41,'セッション実施状況管理'!$A:$U,20,false) -> 清原三和子 | G41: =vlookup(B41,'セッション実施状況管理'!$A:$U,20,false) -> 清原三和子 | H41: ='コーチング報酬管理'!G30 -> 13 | I41: =iferror(vlookup(B41,'セッション実施状況管理'!$A:$B,2,false),"") -> 卒業 | J41: 0 | K41: 2 | L41: =VLOOKUP(B41,'新 月次投稿数'!$A:$N,13,false) -> 86 | M41: =IF(L41>=120, 3, IF(L41>=100, 2, IF(L41>=80, 1, IF(L41>=60, 0, IF(L41>=40, -1, IF(L41>=20, -2, -3)))))) -> 1 | N41: =IF(Q41>=540, 4, IF(Q41>=480, 3, IF(Q41>=420, 2, IF(Q41>=360, 1, IF(Q41>=300, 0, IF(Q41>=240, -1, -2)))))) -> 4 | O41: =IF(P41>=540, 4, IF(P41>=480, 3, IF(P41>=420, 2, IF(P41>=360, 1, IF(P41>=300, 0, IF(P41>=240, -1, -2)))))) -> 4 | P41: =sum(T41:Z41) -> 816 | Q41: =R41*6 -> 699.42857 | R41: =iferror(P41/S41,"0") -> 116.57143 | S41: =count(T41:Z41) -> 7 | T41: 51 | U41: 132 | V41: 137 | W41: 106 | X41: 140 | Y41: 95 | Z41: 155 | AA41: =Vlookup(B41,'セッション実施状況管理'!$A:$R,17,false) | AB41: =(YEAR(TODAY()) - YEAR($AA41)) * 12 + (MONTH(TODAY()) - MONTH($AA41)) -> 1514 | AC41: =IF( OR(AB41=3, AB41=4, AB41=5, AB41=6), "1", "2" ) -> 2
B42: 24 | C42: =vlookup(B42,'セッション実施状況管理'!$A:$U,8,false) -> じょうどじゆうき | D42: =vlookup(B42,'セッション実施状況管理'!$A:$I,9,false) -> じょうどじゆうき | E42: https://docs.google.com/spreadsheets/d/17QYwOXEXZK-iQo82a_DJd27fJUJK4_h-B37kvGzB_g0/edit?gid=0#gid=0 | F42: =vlookup(B42,'セッション実施状況管理'!$A:$U,20,false) -> 福田康裕 | G42: =vlookup(B42,'セッション実施状況管理'!$A:$U,20,false) -> 福田康裕 | H42: ='コーチング報酬管理'!G31 -> 3 | I42: =iferror(vlookup(B42,'セッション実施状況管理'!$A:$B,2,false),"") -> 音不 | J42: 0 | K42: -1 | L42: =VLOOKUP(B42,'新 月次投稿数'!$A:$N,13,false) -> 0 | M42: =IF(L42>=120, 3, IF(L42>=100, 2, IF(L42>=80, 1, IF(L42>=60, 0, IF(L42>=40, -1, IF(L42>=20, -2, -3)))))) -> -3 | N42: =IF(Q42>=540, 4, IF(Q42>=480, 3, IF(Q42>=420, 2, IF(Q42>=360, 1, IF(Q42>=300, 0, IF(Q42>=240, -1, -2)))))) -> -2 | O42: =IF(P42>=540, 4, IF(P42>=480, 3, IF(P42>=420, 2, IF(P42>=360, 1, IF(P42>=300, 0, IF(P42>=240, -1, -2)))))) -> -2 | P42: =sum(T42:Z42) -> 0 | Q42: =R42*6 -> 0 | R42: =iferror(P42/S42,"0") -> 0 | S42: =count(T42:Z42) -> 7 | T42: 0 | U42: 0 | V42: 0 | W42: 0 | X42: 0 | Y42: 0 | Z42: 0 | AA42: =Vlookup(B42,'セッション実施状況管理'!$A:$R,17,false) | AB42: =(YEAR(TODAY()) - YEAR($AA42)) * 12 + (MONTH(TODAY()) - MONTH($AA42)) -> 1514 | AC42: =IF( OR(AB42=3, AB42=4, AB42=5, AB42=6), "1", "2" ) -> 2
B43: 25 | C43: =vlookup(B43,'セッション実施状況管理'!$A:$U,8,false) -> たなかゆりか | D43: =vlookup(B43,'セッション実施状況管理'!$A:$I,9,false) -> たなかゆりか | E43: https://docs.google.com/spreadsheets/d/1wpdiKAZA3G7mneaUJYaYagJAxhvATWlpDsGSeQYEjEU/edit?usp=sharing | F43: =vlookup(B43,'セッション実施状況管理'!$A:$U,20,false) -> 清原三和子 | G43: =vlookup(B43,'セッション実施状況管理'!$A:$U,20,false) -> 清原三和子 | H43: ='コーチング報酬管理'!G32 -> 2 | I43: =iferror(vlookup(B43,'セッション実施状況管理'!$A:$B,2,false),"") -> 例外 | J43: 0 | K43: -1 | L43: =VLOOKUP(B43,'新 月次投稿数'!$A:$N,13,false) -> 0 | M43: =IF(L43>=120, 3, IF(L43>=100, 2, IF(L43>=80, 1, IF(L43>=60, 0, IF(L43>=40, -1, IF(L43>=20, -2, -3)))))) -> -3 | N43: =IF(Q43>=540, 4, IF(Q43>=480, 3, IF(Q43>=420, 2, IF(Q43>=360, 1, IF(Q43>=300, 0, IF(Q43>=240, -1, -2)))))) -> -2 | O43: =IF(P43>=540, 4, IF(P43>=480, 3, IF(P43>=420, 2, IF(P43>=360, 1, IF(P43>=300, 0, IF(P43>=240, -1, -2)))))) -> -2 | P43: =sum(T43:Z43) -> 117 | Q43: =R43*6 -> 100.28571 | R43: =iferror(P43/S43,"0") -> 16.714286 | S43: =count(T43:Z43) -> 7 | T43: 0 | U43: 7 | V43: 0 | W43: 110 | X43: 0 | Y43: 0 | Z43: 0 | AA43: =Vlookup(B43,'セッション実施状況管理'!$A:$R,17,false) | AB43: =(YEAR(TODAY()) - YEAR($AA43)) * 12 + (MONTH(TODAY()) - MONTH($AA43)) -> 1514 | AC43: =IF( OR(AB43=3, AB43=4, AB43=5, AB43=6), "1", "2" ) -> 2
B44: 26 | C44: =vlookup(B44,'セッション実施状況管理'!$A:$U,8,false) -> かわしま あらし | D44: =vlookup(B44,'セッション実施状況管理'!$A:$I,9,false) -> fuui_guitar | E44: https://docs.google.com/spreadsheets/d/1rTTDfcCjHe0OlDMufgES-EFYIo1a0jLvlOSgnQXMQU8/edit?usp=sharing | F44: =vlookup(B44,'セッション実施状況管理'!$A:$U,20,false) -> 森本風花 | G44: =vlookup(B44,'セッション実施状況管理'!$A:$U,20,false) -> 森本風花 | H44: ='コーチング報酬管理'!G33 -> 13 | I44: =iferror(vlookup(B44,'セッション実施状況管理'!$A:$B,2,false),"") -> 卒業 | J44: 0 | K44: 0 | L44: =VLOOKUP(B44,'新 月次投稿数'!$A:$N,13,false) -> 40 | M44: =IF(L44>=120, 3, IF(L44>=100, 2, IF(L44>=80, 1, IF(L44>=60, 0, IF(L44>=40, -1, IF(L44>=20, -2, -3)))))) -> -1 | N44: =IF(Q44>=540, 4, IF(Q44>=480, 3, IF(Q44>=420, 2, IF(Q44>=360, 1, IF(Q44>=300, 0, IF(Q44>=240, -1, -2)))))) -> 3 | O44: =IF(P44>=540, 4, IF(P44>=480, 3, IF(P44>=420, 2, IF(P44>=360, 1, IF(P44>=300, 0, IF(P44>=240, -1, -2)))))) -> 4 | P44: =sum(T44:Z44) -> 566 | Q44: =R44*6 -> 485.14286 | R44: =iferror(P44/S44,"0") -> 80.857143 | S44: =count(T44:Z44) -> 7 | T44: 0 | U44: 95 | V44: 66 | W44: 84 | X44: 61 | Y44: 110 | Z44: 150 | AA44: =Vlookup(B44,'セッション実施状況管理'!$A:$R,17,false) | AB44: =(YEAR(TODAY()) - YEAR($AA44)) * 12 + (MONTH(TODAY()) - MONTH($AA44)) -> 1514 | AC44: =IF( OR(AB44=3, AB44=4, AB44=5, AB44=6), "1", "2" ) -> 2
B45: 27 | C45: =vlookup(B45,'セッション実施状況管理'!$A:$U,8,false) -> せきおかまさき | D45: =vlookup(B45,'セッション実施状況管理'!$A:$I,9,false) -> せきおかまさき | E45: https://docs.google.com/spreadsheets/d/1OatbpHQcF2GQqcx7BWzIrYEahfEK-ZtcYa9MzmWto4U/edit?gid=0#gid=0 | F45: =vlookup(B45,'セッション実施状況管理'!$A:$U,20,false) -> 福田康裕 | G45: =vlookup(B45,'セッション実施状況管理'!$A:$U,20,false) -> 福田康裕 | H45: ='コーチング報酬管理'!G34 -> 2 | I45: =iferror(vlookup(B45,'セッション実施状況管理'!$A:$B,2,false),"") -> 音不 | J45: 0 | K45: -1 | L45: =VLOOKUP(B45,'新 月次投稿数'!$A:$N,13,false) -> 0 | M45: =IF(L45>=120, 3, IF(L45>=100, 2, IF(L45>=80, 1, IF(L45>=60, 0, IF(L45>=40, -1, IF(L45>=20, -2, -3)))))) -> -3 | N45: =IF(Q45>=540, 4, IF(Q45>=480, 3, IF(Q45>=420, 2, IF(Q45>=360, 1, IF(Q45>=300, 0, IF(Q45>=240, -1, -2)))))) -> -2 | O45: =IF(P45>=540, 4, IF(P45>=480, 3, IF(P45>=420, 2, IF(P45>=360, 1, IF(P45>=300, 0, IF(P45>=240, -1, -2)))))) -> -2 | P45: =sum(T45:Z45) -> 0 | Q45: =R45*6 -> 0 | R45: =iferror(P45/S45,"0") -> 0 | S45: =count(T45:Z45) -> 7 | T45: 0 | U45: 0 | V45: 0 | W45: 0 | X45: 0 | Y45: 0 | Z45: 0 | AA45: =Vlookup(B45,'セッション実施状況管理'!$A:$R,17,false) | AB45: =(YEAR(TODAY()) - YEAR($AA45)) * 12 + (MONTH(TODAY()) - MONTH($AA45)) -> 1514 | AC45: =IF( OR(AB45=3, AB45=4, AB45=5, AB45=6), "1", "2" ) -> 2
B46: 28 | C46: =vlookup(B46,'セッション実施状況管理'!$A:$U,8,false) -> しらどうさき | D46: =vlookup(B46,'セッション実施状況管理'!$A:$I,9,false) -> shirasaki_happylife | E46: https://docs.google.com/spreadsheets/d/1KUzmr3xtmoxZoaUGLNkXeiOhWtZH2XMc0mIrtsN5NfY/edit?gid=1837929075#gid=1837929075 | F46: =vlookup(B46,'セッション実施状況管理'!$A:$U,20,false) -> 宮田友理 | G46: =vlookup(B46,'セッション実施状況管理'!$A:$U,20,false) -> 宮田友理 | H46: ='コーチング報酬管理'!G35 -> 13 | I46: =iferror(vlookup(B46,'セッション実施状況管理'!$A:$B,2,false),"") -> 卒業 | J46: 0 | K46: 0 | L46: =VLOOKUP(B46,'新 月次投稿数'!$A:$N,13,false) -> 25 | M46: =IF(L46>=120, 3, IF(L46>=100, 2, IF(L46>=80, 1, IF(L46>=60, 0, IF(L46>=40, -1, IF(L46>=20, -2, -3)))))) -> -2 | N46: =IF(Q46>=540, 4, IF(Q46>=480, 3, IF(Q46>=420, 2, IF(Q46>=360, 1, IF(Q46>=300, 0, IF(Q46>=240, -1, -2)))))) -> 3 | O46: =IF(P46>=540, 4, IF(P46>=480, 3, IF(P46>=420, 2, IF(P46>=360, 1, IF(P46>=300, 0, IF(P46>=240, -1, -2)))))) -> 4 | P46: =sum(T46:Z46) -> 623 | Q46: =R46*6 -> 534 | R46: =iferror(P46/S46,"0") -> 89 | S46: =count(T46:Z46) -> 7 | T46: 86 | U46: 113 | V46: 91 | W46: 76 | X46: 66 | Y46: 91 | Z46: 100 | AA46: =Vlookup(B46,'セッション実施状況管理'!$A:$R,17,false) | AB46: =(YEAR(TODAY()) - YEAR($AA46)) * 12 + (MONTH(TODAY()) - MONTH($AA46)) -> 1514 | AC46: =IF( OR(AB46=3, AB46=4, AB46=5, AB46=6), "1", "2" ) -> 2
B47: 29 | C47: =vlookup(B47,'セッション実施状況管理'!$A:$U,8,false) -> まさきちさと | D47: =vlookup(B47,'セッション実施状況管理'!$A:$I,9,false) -> hachi.footcare | E47: https://docs.google.com/spreadsheets/d/1cLZxLobnns6l5qsCzis2K-0ExuzYfyM-lwwwAIHLs4I/edit?usp=sharing | F47: =vlookup(B47,'セッション実施状況管理'!$A:$U,20,false) -> 宮田友理 | G47: =vlookup(B47,'セッション実施状況管理'!$A:$U,20,false) -> 宮田友理 | H47: ='コーチング報酬管理'!G36 -> 13 | I47: =iferror(vlookup(B47,'セッション実施状況管理'!$A:$B,2,false),"") -> 卒業 | J47: 0 | K47: 2 | L47: =VLOOKUP(B47,'新 月次投稿数'!$A:$N,13,false) -> 97 | M47: =IF(L47>=120, 3, IF(L47>=100, 2, IF(L47>=80, 1, IF(L47>=60, 0, IF(L47>=40, -1, IF(L47>=20, -2, -3)))))) -> 1 | N47: =IF(Q47>=540, 4, IF(Q47>=480, 3, IF(Q47>=420, 2, IF(Q47>=360, 1, IF(Q47>=300, 0, IF(Q47>=240, -1, -2)))))) -> 4 | O47: =IF(P47>=540, 4, IF(P47>=480, 3, IF(P47>=420, 2, IF(P47>=360, 1, IF(P47>=300, 0, IF(P47>=240, -1, -2)))))) -> 4 | P47: =sum(T47:Z47) -> 837 | Q47: =R47*6 -> 717.42857 | R47: =iferror(P47/S47,"0") -> 119.57143 | S47: =count(T47:Z47) -> 7 | T47: 0 | U47: 81 | V47: 134 | W47: 178 | X47: 169 | Y47: 146 | Z47: 129 | AA47: =Vlookup(B47,'セッション実施状況管理'!$A:$R,17,false) | AB47: =(YEAR(TODAY()) - YEAR($AA47)) * 12 + (MONTH(TODAY()) - MONTH($AA47)) -> 1514 | AC47: =IF( OR(AB47=3, AB47=4, AB47=5, AB47=6), "1", "2" ) -> 2
B48: 30 | C48: =vlookup(B48,'セッション実施状況管理'!$A:$U,8,false) -> みよしゆうき | D48: =vlookup(B48,'セッション実施状況管理'!$A:$I,9,false) -> yupi_nariagaru | E48: https://docs.google.com/spreadsheets/d/1-nBXgVm4fFVn9mFP8x3DkA6Hdr4bwHGdacqxyi-qSQQ/edit?usp=sharing | F48: =vlookup(B48,'セッション実施状況管理'!$A:$U,20,false) -> 清原三和子 | G48: =vlookup(B48,'セッション実施状況管理'!$A:$U,20,false) -> 清原三和子 | H48: ='コーチング報酬管理'!G12 -> 13 | I48: =iferror(vlookup(B48,'セッション実施状況管理'!$A:$B,2,false),"") -> 卒業 | J48: 0 | K48: 0 | L48: =VLOOKUP(B48,'新 月次投稿数'!$A:$N,13,false) -> 10 | M48: =IF(L48>=120, 3, IF(L48>=100, 2, IF(L48>=80, 1, IF(L48>=60, 0, IF(L48>=40, -1, IF(L48>=20, -2, -3)))))) -> -3 | N48: =IF(Q48>=540, 4, IF(Q48>=480, 3, IF(Q48>=420, 2, IF(Q48>=360, 1, IF(Q48>=300, 0, IF(Q48>=240, -1, -2)))))) -> 3 | O48: =IF(P48>=540, 4, IF(P48>=480, 3, IF(P48>=420, 2, IF(P48>=360, 1, IF(P48>=300, 0, IF(P48>=240, -1, -2)))))) -> 4 | P48: =sum(T48:Z48) -> 592 | Q48: =R48*6 -> 507.42857 | R48: =iferror(P48/S48,"0") -> 84.571429 | S48: =count(T48:Z48) -> 7 | T48: 92 | U48: 67 | V48: 76 | W48: 78 | X48: 78 | Y48: 138 | Z48: 63 | AA48: =Vlookup(B48,'セッション実施状況管理'!$A:$R,17,false) | AB48: =(YEAR(TODAY()) - YEAR($AA48)) * 12 + (MONTH(TODAY()) - MONTH($AA48)) -> 1514 | AC48: =IF( OR(AB48=3, AB48=4, AB48=5, AB48=6), "1", "2" ) -> 2
B49: 31 | C49: =vlookup(B49,'セッション実施状況管理'!$A:$U,8,false) -> すずきかおり | D49: =vlookup(B49,'セッション実施状況管理'!$A:$I,9,false) -> ryo_life_reset | E49: https://docs.google.com/spreadsheets/d/1ebN8k5ldf44k8jTRewRqsxTldkdZkrenDrjVfnkIifk/edit?gid=997181537#gid=997181537 | F49: =vlookup(B49,'セッション実施状況管理'!$A:$U,20,false) -> 野村佑佳 | G49: =vlookup(B49,'セッション実施状況管理'!$A:$U,20,false) -> 野村佑佳 | H49: ='コーチング報酬管理'!G38 -> 13 | I49: =iferror(vlookup(B49,'セッション実施状況管理'!$A:$B,2,false),"") -> 卒業 | J49: 0 | K49: 0 | L49: =VLOOKUP(B49,'新 月次投稿数'!$A:$N,13,false) -> 39 | M49: =IF(L49>=120, 3, IF(L49>=100, 2, IF(L49>=80, 1, IF(L49>=60, 0, IF(L49>=40, -1, IF(L49>=20, -2, -3)))))) -> -2 | N49: =IF(Q49>=540, 4, IF(Q49>=480, 3, IF(Q49>=420, 2, IF(Q49>=360, 1, IF(Q49>=300, 0, IF(Q49>=240, -1, -2)))))) -> 2 | O49: =IF(P49>=540, 4, IF(P49>=480, 3, IF(P49>=420, 2, IF(P49>=360, 1, IF(P49>=300, 0, IF(P49>=240, -1, -2)))))) -> 3 | P49: =sum(T49:Z49) -> 506 | Q49: =R49*6 -> 433.71429 | R49: =iferror(P49/S49,"0") -> 72.285714 | S49: =count(T49:Z49) -> 7 | T49: 33 | U49: 118 | V49: 86 | W49: 71 | X49: 66 | Y49: 62 | Z49: 70 | AA49: =Vlookup(B49,'セッション実施状況管理'!$A:$R,17,false) | AB49: =(YEAR(TODAY()) - YEAR($AA49)) * 12 + (MONTH(TODAY()) - MONTH($AA49)) -> 1514 | AC49: =IF( OR(AB49=3, AB49=4, AB49=5, AB49=6), "1", "2" ) -> 2
B50: 32 | C50: =vlookup(B50,'セッション実施状況管理'!$A:$U,8,false) -> きたがわあやの | D50: =vlookup(B50,'セッション実施状況管理'!$A:$I,9,false) -> balabo_style_40 | E50: https://www.notion.so/_-h-35951262685743398d81dfd46366359d?pvs=4 | F50: =vlookup(B50,'セッション実施状況管理'!$A:$U,20,false) -> 森本風花 | G50: =vlookup(B50,'セッション実施状況管理'!$A:$U,20,false) -> 森本風花 | H50: ='コーチング報酬管理'!G39 -> 6 | I50: =iferror(vlookup(B50,'セッション実施状況管理'!$A:$B,2,false),"") -> 卒業 | J50: 0 | K50: 0 | L50: =VLOOKUP(B50,'新 月次投稿数'!$A:$N,13,false) -> 0 | M50: =IF(L50>=120, 3, IF(L50>=100, 2, IF(L50>=80, 1, IF(L50>=60, 0, IF(L50>=40, -1, IF(L50>=20, -2, -3)))))) -> -3 | N50: =IF(Q50>=540, 4, IF(Q50>=480, 3, IF(Q50>=420, 2, IF(Q50>=360, 1, IF(Q50>=300, 0, IF(Q50>=240, -1, -2)))))) -> -2 | O50: =IF(P50>=540, 4, IF(P50>=480, 3, IF(P50>=420, 2, IF(P50>=360, 1, IF(P50>=300, 0, IF(P50>=240, -1, -2)))))) -> -2 | P50: =sum(T50:Z50) -> 70 | Q50: =R50*6 -> 210 | R50: =iferror(P50/S50,"0") -> 35 | S50: =count(T50:Z50) -> 2 | T50: 44 | U50: 26 | V50: ー | W50: ー | X50: ー | Y50: ー | Z50: ー | AA50: =Vlookup(B50,'セッション実施状況管理'!$A:$R,17,false) | AB50: =(YEAR(TODAY()) - YEAR($AA50)) * 12 + (MONTH(TODAY()) - MONTH($AA50)) -> 1514 | AC50: =IF( OR(AB50=3, AB50=4, AB50=5, AB50=6), "1", "2" ) -> 2
B51: 33 | C51: =vlookup(B51,'セッション実施状況管理'!$A:$U,8,false) -> さんのうたかひろ | D51: =vlookup(B51,'セッション実施状況管理'!$A:$I,9,false) -> さんのうたかひろ | E51: https://docs.google.com/spreadsheets/d/1QXQuaq3pmYIvHh9F4CNNTetKESed_OfbCrWXPmDI_JA/edit?gid=997181537#gid=997181537 | F51: =vlookup(B51,'セッション実施状況管理'!$A:$U,20,false) -> 森本風花 | G51: =vlookup(B51,'セッション実施状況管理'!$A:$U,20,false) -> 森本風花 | H51: ='コーチング報酬管理'!G40 -> 4 | I51: =iferror(vlookup(B51,'セッション実施状況管理'!$A:$B,2,false),"") -> 例外 | J51: 0 | K51: 0 | L51: =VLOOKUP(B51,'新 月次投稿数'!$A:$N,13,false) -> 0 | M51: =IF(L51>=120, 3, IF(L51>=100, 2, IF(L51>=80, 1, IF(L51>=60, 0, IF(L51>=40, -1, IF(L51>=20, -2, -3)))))) -> -3 | N51: =IF(Q51>=540, 4, IF(Q51>=480, 3, IF(Q51>=420, 2, IF(Q51>=360, 1, IF(Q51>=300, 0, IF(Q51>=240, -1, -2)))))) -> -2 | O51: =IF(P51>=540, 4, IF(P51>=480, 3, IF(P51>=420, 2, IF(P51>=360, 1, IF(P51>=300, 0, IF(P51>=240, -1, -2)))))) -> -2 | P51: =sum(T51:Z51) -> 9 | Q51: =R51*6 -> 27 | R51: =iferror(P51/S51,"0") -> 4.5 | S51: =count(T51:Z51) -> 2 | T51: 2 | U51: 7 | V51: ― | W51: ― | X51: ― | Y51: ー | Z51: ー | AA51: =Vlookup(B51,'セッション実施状況管理'!$A:$R,17,false) | AB51: =(YEAR(TODAY()) - YEAR($AA51)) * 12 + (MONTH(TODAY()) - MONTH($AA51)) -> 1514 | AC51: =IF( OR(AB51=3, AB51=4, AB51=5, AB51=6), "1", "2" ) -> 2
B52: 34 | C52: =vlookup(B52,'セッション実施状況管理'!$A:$U,8,false) -> かどたゆきこ | D52: =vlookup(B52,'セッション実施状況管理'!$A:$I,9,false) -> katherine_kadota | E52: https://docs.google.com/spreadsheets/d/1d8grjIeo0hHS1eJXfducbttTR4LHhyhvHQb35ZZ8VyA/edit?usp=sharing | F52: =vlookup(B52,'セッション実施状況管理'!$A:$U,20,false) -> 清原三和子 | G52: =vlookup(B52,'セッション実施状況管理'!$A:$U,20,false) -> 清原三和子 | H52: ='コーチング報酬管理'!G41 -> 13 | I52: =iferror(vlookup(B52,'セッション実施状況管理'!$A:$B,2,false),"") -> 音不 | J52: 0 | K52: -1 | L52: =VLOOKUP(B52,'新 月次投稿数'!$A:$N,13,false) -> 0 | M52: =IF(L52>=120, 3, IF(L52>=100, 2, IF(L52>=80, 1, IF(L52>=60, 0, IF(L52>=40, -1, IF(L52>=20, -2, -3)))))) -> -3 | N52: =IF(Q52>=540, 4, IF(Q52>=480, 3, IF(Q52>=420, 2, IF(Q52>=360, 1, IF(Q52>=300, 0, IF(Q52>=240, -1, -2)))))) -> -2 | O52: =IF(P52>=540, 4, IF(P52>=480, 3, IF(P52>=420, 2, IF(P52>=360, 1, IF(P52>=300, 0, IF(P52>=240, -1, -2)))))) -> -2 | P52: =sum(T52:Z52) -> 133 | Q52: =R52*6 -> 159.6 | R52: =iferror(P52/S52,"0") -> 26.6 | S52: =count(T52:Z52) -> 5 | T52: 46 | U52: 21 | V52: 0 | W52: 62 | X52: 4 | Y52: ー | Z52: ー | AA52: =Vlookup(B52,'セッション実施状況管理'!$A:$R,17,false) | AB52: =(YEAR(TODAY()) - YEAR($AA52)) * 12 + (MONTH(TODAY()) - MONTH($AA52)) -> 1514 | AC52: =IF( OR(AB52=3, AB52=4, AB52=5, AB52=6), "1", "2" ) -> 2
B53: 35 | C53: =vlookup(B53,'セッション実施状況管理'!$A:$U,8,false) -> まつもとたくみ | D53: nanami_movie_streaming | E53: https://docs.google.com/spreadsheets/d/14C4EEtFXcUlQ9weztnfV3d21_BUlEy8LNPo2MEHJx_Q/edit | F53: =vlookup(B53,'セッション実施状況管理'!$A:$U,20,false) -> 中村恵理 | G53: =vlookup(B53,'セッション実施状況管理'!$A:$U,20,false) -> 中村恵理 | H53: ='コーチング報酬管理'!G42 -> 9 | I53: =iferror(vlookup(B53,'セッション実施状況管理'!$A:$B,2,false),"") -> 卒業 | J53: 0 | K53: 0 | L53: =VLOOKUP(B53,'新 月次投稿数'!$A:$N,13,false) -> 2 | M53: =IF(L53>=120, 3, IF(L53>=100, 2, IF(L53>=80, 1, IF(L53>=60, 0, IF(L53>=40, -1, IF(L53>=20, -2, -3)))))) -> -3 | N53: =IF(Q53>=540, 4, IF(Q53>=480, 3, IF(Q53>=420, 2, IF(Q53>=360, 1, IF(Q53>=300, 0, IF(Q53>=240, -1, -2)))))) -> -1 | O53: =IF(P53>=540, 4, IF(P53>=480, 3, IF(P53>=420, 2, IF(P53>=360, 1, IF(P53>=300, 0, IF(P53>=240, -1, -2)))))) -> 0 | P53: =sum(T53:Z53) -> 335 | Q53: =R53*6 -> 287.14286 | R53: =iferror(P53/S53,"0") -> 47.857143 | S53: =count(T53:Z53) -> 7 | T53: 22 | U53: 93 | V53: 95 | W53: 61 | X53: 64 | Y53: 0 | Z53: 0 | AA53: =Vlookup(B53,'セッション実施状況管理'!$A:$R,17,false) | AB53: =(YEAR(TODAY()) - YEAR($AA53)) * 12 + (MONTH(TODAY()) - MONTH($AA53)) -> 1514 | AC53: =IF( OR(AB53=3, AB53=4, AB53=5, AB53=6), "1", "2" ) -> 2
B54: 36 | C54: =vlookup(B54,'セッション実施状況管理'!$A:$U,8,false) -> にしむらゆうの | D54: =vlookup(B54,'セッション実施状況管理'!$A:$I,9,false) -> nomuuno_kurashi | E54: https://docs.google.com/spreadsheets/d/1ZFIKfjjCS0lYeQg1VvF9L5T89pGQVX0-Ogw4b5gKuPM/edit?usp=sharing | F54: =vlookup(B54,'セッション実施状況管理'!$A:$U,20,false) -> 小針彩乃 | G54: =vlookup(B54,'セッション実施状況管理'!$A:$U,20,false) -> 小針彩乃 | H54: ='コーチング報酬管理'!G43 -> 13 | I54: =iferror(vlookup(B54,'セッション実施状況管理'!$A:$B,2,false),"") -> 卒業 | J54: 0 | K54: 0 | L54: =VLOOKUP(B54,'新 月次投稿数'!$A:$N,13,false) -> 9 | M54: =IF(L54>=120, 3, IF(L54>=100, 2, IF(L54>=80, 1, IF(L54>=60, 0, IF(L54>=40, -1, IF(L54>=20, -2, -3)))))) -> -3 | N54: =IF(Q54>=540, 4, IF(Q54>=480, 3, IF(Q54>=420, 2, IF(Q54>=360, 1, IF(Q54>=300, 0, IF(Q54>=240, -1, -2)))))) -> 0 | O54: =IF(P54>=540, 4, IF(P54>=480, 3, IF(P54>=420, 2, IF(P54>=360, 1, IF(P54>=300, 0, IF(P54>=240, -1, -2)))))) -> 0 | P54: =sum(T54:Z54) -> 356 | Q54: =R54*6 -> 305.14286 | R54: =iferror(P54/S54,"0") -> 50.857143 | S54: =count(T54:Z54) -> 7 | T54: 12 | U54: 79 | V54: 73 | W54: 65 | X54: 51 | Y54: 42 | Z54: 34 | AA54: =Vlookup(B54,'セッション実施状況管理'!$A:$R,17,false) | AB54: =(YEAR(TODAY()) - YEAR($AA54)) * 12 + (MONTH(TODAY()) - MONTH($AA54)) -> 1514 | AC54: =IF( OR(AB54=3, AB54=4, AB54=5, AB54=6), "1", "2" ) -> 2
B55: 37 | C55: =vlookup(B55,'セッション実施状況管理'!$A:$U,8,false) -> やまもとゆり | D55: =vlookup(B55,'セッション実施状況管理'!$A:$I,9,false) -> yururi_ikuji | E55: https://docs.google.com/spreadsheets/d/16QaGXtVjnl5cPXQE1qTlz8GODeQV7sxGiSCsO8FuFPo/edit?usp=sharing | F55: =vlookup(B55,'セッション実施状況管理'!$A:$U,20,false) -> 山見阪佳子 | G55: =vlookup(B55,'セッション実施状況管理'!$A:$U,20,false) -> 山見阪佳子 | H55: ='コーチング報酬管理'!G44 -> 13 | I55: =iferror(vlookup(B55,'セッション実施状況管理'!$A:$B,2,false),"") -> 卒業 | J55: 3 | K55: 0 | L55: =VLOOKUP(B55,'新 月次投稿数'!$A:$N,13,false) -> 86 | M55: =IF(L55>=120, 3, IF(L55>=100, 2, IF(L55>=80, 1, IF(L55>=60, 0, IF(L55>=40, -1, IF(L55>=20, -2, -3)))))) -> 1 | N55: =IF(Q55>=540, 4, IF(Q55>=480, 3, IF(Q55>=420, 2, IF(Q55>=360, 1, IF(Q55>=300, 0, IF(Q55>=240, -1, -2)))))) -> 3 | O55: =IF(P55>=540, 4, IF(P55>=480, 3, IF(P55>=420, 2, IF(P55>=360, 1, IF(P55>=300, 0, IF(P55>=240, -1, -2)))))) -> 4 | P55: =sum(T55:Z55) -> 574 | Q55: =R55*6 -> 492 | R55: =iferror(P55/S55,"0") -> 82 | S55: =count(T55:Z55) -> 7 | T55: 9 | U55: 87 | V55: 90 | W55: 113 | X55: 119 | Y55: 91 | Z55: 65 | AA55: =Vlookup(B55,'セッション実施状況管理'!$A:$R,17,false) | AB55: =(YEAR(TODAY()) - YEAR($AA55)) * 12 + (MONTH(TODAY()) - MONTH($AA55)) -> 1514 | AC55: =IF( OR(AB55=3, AB55=4, AB55=5, AB55=6), "1", "2" ) -> 2
B56: 38 | C56: =vlookup(B56,'セッション実施状況管理'!$A:$U,8,false) -> おばたみずき | D56: =vlookup(B56,'セッション実施状況管理'!$A:$I,9,false) -> hanako_okane | E56: https://docs.google.com/spreadsheets/d/11zQ7LGBBG1J1QvPRFt2jkhhxOIBkWHInjVqqzUuba7Y/edit?usp=sharing | F56: =vlookup(B56,'セッション実施状況管理'!$A:$U,20,false) -> 多田祐輔 | G56: =vlookup(B56,'セッション実施状況管理'!$A:$U,20,false) -> 多田祐輔 | H56: ='コーチング報酬管理'!G45 -> 13 | I56: =iferror(vlookup(B56,'セッション実施状況管理'!$A:$B,2,false),"") -> 卒業 | J56: 0 | K56: 0 | L56: =VLOOKUP(B56,'新 月次投稿数'!$A:$N,13,false) -> 23 | M56: =IF(L56>=120, 3, IF(L56>=100, 2, IF(L56>=80, 1, IF(L56>=60, 0, IF(L56>=40, -1, IF(L56>=20, -2, -3)))))) -> -2 | N56: =IF(Q56>=540, 4, IF(Q56>=480, 3, IF(Q56>=420, 2, IF(Q56>=360, 1, IF(Q56>=300, 0, IF(Q56>=240, -1, -2)))))) -> 3 | O56: =IF(P56>=540, 4, IF(P56>=480, 3, IF(P56>=420, 2, IF(P56>=360, 1, IF(P56>=300, 0, IF(P56>=240, -1, -2)))))) -> 4 | P56: =sum(T56:Z56) -> 587 | Q56: =R56*6 -> 503.14286 | R56: =iferror(P56/S56,"0") -> 83.857143 | S56: =count(T56:Z56) -> 7 | T56: 54 | U56: 72 | V56: 109 | W56: 89 | X56: 63 | Y56: 150 | Z56: 50 | AA56: =Vlookup(B56,'セッション実施状況管理'!$A:$R,17,false) | AB56: =(YEAR(TODAY()) - YEAR($AA56)) * 12 + (MONTH(TODAY()) - MONTH($AA56)) -> 1514 | AC56: =IF( OR(AB56=3, AB56=4, AB56=5, AB56=6), "1", "2" ) -> 2
B57: 39 | C57: =vlookup(B57,'セッション実施状況管理'!$A:$U,8,false) -> い さちよ | D57: =vlookup(B57,'セッション実施状況管理'!$A:$I,9,false) -> sachi_marathon | E57: https://docs.google.com/spreadsheets/d/17aQgAeC-4lrjNGk2OjjNRj_JJ_FG7RENQ9C9x2KPkzI/edit?usp=sharing | F57: =vlookup(B57,'セッション実施状況管理'!$A:$U,20,false) -> 野村佑佳 | G57: =vlookup(B57,'セッション実施状況管理'!$A:$U,20,false) -> 野村佑佳 | H57: ='コーチング報酬管理'!G46 -> 12 | I57: =iferror(vlookup(B57,'セッション実施状況管理'!$A:$B,2,false),"") -> 卒業 | J57: 3 | K57: 2 | L57: =VLOOKUP(B57,'新 月次投稿数'!$A:$N,13,false) -> 117 | M57: =IF(L57>=120, 3, IF(L57>=100, 2, IF(L57>=80, 1, IF(L57>=60, 0, IF(L57>=40, -1, IF(L57>=20, -2, -3)))))) -> 2 | N57: =IF(Q57>=540, 4, IF(Q57>=480, 3, IF(Q57>=420, 2, IF(Q57>=360, 1, IF(Q57>=300, 0, IF(Q57>=240, -1, -2)))))) -> 3 | O57: =IF(P57>=540, 4, IF(P57>=480, 3, IF(P57>=420, 2, IF(P57>=360, 1, IF(P57>=300, 0, IF(P57>=240, -1, -2)))))) -> 4 | P57: =sum(T57:Z57) -> 614 | Q57: =R57*6 -> 526.28571 | R57: =iferror(P57/S57,"0") -> 87.714286 | S57: =count(T57:Z57) -> 7 | T57: 81 | U57: 104 | V57: 92 | W57: 72 | X57: 107 | Y57: 73 | Z57: 85 | AA57: =Vlookup(B57,'セッション実施状況管理'!$A:$R,17,false) | AB57: =(YEAR(TODAY()) - YEAR($AA57)) * 12 + (MONTH(TODAY()) - MONTH($AA57)) -> 1514 | AC57: =IF( OR(AB57=3, AB57=4, AB57=5, AB57=6), "1", "2" ) -> 2
B58: 40 | C58: =vlookup(B58,'セッション実施状況管理'!$A:$U,8,false) -> ひぐちゆき | D58: =vlookup(B58,'セッション実施状況管理'!$A:$I,9,false) -> snow_kango | E58: https://docs.google.com/spreadsheets/d/1BzLaVlXkAfZj65CEe6dflGe2tauh195QIODDIaP56MA/edit?usp=sharing | F58: =vlookup(B58,'セッション実施状況管理'!$A:$U,20,false) -> 清原三和子 | G58: =vlookup(B58,'セッション実施状況管理'!$A:$U,20,false) -> 清原三和子 | H58: ='コーチング報酬管理'!G46 -> 12 | I58: =iferror(vlookup(B58,'セッション実施状況管理'!$A:$B,2,false),"") -> 音不 | J58: 0 | K58: -1 | L58: =VLOOKUP(B58,'新 月次投稿数'!$A:$N,13,false) -> 0 | M58: =IF(L58>=100, 4, IF(L58>=81, 3, IF(L58>=56, 2, IF(L58>=31, 1, 0)))) -> 0 | N58: =IF(Q58>=540, 4, IF(Q58>=480, 3, IF(Q58>=420, 2, IF(Q58>=360, 1, IF(Q58>=300, 0, IF(Q58>=240, -1, -2)))))) -> 1 | O58: =IF(P58>=540, 4, IF(P58>=480, 3, IF(P58>=420, 2, IF(P58>=360, 1, IF(P58>=300, 0, IF(P58>=240, -1, -2)))))) -> -2 | P58: =sum(T58:Z58) -> 187 | Q58: =R58*6 -> 374 | R58: =iferror(P58/S58,"0") -> 62.333333 | S58: =count(T58:Z58) -> 3 | T58: 64 | U58: 77 | V58: 46 | W58: ー | X58: ー | Y58: ー | Z58: ー | AA58: =Vlookup(B58,'セッション実施状況管理'!$A:$R,17,false) | AB58: =(YEAR(TODAY()) - YEAR($AA58)) * 12 + (MONTH(TODAY()) - MONTH($AA58)) -> 1514 | AC58: =IF( OR(AB58=3, AB58=4, AB58=5, AB58=6), "1", "2" ) -> 2
B59: 41 | C59: =vlookup(B59,'セッション実施状況管理'!$A:$U,8,false) -> つかだひさえ | D59: =vlookup(B59,'セッション実施状況管理'!$A:$I,9,false) -> つかだひさえ | E59: https://docs.google.com/spreadsheets/d/1jQFF11-NlB3UKVvEQ1qr1N4R7OXYXRHcRh6K2FJwwrg/edit?usp=sharing | F59: =vlookup(B59,'セッション実施状況管理'!$A:$U,20,false) -> 須見浩人 | G59: =vlookup(B59,'セッション実施状況管理'!$A:$U,20,false) -> 須見浩人 | H59: ='コーチング報酬管理'!G47 -> 13 | I59: =iferror(vlookup(B59,'セッション実施状況管理'!$A:$B,2,false),"") -> 音不 | J59: 0 | K59: -1 | L59: =VLOOKUP(B59,'新 月次投稿数'!$A:$N,13,false) -> 0 | M59: =IF(L59>=100, 4, IF(L59>=81, 3, IF(L59>=56, 2, IF(L59>=31, 1, 0)))) -> 0 | N59: =IF(Q59>=540, 4, IF(Q59>=480, 3, IF(Q59>=420, 2, IF(Q59>=360, 1, IF(Q59>=300, 0, IF(Q59>=240, -1, -2)))))) -> -2 | O59: =IF(P59>=540, 4, IF(P59>=480, 3, IF(P59>=420, 2, IF(P59>=360, 1, IF(P59>=300, 0, IF(P59>=240, -1, -2)))))) -> -2 | P59: =sum(T59:Z59) -> 6 | Q59: =R59*6 -> 18 | R59: =iferror(P59/S59,"0") -> 3 | S59: =count(T59:Z59) -> 2 | T59: 0 | U59: 6 | V59: ー | W59: ー | X59: ー | Y59: ー | Z59: ー | AA59: =Vlookup(B59,'セッション実施状況管理'!$A:$R,17,false) | AB59: =(YEAR(TODAY()) - YEAR($AA59)) * 12 + (MONTH(TODAY()) - MONTH($AA59)) -> 1514 | AC59: =IF( OR(AB59=3, AB59=4, AB59=5, AB59=6), "1", "2" ) -> 2
B60: 42 | C60: =vlookup(B60,'セッション実施状況管理'!$A:$U,8,false) -> すがわらようこ | D60: =vlookup(B60,'セッション実施状況管理'!$A:$I,9,false) -> Daily_Bag_Storie | E60: https://docs.google.com/spreadsheets/d/1otQobybd52I1J6FPx51aKUr94LHXkarSkef57LsVlog/edit?gid=1837929075#gid=1837929075 | F60: =vlookup(B60,'セッション実施状況管理'!$A:$U,20,false) -> 福田康裕 | G60: =vlookup(B60,'セッション実施状況管理'!$A:$U,20,false) -> 福田康裕 | H60: ='コーチング報酬管理'!G48 -> 7 | I60: =iferror(vlookup(B60,'セッション実施状況管理'!$A:$B,2,false),"") -> 卒業 | J60: 0 | K60: 2 | L60: =VLOOKUP(B60,'新 月次投稿数'!$A:$N,13,false) -> 68 | M60: =IF(L60>=100, 4, IF(L60>=81, 3, IF(L60>=56, 2, IF(L60>=31, 1, 0)))) -> 2 | N60: =IF(Q60>=540, 4, IF(Q60>=480, 3, IF(Q60>=420, 2, IF(Q60>=360, 1, IF(Q60>=300, 0, IF(Q60>=240, -1, -2)))))) -> -2 | O60: =IF(P60>=540, 4, IF(P60>=480, 3, IF(P60>=420, 2, IF(P60>=360, 1, IF(P60>=300, 0, IF(P60>=240, -1, -2)))))) -> -2 | P60: =sum(T60:Z60) -> 98 | Q60: =R60*6 -> 84 | R60: =iferror(P60/S60,"0") -> 14 | S60: =count(T60:Z60) -> 7 | T60: 1 | U60: 9 | V60: 20 | W60: 38 | X60: 30 | Y60: 0 | Z60: 0 | AA60: =Vlookup(B60,'セッション実施状況管理'!$A:$R,17,false) | AB60: =(YEAR(TODAY()) - YEAR($AA60)) * 12 + (MONTH(TODAY()) - MONTH($AA60)) -> 1514 | AC60: =IF( OR(AB60=3, AB60=4, AB60=5, AB60=6), "1", "2" ) -> 2
B61: 43 | C61: =vlookup(B61,'セッション実施状況管理'!$A:$U,8,false) -> さかがみけいた | D61: =vlookup(B61,'セッション実施状況管理'!$A:$I,9,false) -> tedori19.men | E61: https://docs.google.com/spreadsheets/d/1d77fNnj8kZBtaGnHf0ctthbmIwyZgdDrh5j5VDxQmLw/edit?usp=sharing | F61: =vlookup(B61,'セッション実施状況管理'!$A:$U,20,false) -> 多田祐輔 | G61: =vlookup(B61,'セッション実施状況管理'!$A:$U,20,false) -> 多田祐輔 | H61: ='コーチング報酬管理'!G49 -> 13 | I61: =iferror(vlookup(B61,'セッション実施状況管理'!$A:$B,2,false),"") -> 音不 | J61: 0 | K61: 0 | L61: =VLOOKUP(B61,'新 月次投稿数'!$A:$N,13,false) -> 0 | M61: =IF(L61>=100, 4, IF(L61>=81, 3, IF(L61>=56, 2, IF(L61>=31, 1, 0)))) -> 0 | N61: =IF(Q61>=540, 4, IF(Q61>=480, 3, IF(Q61>=420, 2, IF(Q61>=360, 1, IF(Q61>=300, 0, IF(Q61>=240, -1, -2)))))) -> 1 | O61: =IF(P61>=540, 4, IF(P61>=480, 3, IF(P61>=420, 2, IF(P61>=360, 1, IF(P61>=300, 0, IF(P61>=240, -1, -2)))))) -> 0 | P61: =sum(T61:Z61) -> 328 | Q61: =R61*6 -> 393.6 | R61: =iferror(P61/S61,"0") -> 65.6 | S61: =count(T61:Z61) -> 5 | T61: 26 | U61: 103 | V61: 51 | W61: 60 | X61: 88 | Y61: ー | Z61: ー | AA61: =Vlookup(B61,'セッション実施状況管理'!$A:$R,17,false) | AB61: =(YEAR(TODAY()) - YEAR($AA61)) * 12 + (MONTH(TODAY()) - MONTH($AA61)) -> 1514 | AC61: =IF( OR(AB61=3, AB61=4, AB61=5, AB61=6), "1", "2" ) -> 2
B62: 44 | C62: =vlookup(B62,'セッション実施状況管理'!$A:$U,8,false) -> いけぐちはるか | D62: =vlookup(B62,'セッション実施状況管理'!$A:$I,9,false) -> haru_bodymake_ | E62: https://docs.google.com/spreadsheets/d/1SQ5HuJae9eTM_r1ZGWkiRdH9vJv4qajZrmRnmvtHgu8/edit?gid=1519876919#gid=1519876919 | F62: =vlookup(B62,'セッション実施状況管理'!$A:$U,20,false) -> 森本風花 | G62: =vlookup(B62,'セッション実施状況管理'!$A:$U,20,false) -> 森本風花 | H62: ='コーチング報酬管理'!G50 -> 11 | I62: =iferror(vlookup(B62,'セッション実施状況管理'!$A:$B,2,false),"") -> 卒業 | J62: 0 | K62: 2 | L62: =VLOOKUP(B62,'新 月次投稿数'!$A:$N,13,false) -> 102 | M62: =IF(L62>=100, 4, IF(L62>=81, 3, IF(L62>=56, 2, IF(L62>=31, 1, 0)))) -> 4 | N62: =IF(Q62>=540, 4, IF(Q62>=480, 3, IF(Q62>=420, 2, IF(Q62>=360, 1, IF(Q62>=300, 0, IF(Q62>=240, -1, -2)))))) -> -2 | O62: =IF(P62>=540, 4, IF(P62>=480, 3, IF(P62>=420, 2, IF(P62>=360, 1, IF(P62>=300, 0, IF(P62>=240, -1, -2)))))) -> -1 | P62: =sum(T62:Z62) -> 240 | Q62: =R62*6 -> 205.71429 | R62: =iferror(P62/S62,"0") -> 34.285714 | S62: =count(T62:Z62) -> 7 | T62: 14 | U62: 38 | V62: 24 | W62: 12 | X62: 78 | Y62: 53 | Z62: 21 | AA62: =Vlookup(B62,'セッション実施状況管理'!$A:$R,17,false) | AB62: =(YEAR(TODAY()) - YEAR($AA62)) * 12 + (MONTH(TODAY()) - MONTH($AA62)) -> 1514 | AC62: =IF( OR(AB62=3, AB62=4, AB62=5, AB62=6), "1", "2" ) -> 2
A63: 120投稿生 | B63: 45 | C63: =vlookup(B63,'セッション実施状況管理'!$A:$U,8,false) -> ふじためぐみ | D63: =vlookup(B63,'セッション実施状況管理'!$A:$I,9,false) -> megu_study_ | E63: https://docs.google.com/spreadsheets/d/1nx1gDIkVqGDoNx2Cl-w9rIUFbUHUz51gZrzOiXhWNL4/edit?usp=sharing | F63: =vlookup(B63,'セッション実施状況管理'!$A:$U,20,false) -> 森本風花 | G63: =vlookup(B63,'セッション実施状況管理'!$A:$U,20,false) -> 森本風花 | H63: ='コーチング報酬管理'!G51 -> 13 | I63: =iferror(vlookup(B63,'セッション実施状況管理'!$A:$B,2,false),"") -> 卒業 | J63: 0 | K63: 0 | L63: =VLOOKUP(B63,'新 月次投稿数'!$A:$N,13,false) -> 76 | M63: =IF(L63>=100, 4, IF(L63>=81, 3, IF(L63>=56, 2, IF(L63>=31, 1, 0)))) -> 2 | N63: =IF(Q63>=540, 4, IF(Q63>=480, 3, IF(Q63>=420, 2, IF(Q63>=360, 1, IF(Q63>=300, 0, IF(Q63>=240, -1, -2)))))) -> 4 | O63: =IF(P63>=540, 4, IF(P63>=480, 3, IF(P63>=420, 2, IF(P63>=360, 1, IF(P63>=300, 0, IF(P63>=240, -1, -2)))))) -> 4 | P63: =sum(T63:Z63) -> 751 | Q63: =R63*6 -> 643.71429 | R63: =iferror(P63/S63,"0") -> 107.28571 | S63: =count(T63:Z63) -> 7 | T63: 106 | U63: 165 | V63: 96 | W63: 88 | X63: 97 | Y63: 114 | Z63: 85 | AA63: =Vlookup(B63,'セッション実施状況管理'!$A:$R,17,false) | AB63: =(YEAR(TODAY()) - YEAR($AA63)) * 12 + (MONTH(TODAY()) - MONTH($AA63)) -> 1514 | AC63: =IF( OR(AB63=3, AB63=4, AB63=5, AB63=6), "1", "2" ) -> 2
A64: 120投稿生 | B64: 46 | C64: =vlookup(B64,'セッション実施状況管理'!$A:$U,8,false) -> いしかわまい | D64: =vlookup(B64,'セッション実施状況管理'!$A:$I,9,false) -> rio_kurahi_ | E64: https://docs.google.com/spreadsheets/d/1_pg5KqZzYBQSwQuapTI79iH-errU6r-0qWoVbFwvd0s/edit?usp=sharing | F64: =vlookup(B64,'セッション実施状況管理'!$A:$U,20,false) -> 清原三和子 | G64: =vlookup(B64,'セッション実施状況管理'!$A:$U,20,false) -> 清原三和子 | H64: ='コーチング報酬管理'!G40 -> 4 | I64: =iferror(vlookup(B64,'セッション実施状況管理'!$A:$B,2,false),"") -> 卒業 | J64: 0 | K64: 0 | L64: =VLOOKUP(B64,'新 月次投稿数'!$A:$N,13,false) -> 57 | M64: =IF(L64>=100, 4, IF(L64>=81, 3, IF(L64>=56, 2, IF(L64>=31, 1, 0)))) -> 2 | N64: =IF(Q64>=540, 4, IF(Q64>=480, 3, IF(Q64>=420, 2, IF(Q64>=360, 1, IF(Q64>=300, 0, IF(Q64>=240, -1, -2)))))) -> 3 | O64: =IF(P64>=540, 4, IF(P64>=480, 3, IF(P64>=420, 2, IF(P64>=360, 1, IF(P64>=300, 0, IF(P64>=240, -1, -2)))))) -> 4 | P64: =sum(T64:Z64) -> 629 | Q64: =R64*6 -> 539.14286 | R64: =iferror(P64/S64,"0") -> 89.857143 | S64: =count(T64:Z64) -> 7 | T64: 0 | U64: 33 | V64: 175 | W64: 107 | X64: 105 | Y64: 107 | Z64: 102 | AA64: =Vlookup(B64,'セッション実施状況管理'!$A:$R,17,false) | AB64: =(YEAR(TODAY()) - YEAR($AA64)) * 12 + (MONTH(TODAY()) - MONTH($AA64)) -> 1514 | AC64: =IF( OR(AB64=3, AB64=4, AB64=5, AB64=6), "1", "2" ) -> 2
A65: 120投稿生 | B65: 47 | C65: =vlookup(B65,'セッション実施状況管理'!$A:$U,8,false) -> なかじまえみ | D65: =vlookup(B65,'セッション実施状況管理'!$A:$I,9,false) -> なかじまえみ | E65: https://docs.google.com/spreadsheets/d/1FeQAKQ0e5IPTM8i1QLDx_O4jnpNUNFNF-tdJV37FpM4/edit | F65: =vlookup(B65,'セッション実施状況管理'!$A:$U,20,false) -> 須見浩人 | G65: =vlookup(B65,'セッション実施状況管理'!$A:$U,20,false) -> 須見浩人 | H65: ='コーチング報酬管理'!G53 -> 13 | I65: =iferror(vlookup(B65,'セッション実施状況管理'!$A:$B,2,false),"") -> 卒業 | J65: 0 | K65: 0 | L65: =VLOOKUP(B65,'新 月次投稿数'!$A:$N,13,false) -> 1 | M65: =IF(L65>=100, 4, IF(L65>=81, 3, IF(L65>=56, 2, IF(L65>=31, 1, 0)))) -> 0 | N65: =IF(Q65>=540, 4, IF(Q65>=480, 3, IF(Q65>=420, 2, IF(Q65>=360, 1, IF(Q65>=300, 0, IF(Q65>=240, -1, -2)))))) -> -1 | O65: =IF(P65>=540, 4, IF(P65>=480, 3, IF(P65>=420, 2, IF(P65>=360, 1, IF(P65>=300, 0, IF(P65>=240, -1, -2)))))) -> 0 | P65: =sum(T65:Z65) -> 325 | Q65: =R65*6 -> 278.57143 | R65: =iferror(P65/S65,"0") -> 46.428571 | S65: =count(T65:Z65) -> 7 | T65: 0 | U65: 117 | V65: 76 | W65: 78 | X65: 54 | Y65: 0 | Z65: 0 | AA65: =Vlookup(B65,'セッション実施状況管理'!$A:$R,17,false) | AB65: =(YEAR(TODAY()) - YEAR($AA65)) * 12 + (MONTH(TODAY()) - MONTH($AA65)) -> 1514 | AC65: =IF( OR(AB65=3, AB65=4, AB65=5, AB65=6), "1", "2" ) -> 2
A66: 120投稿生 | B66: 48 | C66: =vlookup(B66,'セッション実施状況管理'!$A:$U,8,false) -> やまだつかさ | D66: =vlookup(B66,'セッション実施状況管理'!$A:$I,9,false) -> cbd_bao | E66: https://docs.google.com/spreadsheets/d/17EkWnSWJwrJ4r5T-Mmxe-CetQl9oAnCGJ4llyFAgKtU/edit?usp=sharing | F66: =vlookup(B66,'セッション実施状況管理'!$A:$U,20,false) -> 小針彩乃 | G66: =vlookup(B66,'セッション実施状況管理'!$A:$U,20,false) -> 小針彩乃 | H66: ='コーチング報酬管理'!G54 -> 13 | I66: =iferror(vlookup(B66,'セッション実施状況管理'!$A:$B,2,false),"") -> 卒業 | J66: 0 | K66: 0 | L66: =VLOOKUP(B66,'新 月次投稿数'!$A:$N,13,false) -> 72 | M66: =IF(L66>=100, 4, IF(L66>=81, 3, IF(L66>=56, 2, IF(L66>=31, 1, 0)))) -> 2 | N66: =IF(Q66>=540, 4, IF(Q66>=480, 3, IF(Q66>=420, 2, IF(Q66>=360, 1, IF(Q66>=300, 0, IF(Q66>=240, -1, -2)))))) -> -1 | O66: =IF(P66>=540, 4, IF(P66>=480, 3, IF(P66>=420, 2, IF(P66>=360, 1, IF(P66>=300, 0, IF(P66>=240, -1, -2)))))) -> 0 | P66: =sum(T66:Z66) -> 307 | Q66: =R66*6 -> 263.14286 | R66: =iferror(P66/S66,"0") -> 43.857143 | S66: =count(T66:Z66) -> 7 | T66: 0 | U66: 52 | V66: 65 | W66: 65 | X66: 57 | Y66: 63 | Z66: 5 | AA66: =Vlookup(B66,'セッション実施状況管理'!$A:$R,17,false) | AB66: =(YEAR(TODAY()) - YEAR($AA66)) * 12 + (MONTH(TODAY()) - MONTH($AA66)) -> 1514 | AC66: =IF( OR(AB66=3, AB66=4, AB66=5, AB66=6), "1", "2" ) -> 2
B67: 49 | C67: =vlookup(B67,'セッション実施状況管理'!$A:$U,8,false) -> ななやまたえこ | D67: =vlookup(B67,'セッション実施状況管理'!$A:$I,9,false) -> ななやまたえこ | E67: https://docs.google.com/spreadsheets/d/1FOlzcxfNqueQQCJw_EG8x9LZrNjY8nFCF3sUXbyxr1o/edit?usp=sharing | F67: =vlookup(B67,'セッション実施状況管理'!$A:$U,20,false) -> 清原三和子 | G67: =vlookup(B67,'セッション実施状況管理'!$A:$U,20,false) -> 清原三和子 | H67: ='コーチング報酬管理'!G55 -> 13 | I67: =iferror(vlookup(B67,'セッション実施状況管理'!$A:$B,2,false),"") -> 例外 | J67: 0 | K67: 0 | L67: =VLOOKUP(B67,'新 月次投稿数'!$A:$N,13,false) -> 0 | M67: =IF(L67>=100, 4, IF(L67>=81, 3, IF(L67>=56, 2, IF(L67>=31, 1, 0)))) -> 0 | N67: =IF(Q67>=540, 4, IF(Q67>=480, 3, IF(Q67>=420, 2, IF(Q67>=360, 1, IF(Q67>=300, 0, IF(Q67>=240, -1, -2)))))) -> -2 | O67: =IF(P67>=540, 4, IF(P67>=480, 3, IF(P67>=420, 2, IF(P67>=360, 1, IF(P67>=300, 0, IF(P67>=240, -1, -2)))))) -> -2 | P67: =sum(T67:Z67) -> 0 | Q67: =R67*6 -> 0 | R67: =iferror(P67/S67,"0") -> 0 | S67: =count(T67:Z67) -> 0 | T67: ー | U67: ー | V67: ー | W67: ー | X67: ー | Y67: ー | Z67: ー | AA67: =Vlookup(B67,'セッション実施状況管理'!$A:$R,17,false) | AB67: =(YEAR(TODAY()) - YEAR($AA67)) * 12 + (MONTH(TODAY()) - MONTH($AA67)) -> 1514 | AC67: =IF( OR(AB67=3, AB67=4, AB67=5, AB67=6), "1", "2" ) -> 2
A68: 120投稿生 | B68: 50 | C68: =vlookup(B68,'セッション実施状況管理'!$A:$U,8,false) -> しもたかたにかな | D68: =vlookup(B68,'セッション実施状況管理'!$A:$I,9,false) -> kana_and_english | E68: https://docs.google.com/spreadsheets/d/1w7DziHt8oLtqrqqryhDskFi9g0hakM37GHtj28eY0Es/edit?gid=997181537#gid=997181537 | F68: =vlookup(B68,'セッション実施状況管理'!$A:$U,20,false) -> 山見阪佳子 | G68: =vlookup(B68,'セッション実施状況管理'!$A:$U,20,false) -> 山見阪佳子 | H68: ='コーチング報酬管理'!G56 -> 6 | I68: =iferror(vlookup(B68,'セッション実施状況管理'!$A:$B,2,false),"") -> 卒業 | J68: 0 | K68: 0 | L68: =VLOOKUP(B68,'新 月次投稿数'!$A:$N,13,false) -> 96 | M68: =IF(L68>=100, 4, IF(L68>=81, 3, IF(L68>=56, 2, IF(L68>=31, 1, 0)))) -> 3 | N68: =IF(Q68>=540, 4, IF(Q68>=480, 3, IF(Q68>=420, 2, IF(Q68>=360, 1, IF(Q68>=300, 0, IF(Q68>=240, -1, -2)))))) -> 4 | O68: =IF(P68>=540, 4, IF(P68>=480, 3, IF(P68>=420, 2, IF(P68>=360, 1, IF(P68>=300, 0, IF(P68>=240, -1, -2)))))) -> 4 | P68: =sum(T68:Z68) -> 647 | Q68: =R68*6 -> 554.57143 | R68: =iferror(P68/S68,"0") -> 92.428571 | S68: =count(T68:Z68) -> 7 | T68: 63 | U68: 79 | V68: 73 | W68: 104 | X68: 124 | Y68: 109 | Z68: 95 | AA68: =Vlookup(B68,'セッション実施状況管理'!$A:$R,17,false) | AB68: =(YEAR(TODAY()) - YEAR($AA68)) * 12 + (MONTH(TODAY()) - MONTH($AA68)) -> 1514 | AC68: =IF( OR(AB68=3, AB68=4, AB68=5, AB68=6), "1", "2" ) -> 2
A69: 120投稿生 | B69: 51 | C69: =vlookup(B69,'セッション実施状況管理'!$A:$U,8,false) -> たなかゆみこ | D69: =vlookup(B69,'セッション実施状況管理'!$A:$I,9,false) -> yumimama_gohan | E69: https://docs.google.com/spreadsheets/d/1DnJk4CGiYGl9ZHmZV7usbbf2SBA_JBfVUD9YXJU9ufE/edit?usp=sharing | F69: =vlookup(B69,'セッション実施状況管理'!$A:$U,20,false) -> 野村佑佳 | G69: =vlookup(B69,'セッション実施状況管理'!$A:$U,20,false) -> 野村佑佳 | H69: ='コーチング報酬管理'!G57 -> 12 | I69: =iferror(vlookup(B69,'セッション実施状況管理'!$A:$B,2,false),"") -> 卒業 | J69: 0 | K69: 0 | L69: =VLOOKUP(B69,'新 月次投稿数'!$A:$N,13,false) -> 74 | M69: =IF(L69>=100, 4, IF(L69>=81, 3, IF(L69>=56, 2, IF(L69>=31, 1, 0)))) -> 2 | N69: =IF(Q69>=540, 4, IF(Q69>=480, 3, IF(Q69>=420, 2, IF(Q69>=360, 1, IF(Q69>=300, 0, IF(Q69>=240, -1, -2)))))) -> 3 | O69: =IF(P69>=540, 4, IF(P69>=480, 3, IF(P69>=420, 2, IF(P69>=360, 1, IF(P69>=300, 0, IF(P69>=240, -1, -2)))))) -> 4 | P69: =sum(T69:Z69) -> 589 | Q69: =R69*6 -> 504.85714 | R69: =iferror(P69/S69,"0") -> 84.142857 | S69: =count(T69:Z69) -> 7 | T69: 84 | U69: 104 | V69: 84 | W69: 80 | X69: 81 | Y69: 81 | Z69: 75 | AA69: =Vlookup(B69,'セッション実施状況管理'!$A:$R,17,false) | AB69: =(YEAR(TODAY()) - YEAR($AA69)) * 12 + (MONTH(TODAY()) - MONTH($AA69)) -> 1514 | AC69: =IF( OR(AB69=3, AB69=4, AB69=5, AB69=6), "1", "2" ) -> 2
A70: 120投稿生 | B70: 52 | C70: =vlookup(B70,'セッション実施状況管理'!$A:$U,8,false) -> こせきあゆみ | D70: =vlookup(B70,'セッション実施状況管理'!$A:$I,9,false) -> nabeko_kurashi | E70: https://docs.google.com/spreadsheets/d/151mQZY8cgk5_7Q59N_ET3Hj7l7ZcJMP6G8_fl6uqI8U/edit?gid=0#gid=0 | F70: =vlookup(B70,'セッション実施状況管理'!$A:$U,20,false) -> 森本風花 | G70: =vlookup(B70,'セッション実施状況管理'!$A:$U,20,false) -> 森本風花 | H70: ='コーチング報酬管理'!G58 -> 12 | I70: =iferror(vlookup(B70,'セッション実施状況管理'!$A:$B,2,false),"") -> 卒業 | J70: 0 | K70: 0 | L70: =VLOOKUP(B70,'新 月次投稿数'!$A:$N,13,false) -> 80 | M70: =IF(L70>=100, 4, IF(L70>=81, 3, IF(L70>=56, 2, IF(L70>=31, 1, 0)))) -> 2 | N70: =IF(Q70>=540, 4, IF(Q70>=480, 3, IF(Q70>=420, 2, IF(Q70>=360, 1, IF(Q70>=300, 0, IF(Q70>=240, -1, -2)))))) -> 2 | O70: =IF(P70>=540, 4, IF(P70>=480, 3, IF(P70>=420, 2, IF(P70>=360, 1, IF(P70>=300, 0, IF(P70>=240, -1, -2)))))) -> 4 | P70: =sum(T70:Z70) -> 540 | Q70: =R70*6 -> 462.85714 | R70: =iferror(P70/S70,"0") -> 77.142857 | S70: =count(T70:Z70) -> 7 | T70: 72 | U70: 96 | V70: 85 | W70: 81 | X70: 80 | Y70: 79 | Z70: 47 | AA70: =Vlookup(B70,'セッション実施状況管理'!$A:$R,17,false) | AB70: =(YEAR(TODAY()) - YEAR($AA70)) * 12 + (MONTH(TODAY()) - MONTH($AA70)) -> 1514 | AC70: =IF( OR(AB70=3, AB70=4, AB70=5, AB70=6), "1", "2" ) -> 2
A71: 120投稿生 | B71: 53 | C71: =vlookup(B71,'セッション実施状況管理'!$A:$U,8,false) -> わだよしろう | D71: =vlookup(B71,'セッション実施状況管理'!$A:$I,9,false) -> dr.sora_ped | E71: https://docs.google.com/spreadsheets/d/1lv4vqmJ8QeM-m4aVV46mDtCgFlU5jIcJjsV73F4vj-w/edit?usp=sharing https://docs.google.com/spreadsheets/d/1GOn6TW2r2-3bGJ3Lr9Ewv99Pz2jOc3UKYgjySC5msVg/edit?usp=sharing | F71: =vlookup(B71,'セッション実施状況管理'!$A:$U,20,false) -> 野村佑佳 | G71: =vlookup(B71,'セッション実施状況管理'!$A:$U,20,false) -> 野村佑佳 | H71: ='コーチング報酬管理'!G59 -> 13 | I71: =iferror(vlookup(B71,'セッション実施状況管理'!$A:$B,2,false),"") -> 卒業 | J71: 1 | K71: 2 | L71: =VLOOKUP(B71,'新 月次投稿数'!$A:$N,13,false) -> 115 | M71: =IF(L71>=100, 4, IF(L71>=81, 3, IF(L71>=56, 2, IF(L71>=31, 1, 0)))) -> 4 | N71: =IF(Q71>=540, 4, IF(Q71>=480, 3, IF(Q71>=420, 2, IF(Q71>=360, 1, IF(Q71>=300, 0, IF(Q71>=240, -1, -2)))))) -> 2 | O71: =IF(P71>=540, 4, IF(P71>=480, 3, IF(P71>=420, 2, IF(P71>=360, 1, IF(P71>=300, 0, IF(P71>=240, -1, -2)))))) -> 3 | P71: =sum(T71:Z71) -> 537 | Q71: =R71*6 -> 460.28571 | R71: =iferror(P71/S71,"0") -> 76.714286 | S71: =count(T71:Z71) -> 7 | T71: 41 | U71: 98 | V71: 102 | W71: 71 | X71: 81 | Y71: 79 | Z71: 65 | AA71: =Vlookup(B71,'セッション実施状況管理'!$A:$R,17,false) | AB71: =(YEAR(TODAY()) - YEAR($AA71)) * 12 + (MONTH(TODAY()) - MONTH($AA71)) -> 1514 | AC71: =IF( OR(AB71=3, AB71=4, AB71=5, AB71=6), "1", "2" ) -> 2
A72: 120投稿生 | B72: 54 | C72: =vlookup(B72,'セッション実施状況管理'!$A:$U,8,false) -> こもりみちこ | D72: =vlookup(B72,'セッション実施状況管理'!$A:$I,9,false) -> shiia_zubora_gohan | E72: https://docs.google.com/spreadsheets/d/1dsb-jSrU9cc_c0mk5JAll4Iy0YdqQvWMcVwT3x-vH8s/edit?gid=1837929075#gid=1837929075 | F72: =vlookup(B72,'セッション実施状況管理'!$A:$U,20,false) -> 有山友菜 | G72: =vlookup(B72,'セッション実施状況管理'!$A:$U,20,false) -> 有山友菜 | H72: ='コーチング報酬管理'!G60 -> 13 | I72: =iferror(vlookup(B72,'セッション実施状況管理'!$A:$B,2,false),"") -> 卒業 | J72: 0 | K72: 0 | L72: =VLOOKUP(B72,'新 月次投稿数'!$A:$N,13,false) -> 102 | M72: =IF(L72>=100, 4, IF(L72>=81, 3, IF(L72>=56, 2, IF(L72>=31, 1, 0)))) -> 4 | N72: =IF(Q72>=540, 4, IF(Q72>=480, 3, IF(Q72>=420, 2, IF(Q72>=360, 1, IF(Q72>=300, 0, IF(Q72>=240, -1, -2)))))) -> 2 | O72: =IF(P72>=540, 4, IF(P72>=480, 3, IF(P72>=420, 2, IF(P72>=360, 1, IF(P72>=300, 0, IF(P72>=240, -1, -2)))))) -> 3 | P72: =sum(T72:Z72) -> 514 | Q72: =R72*6 -> 440.57143 | R72: =iferror(P72/S72,"0") -> 73.428571 | S72: =count(T72:Z72) -> 7 | T72: 47 | U72: 75 | V72: 94 | W72: 92 | X72: 75 | Y72: 73 | Z72: 58 | AA72: =Vlookup(B72,'セッション実施状況管理'!$A:$R,17,false) | AB72: =(YEAR(TODAY()) - YEAR($AA72)) * 12 + (MONTH(TODAY()) - MONTH($AA72)) -> 1514 | AC72: =IF( OR(AB72=3, AB72=4, AB72=5, AB72=6), "1", "2" ) -> 2
A73: 120投稿生 | B73: 55 | C73: =vlookup(B73,'セッション実施状況管理'!$A:$U,8,false) -> にしじまなおこ | D73: =vlookup(B73,'セッション実施状況管理'!$A:$I,9,false) -> nao_mamadiet_39 | E73: https://docs.google.com/spreadsheets/d/1ear-6aN5nVpIjEG_k_UPzDUD_MvWpiN0WxY0qq5cmQI/edit?gid=1837929075#gid=1837929075 | F73: =vlookup(B73,'セッション実施状況管理'!$A:$U,20,false) -> 福田康裕 | G73: =vlookup(B73,'セッション実施状況管理'!$A:$U,20,false) -> 福田康裕 | H73: ='コーチング報酬管理'!G61 -> 13 | I73: =iferror(vlookup(B73,'セッション実施状況管理'!$A:$B,2,false),"") -> 卒業 | J73: 0 | K73: 0 | L73: =VLOOKUP(B73,'新 月次投稿数'!$A:$N,13,false) -> 62 | M73: =IF(L73>=100, 4, IF(L73>=81, 3, IF(L73>=56, 2, IF(L73>=31, 1, 0)))) -> 2 | N73: =IF(Q73>=540, 4, IF(Q73>=480, 3, IF(Q73>=420, 2, IF(Q73>=360, 1, IF(Q73>=300, 0, IF(Q73>=240, -1, -2)))))) -> 0 | O73: =IF(P73>=540, 4, IF(P73>=480, 3, IF(P73>=420, 2, IF(P73>=360, 1, IF(P73>=300, 0, IF(P73>=240, -1, -2)))))) -> 0 | P73: =sum(T73:Z73) -> 354 | Q73: =R73*6 -> 303.42857 | R73: =iferror(P73/S73,"0") -> 50.571429 | S73: =count(T73:Z73) -> 7 | T73: 23 | U73: 79 | V73: 98 | W73: 83 | X73: 71 | Y73: 0 | Z73: 0 | AA73: =Vlookup(B73,'セッション実施状況管理'!$A:$R,17,false) | AB73: =(YEAR(TODAY()) - YEAR($AA73)) * 12 + (MONTH(TODAY()) - MONTH($AA73)) -> 1514 | AC73: =IF( OR(AB73=3, AB73=4, AB73=5, AB73=6), "1", "2" ) -> 2
A74: 120投稿生 | B74: 56 | C74: =vlookup(B74,'セッション実施状況管理'!$A:$U,8,false) -> あらききみえ | D74: aki157_diet | E74: https://docs.google.com/spreadsheets/d/1cgXmUgeV2eKA6n499noe4cs7p6E30ynLDb9EwSnRwyk/edit?gid=0#gid=0 | F74: =vlookup(B74,'セッション実施状況管理'!$A:$U,20,false) -> 鈴木久美子 | G74: =vlookup(B74,'セッション実施状況管理'!$A:$U,20,false) -> 鈴木久美子 | H74: ='コーチング報酬管理'!G62 -> 7 | I74: =iferror(vlookup(B74,'セッション実施状況管理'!$A:$B,2,false),"") -> 卒業 | J74: 0 | K74: 0 | L74: =VLOOKUP(B74,'新 月次投稿数'!$A:$N,13,false) -> 120 | M74: =IF(L74>=100, 4, IF(L74>=81, 3, IF(L74>=56, 2, IF(L74>=31, 1, 0)))) -> 4 | N74: =IF(Q74>=540, 4, IF(Q74>=480, 3, IF(Q74>=420, 2, IF(Q74>=360, 1, IF(Q74>=300, 0, IF(Q74>=240, -1, -2)))))) -> 2 | O74: =IF(P74>=540, 4, IF(P74>=480, 3, IF(P74>=420, 2, IF(P74>=360, 1, IF(P74>=300, 0, IF(P74>=240, -1, -2)))))) -> 4 | P74: =sum(T74:Z74) -> 554 | Q74: =R74*6 -> 474.85714 | R74: =iferror(P74/S74,"0") -> 79.142857 | S74: =count(T74:Z74) -> 7 | T74: 36 | U74: 95 | V74: 91 | W74: 91 | X74: 82 | Y74: 91 | Z74: 68 | AA74: =Vlookup(B74,'セッション実施状況管理'!$A:$R,17,false) | AB74: =(YEAR(TODAY()) - YEAR($AA74)) * 12 + (MONTH(TODAY()) - MONTH($AA74)) -> 1514 | AC74: =IF( OR(AB74=3, AB74=4, AB74=5, AB74=6), "1", "2" ) -> 2
A75: 120投稿生 | B75: 57 | C75: =vlookup(B75,'セッション実施状況管理'!$A:$U,8,false) -> しがあかね | D75: =vlookup(B75,'セッション実施状況管理'!$A:$I,9,false) -> shiga_chan_diet | E75: https://docs.google.com/spreadsheets/d/1cgXmUgeV2eKA6n499noe4cs7p6E30ynLDb9EwSnRwyk/edit | F75: =vlookup(B75,'セッション実施状況管理'!$A:$U,20,false) -> 有山友菜 | G75: =vlookup(B75,'セッション実施状況管理'!$A:$U,20,false) -> 有山友菜 | H75: ='コーチング報酬管理'!G63 -> 7 | I75: =iferror(vlookup(B75,'セッション実施状況管理'!$A:$B,2,false),"") -> 卒業 | J75: 0 | K75: 0 | L75: =VLOOKUP(B75,'新 月次投稿数'!$A:$N,13,false) -> 79 | M75: =IF(L75>=100, 4, IF(L75>=81, 3, IF(L75>=56, 2, IF(L75>=31, 1, 0)))) -> 2 | N75: =IF(Q75>=540, 4, IF(Q75>=480, 3, IF(Q75>=420, 2, IF(Q75>=360, 1, IF(Q75>=300, 0, IF(Q75>=240, -1, -2)))))) -> 2 | O75: =IF(P75>=540, 4, IF(P75>=480, 3, IF(P75>=420, 2, IF(P75>=360, 1, IF(P75>=300, 0, IF(P75>=240, -1, -2)))))) -> 3 | P75: =sum(T75:Z75) -> 533 | Q75: =R75*6 -> 456.85714 | R75: =iferror(P75/S75,"0") -> 76.142857 | S75: =count(T75:Z75) -> 7 | T75: 4 | U75: 78 | V75: 89 | W75: 108 | X75: 83 | Y75: 89 | Z75: 82 | AA75: =Vlookup(B75,'セッション実施状況管理'!$A:$R,17,false) | AB75: =(YEAR(TODAY()) - YEAR($AA75)) * 12 + (MONTH(TODAY()) - MONTH($AA75)) -> 1514 | AC75: =IF( OR(AB75=3, AB75=4, AB75=5, AB75=6), "1", "2" ) -> 2
A76: 120投稿生 | B76: 58 | C76: =vlookup(B76,'セッション実施状況管理'!$A:$U,8,false) -> ねもとみさ | D76: =vlookup(B76,'セッション実施状況管理'!$A:$I,9,false) -> misa_sweets_diet | E76: https://docs.google.com/spreadsheets/d/1HqPVDdr26PvLp1LiurBog8pPnESlPZf4cT6jYF9SROU/edit?gid=1449816138#gid=1449816138 | F76: =vlookup(B76,'セッション実施状況管理'!$A:$U,20,false) -> 長尾あみり | G76: =vlookup(B76,'セッション実施状況管理'!$A:$U,20,false) -> 長尾あみり | H76: ='コーチング報酬管理'!G64 -> 6 | I76: =iferror(vlookup(B76,'セッション実施状況管理'!$A:$B,2,false),"") -> 卒業 | J76: 0 | K76: 0 | L76: =VLOOKUP(B76,'新 月次投稿数'!$A:$N,13,false) -> 78 | M76: =IF(L76>=100, 4, IF(L76>=81, 3, IF(L76>=56, 2, IF(L76>=31, 1, 0)))) -> 2 | N76: =IF(Q76>=540, 4, IF(Q76>=480, 3, IF(Q76>=420, 2, IF(Q76>=360, 1, IF(Q76>=300, 0, IF(Q76>=240, -1, -2)))))) -> 3 | O76: =IF(P76>=540, 4, IF(P76>=480, 3, IF(P76>=420, 2, IF(P76>=360, 1, IF(P76>=300, 0, IF(P76>=240, -1, -2)))))) -> 4 | P76: =sum(T76:Z76) -> 577 | Q76: =R76*6 -> 494.57143 | R76: =iferror(P76/S76,"0") -> 82.428571 | S76: =count(T76:Z76) -> 7 | T76: 28 | U76: 95 | V76: 102 | W76: 99 | X76: 91 | Y76: 83 | Z76: 79 | AA76: =Vlookup(B76,'セッション実施状況管理'!$A:$R,17,false) | AB76: =(YEAR(TODAY()) - YEAR($AA76)) * 12 + (MONTH(TODAY()) - MONTH($AA76)) -> 1514 | AC76: =IF( OR(AB76=3, AB76=4, AB76=5, AB76=6), "1", "2" ) -> 2
A77: 120投稿生 | B77: 59 | C77: =vlookup(B77,'セッション実施状況管理'!$A:$U,8,false) -> ふかくさゆか | D77: =vlookup(B77,'セッション実施状況管理'!$A:$I,9,false) -> hana_diet.recipe | E77: https://docs.google.com/spreadsheets/d/16pp5KhXzsROfzGIbbHxyalPddNj4-Jid11lhfpWal6c/edit?usp=sharing | F77: =vlookup(B77,'セッション実施状況管理'!$A:$U,20,false) -> 須見浩人 | G77: =vlookup(B77,'セッション実施状況管理'!$A:$U,20,false) -> 須見浩人 | H77: ='コーチング報酬管理'!G65 -> 3 | I77: =iferror(vlookup(B77,'セッション実施状況管理'!$A:$B,2,false),"") -> 卒業 | J77: 0 | K77: 0 | L77: =VLOOKUP(B77,'新 月次投稿数'!$A:$N,13,false) -> 120 | M77: =IF(L77>=100, 4, IF(L77>=81, 3, IF(L77>=56, 2, IF(L77>=31, 1, 0)))) -> 4 | N77: =IF(Q77>=540, 4, IF(Q77>=480, 3, IF(Q77>=420, 2, IF(Q77>=360, 1, IF(Q77>=300, 0, IF(Q77>=240, -1, -2)))))) -> 2 | O77: =IF(P77>=540, 4, IF(P77>=480, 3, IF(P77>=420, 2, IF(P77>=360, 1, IF(P77>=300, 0, IF(P77>=240, -1, -2)))))) -> 4 | P77: =sum(T77:Z77) -> 543 | Q77: =R77*6 -> 465.42857 | R77: =iferror(P77/S77,"0") -> 77.571429 | S77: =count(T77:Z77) -> 7 | T77: 32 | U77: 124 | V77: 93 | W77: 91 | X77: 97 | Y77: 71 | Z77: 35 | AA77: =Vlookup(B77,'セッション実施状況管理'!$A:$R,17,false) | AB77: =(YEAR(TODAY()) - YEAR($AA77)) * 12 + (MONTH(TODAY()) - MONTH($AA77)) -> 1514 | AC77: =IF( OR(AB77=3, AB77=4, AB77=5, AB77=6), "1", "2" ) -> 2
A78: 120投稿生 | B78: 60 | C78: =vlookup(B78,'セッション実施状況管理'!$A:$U,8,false) -> ごとうしんじ | D78: =vlookup(B78,'セッション実施状況管理'!$A:$I,9,false) -> justin_inuformation | E78: https://docs.google.com/spreadsheets/d/1511S8N3fqodY6J8oF9aP1IkcXR0YaUyyn9nmSFNRpEk/edit?gid=997181537#gid=997181537 | F78: =vlookup(B78,'セッション実施状況管理'!$A:$U,20,false) -> 森本風花 | G78: =vlookup(B78,'セッション実施状況管理'!$A:$U,20,false) -> 森本風花 | H78: ='コーチング報酬管理'!G66 -> 6 | I78: =iferror(vlookup(B78,'セッション実施状況管理'!$A:$B,2,false),"") -> 卒業 | J78: 0 | K78: 0 | L78: =VLOOKUP(B78,'新 月次投稿数'!$A:$N,13,false) -> 124 | M78: =IF(L78>=100, 4, IF(L78>=81, 3, IF(L78>=56, 2, IF(L78>=31, 1, 0)))) -> 4 | N78: =IF(Q78>=540, 4, IF(Q78>=480, 3, IF(Q78>=420, 2, IF(Q78>=360, 1, IF(Q78>=300, 0, IF(Q78>=240, -1, -2)))))) -> 1 | O78: =IF(P78>=540, 4, IF(P78>=480, 3, IF(P78>=420, 2, IF(P78>=360, 1, IF(P78>=300, 0, IF(P78>=240, -1, -2)))))) -> 2 | P78: =sum(T78:Z78) -> 425 | Q78: =R78*6 -> 364.28571 | R78: =iferror(P78/S78,"0") -> 60.714286 | S78: =count(T78:Z78) -> 7 | T78: 0 | U78: 92 | V78: 90 | W78: 82 | X78: 64 | Y78: 50 | Z78: 47 | AA78: =Vlookup(B78,'セッション実施状況管理'!$A:$R,17,false) | AB78: =(YEAR(TODAY()) - YEAR($AA78)) * 12 + (MONTH(TODAY()) - MONTH($AA78)) -> 1514 | AC78: =IF( OR(AB78=3, AB78=4, AB78=5, AB78=6), "1", "2" ) -> 2
A79: 120投稿生 | B79: 61 | C79: =vlookup(B79,'セッション実施状況管理'!$A:$U,8,false) -> こまつゆか | D79: =vlookup(B79,'セッション実施状況管理'!$A:$I,9,false) -> yukappe_room | E79: https://docs.google.com/spreadsheets/d/1ORWoMTpGoYtyRNrgKC_IbOipx9RJuxITdAaNAgLa_aU/edit?gid=1837929075#gid=1837929075 | F79: =vlookup(B79,'セッション実施状況管理'!$A:$U,20,false) -> 森本風花 | G79: =vlookup(B79,'セッション実施状況管理'!$A:$U,20,false) -> 森本風花 | H79: ='コーチング報酬管理'!G67 -> 5 | I79: =iferror(vlookup(B79,'セッション実施状況管理'!$A:$B,2,false),"") -> 卒業 | J79: 0 | K79: 0 | L79: =VLOOKUP(B79,'新 月次投稿数'!$A:$N,13,false) -> 25 | M79: =IF(L79>=100, 4, IF(L79>=81, 3, IF(L79>=56, 2, IF(L79>=31, 1, 0)))) -> 0 | N79: =IF(Q79>=540, 4, IF(Q79>=480, 3, IF(Q79>=420, 2, IF(Q79>=360, 1, IF(Q79>=300, 0, IF(Q79>=240, -1, -2)))))) -> 2 | O79: =IF(P79>=540, 4, IF(P79>=480, 3, IF(P79>=420, 2, IF(P79>=360, 1, IF(P79>=300, 0, IF(P79>=240, -1, -2)))))) -> 3 | P79: =sum(T79:Z79) -> 496 | Q79: =R79*6 -> 425.14286 | R79: =iferror(P79/S79,"0") -> 70.857143 | S79: =count(T79:Z79) -> 7 | T79: 12 | U79: 100 | V79: 87 | W79: 109 | X79: 74 | Y79: 83 | Z79: 31 | AA79: =Vlookup(B79,'セッション実施状況管理'!$A:$R,17,false) | AB79: =(YEAR(TODAY()) - YEAR($AA79)) * 12 + (MONTH(TODAY()) - MONTH($AA79)) -> 1514 | AC79: =IF( OR(AB79=3, AB79=4, AB79=5, AB79=6), "1", "2" ) -> 2
A80: 120投稿生 | B80: 62 | C80: =vlookup(B80,'セッション実施状況管理'!$A:$U,8,false) -> すがの ゆうた | D80: =vlookup(B80,'セッション実施状況管理'!$A:$I,9,false) -> kuroko_book | E80: https://docs.google.com/spreadsheets/d/1irC9yPxJZzB0yqE7yFX7FdVnyi7ZVeLtZE3wNhDGkxY/edit?gid=159884613#gid=159884613 | F80: =vlookup(B80,'セッション実施状況管理'!$A:$U,20,false) -> 森本風花 | G80: =vlookup(B80,'セッション実施状況管理'!$A:$U,20,false) -> 森本風花 | H80: ='コーチング報酬管理'!G68 -> 7 | I80: =iferror(vlookup(B80,'セッション実施状況管理'!$A:$B,2,false),"") -> 卒業 | J80: 0 | K80: 0 | L80: =VLOOKUP(B80,'新 月次投稿数'!$A:$N,13,false) -> 77 | M80: =IF(L80>=100, 4, IF(L80>=81, 3, IF(L80>=56, 2, IF(L80>=31, 1, 0)))) -> 2 | N80: =IF(Q80>=540, 4, IF(Q80>=480, 3, IF(Q80>=420, 2, IF(Q80>=360, 1, IF(Q80>=300, 0, IF(Q80>=240, -1, -2)))))) -> 0 | O80: =IF(P80>=540, 4, IF(P80>=480, 3, IF(P80>=420, 2, IF(P80>=360, 1, IF(P80>=300, 0, IF(P80>=240, -1, -2)))))) -> 1 | P80: =sum(T80:Z80) -> 410 | Q80: =R80*6 -> 351.42857 | R80: =iferror(P80/S80,"0") -> 58.571429 | S80: =count(T80:Z80) -> 7 | T80: 20 | U80: 102 | V80: 102 | W80: 79 | X80: 68 | Y80: 38 | Z80: 1 | AA80: =Vlookup(B80,'セッション実施状況管理'!$A:$R,17,false) | AB80: =(YEAR(TODAY()) - YEAR($AA80)) * 12 + (MONTH(TODAY()) - MONTH($AA80)) -> 1514 | AC80: =IF( OR(AB80=3, AB80=4, AB80=5, AB80=6), "1", "2" ) -> 2
A81: 120投稿生 | B81: 63 | C81: =vlookup(B81,'セッション実施状況管理'!$A:$U,8,false) -> おかひろし | D81: =vlookup(B81,'セッション実施状況管理'!$A:$I,9,false) -> passion_okatyan | E81: https://docs.google.com/spreadsheets/d/1kYFdRSfcFeUWy53n_3sJwY5qDhhG6cQ81POhWsPWNnw/edit?gid=1837929075#gid=1837929075 | F81: =vlookup(B81,'セッション実施状況管理'!$A:$U,20,false) -> 森本風花 | G81: =vlookup(B81,'セッション実施状況管理'!$A:$U,20,false) -> 森本風花 | H81: ='コーチング報酬管理'!G69 -> 6 | I81: =iferror(vlookup(B81,'セッション実施状況管理'!$A:$B,2,false),"") -> 音不 | J81: 0 | K81: 0 | L81: =VLOOKUP(B81,'新 月次投稿数'!$A:$N,13,false) -> 11 | M81: =IF(L81>=100, 4, IF(L81>=81, 3, IF(L81>=56, 2, IF(L81>=31, 1, 0)))) -> 0 | N81: =IF(Q81>=540, 4, IF(Q81>=480, 3, IF(Q81>=420, 2, IF(Q81>=360, 1, IF(Q81>=300, 0, IF(Q81>=240, -1, -2)))))) -> 3 | O81: =IF(P81>=540, 4, IF(P81>=480, 3, IF(P81>=420, 2, IF(P81>=360, 1, IF(P81>=300, 0, IF(P81>=240, -1, -2)))))) -> 2 | P81: =sum(T81:Z81) -> 425 | Q81: =R81*6 -> 510 | R81: =iferror(P81/S81,"0") -> 85 | S81: =count(T81:Z81) -> 5 | T81: 48 | U81: 230 | V81: 94 | W81: 40 | X81: 13 | Y81: ー | Z81: ー | AA81: =Vlookup(B81,'セッション実施状況管理'!$A:$R,17,false) | AB81: =(YEAR(TODAY()) - YEAR($AA81)) * 12 + (MONTH(TODAY()) - MONTH($AA81)) -> 1514 | AC81: =IF( OR(AB81=3, AB81=4, AB81=5, AB81=6), "1", "2" ) -> 2
A82: 120投稿生 | B82: 64 | C82: =vlookup(B82,'セッション実施状況管理'!$A:$U,8,false) -> てらもとまさゆき | D82: tera.security | E82: https://docs.google.com/spreadsheets/d/1SJcOeaE_21BchVEZMUF0uGMXfwGoFX6TcGOr4RiV73s/edit?gid=0#gid=0 | F82: =vlookup(B82,'セッション実施状況管理'!$A:$U,20,false) -> 山見阪佳子 | G82: =vlookup(B82,'セッション実施状況管理'!$A:$U,20,false) -> 山見阪佳子 | H82: ='コーチング報酬管理'!G70 -> 6 | I82: =iferror(vlookup(B82,'セッション実施状況管理'!$A:$B,2,false),"") -> 卒業 | J82: 1 | K82: 2 | L82: =VLOOKUP(B82,'新 月次投稿数'!$A:$N,13,false) -> 40 | M82: =IF(L82>=100, 4, IF(L82>=81, 3, IF(L82>=56, 2, IF(L82>=31, 1, 0)))) -> 1 | N82: =IF(Q82>=540, 4, IF(Q82>=480, 3, IF(Q82>=420, 2, IF(Q82>=360, 1, IF(Q82>=300, 0, IF(Q82>=240, -1, -2)))))) -> 4 | O82: =IF(P82>=540, 4, IF(P82>=480, 3, IF(P82>=420, 2, IF(P82>=360, 1, IF(P82>=300, 0, IF(P82>=240, -1, -2)))))) -> 4 | P82: =sum(T82:Z82) -> 1066 | Q82: =R82*6 -> 913.71429 | R82: =iferror(P82/S82,"0") -> 152.28571 | S82: =count(T82:Z82) -> 7 | T82: 74 | U82: 123 | V82: 157 | W82: 186 | X82: 180 | Y82: 162 | Z82: 184 | AA82: =Vlookup(B82,'セッション実施状況管理'!$A:$R,17,false) | AB82: =(YEAR(TODAY()) - YEAR($AA82)) * 12 + (MONTH(TODAY()) - MONTH($AA82)) -> 1514 | AC82: =IF( OR(AB82=3, AB82=4, AB82=5, AB82=6), "1", "2" ) -> 2
A83: 120投稿生 | B83: 65 | C83: =vlookup(B83,'セッション実施状況管理'!$A:$U,8,false) -> いけうちさや | D83: =vlookup(B83,'セッション実施状況管理'!$A:$I,9,false) -> pan_chan0380 | E83: https://docs.google.com/spreadsheets/d/1kDua-zpg-zmrarr4gGZ0aG-wCpNlxzvCQNKR4VD95V0/edit | F83: =vlookup(B83,'セッション実施状況管理'!$A:$U,20,false) -> 正木千智 | G83: =vlookup(B83,'セッション実施状況管理'!$A:$U,20,false) -> 正木千智 | H83: ='コーチング報酬管理'!G71 -> 5 | I83: =iferror(vlookup(B83,'セッション実施状況管理'!$A:$B,2,false),"") -> 卒業 | J83: 0 | K83: 0 | L83: =VLOOKUP(B83,'新 月次投稿数'!$A:$N,13,false) -> 28 | M83: =IF(L83>=100, 4, IF(L83>=81, 3, IF(L83>=56, 2, IF(L83>=31, 1, 0)))) -> 0 | N83: =IF(Q83>=540, 4, IF(Q83>=480, 3, IF(Q83>=420, 2, IF(Q83>=360, 1, IF(Q83>=300, 0, IF(Q83>=240, -1, -2)))))) -> -2 | O83: =IF(P83>=540, 4, IF(P83>=480, 3, IF(P83>=420, 2, IF(P83>=360, 1, IF(P83>=300, 0, IF(P83>=240, -1, -2)))))) -> -2 | P83: =sum(T83:Z83) -> 147 | Q83: =R83*6 -> 126 | R83: =iferror(P83/S83,"0") -> 21 | S83: =count(T83:Z83) -> 7 | T83: 21 | U83: 76 | V83: 48 | W83: 2 | X83: 0 | Y83: 0 | Z83: 0 | AA83: =Vlookup(B83,'セッション実施状況管理'!$A:$R,17,false) | AB83: =(YEAR(TODAY()) - YEAR($AA83)) * 12 + (MONTH(TODAY()) - MONTH($AA83)) -> 1514 | AC83: =IF( OR(AB83=3, AB83=4, AB83=5, AB83=6), "1", "2" ) -> 2
A84: 120投稿生 | B84: 66 | C84: =vlookup(B84,'セッション実施状況管理'!$A:$U,8,false) -> しまむらまりな | D84: =vlookup(B84,'セッション実施状況管理'!$A:$I,9,false) -> english_no_maria | E84: https://docs.google.com/spreadsheets/d/1nCnPVnaJvB7QrlrTko_HQ9FQvle8R90qA-M-PT74Kbo/edit?gid=997181537#gid=997181537 | F84: =vlookup(B84,'セッション実施状況管理'!$A:$U,20,false) -> 鈴木久美子 | G84: =vlookup(B84,'セッション実施状況管理'!$A:$U,20,false) -> 鈴木久美子 | H84: ='コーチング報酬管理'!G72 -> 6 | I84: =iferror(vlookup(B84,'セッション実施状況管理'!$A:$B,2,false),"") -> 卒業 | J84: 0 | K84: 0 | L84: =VLOOKUP(B84,'新 月次投稿数'!$A:$N,13,false) -> 2 | M84: =IF(L84>=100, 4, IF(L84>=81, 3, IF(L84>=56, 2, IF(L84>=31, 1, 0)))) -> 0 | N84: =IF(Q84>=540, 4, IF(Q84>=480, 3, IF(Q84>=420, 2, IF(Q84>=360, 1, IF(Q84>=300, 0, IF(Q84>=240, -1, -2)))))) -> -2 | O84: =IF(P84>=540, 4, IF(P84>=480, 3, IF(P84>=420, 2, IF(P84>=360, 1, IF(P84>=300, 0, IF(P84>=240, -1, -2)))))) -> -2 | P84: =sum(T84:Z84) -> 36 | Q84: =R84*6 -> 36 | R84: =iferror(P84/S84,"0") -> 6 | S84: =count(T84:Z84) -> 6 | T84: 9 | U84: 8 | V84: 0 | W84: 0 | X84: ４ | Y84: 19 | Z84: 0 | AA84: =Vlookup(B84,'セッション実施状況管理'!$A:$R,17,false) | AB84: =(YEAR(TODAY()) - YEAR($AA84)) * 12 + (MONTH(TODAY()) - MONTH($AA84)) -> 1514 | AC84: =IF( OR(AB84=3, AB84=4, AB84=5, AB84=6), "1", "2" ) -> 2
A85: 120投稿生 | B85: 67 | C85: =vlookup(B85,'セッション実施状況管理'!$A:$U,8,false) -> いしいるりな | D85: =vlookup(B85,'セッション実施状況管理'!$A:$I,9,false) -> amopi_asd | E85: https://docs.google.com/spreadsheets/d/1GuHkUl7tAhrpuhUak8u5QSGppPV0Q_T4z-fdMslErk0/edit?gid=1837929075#gid=1837929075 | F85: =vlookup(B85,'セッション実施状況管理'!$A:$U,20,false) -> 有山友菜 | G85: =vlookup(B85,'セッション実施状況管理'!$A:$U,20,false) -> 有山友菜 | H85: ='コーチング報酬管理'!G73 -> 4 | I85: =iferror(vlookup(B85,'セッション実施状況管理'!$A:$B,2,false),"") -> 卒業 | J85: 0 | K85: 0 | L85: =VLOOKUP(B85,'新 月次投稿数'!$A:$N,13,false) -> 37 | M85: =IF(L85>=100, 4, IF(L85>=81, 3, IF(L85>=56, 2, IF(L85>=31, 1, 0)))) -> 1 | N85: =IF(Q85>=540, 4, IF(Q85>=480, 3, IF(Q85>=420, 2, IF(Q85>=360, 1, IF(Q85>=300, 0, IF(Q85>=240, -1, -2)))))) -> 3 | O85: =IF(P85>=540, 4, IF(P85>=480, 3, IF(P85>=420, 2, IF(P85>=360, 1, IF(P85>=300, 0, IF(P85>=240, -1, -2)))))) -> 4 | P85: =sum(T85:Z85) -> 564 | Q85: =R85*6 -> 483.42857 | R85: =iferror(P85/S85,"0") -> 80.571429 | S85: =count(T85:Z85) -> 7 | T85: 46 | U85: 111 | V85: 87 | W85: 83 | X85: 87 | Y85: 85 | Z85: 65 | AA85: =Vlookup(B85,'セッション実施状況管理'!$A:$R,17,false) | AB85: =(YEAR(TODAY()) - YEAR($AA85)) * 12 + (MONTH(TODAY()) - MONTH($AA85)) -> 1514 | AC85: =IF( OR(AB85=3, AB85=4, AB85=5, AB85=6), "1", "2" ) -> 2
A86: 120投稿生 | B86: 68 | C86: =vlookup(B86,'セッション実施状況管理'!$A:$U,8,false) -> かわさきちあき | D86: =vlookup(B86,'セッション実施状況管理'!$A:$I,9,false) -> chi.wankogohan | E86: https://docs.google.com/spreadsheets/d/1nXaLCe8qHk3XZhV0LtdzyKLnnoTYbDQhii7kMl3ebuY/edit?usp=sharing | F86: =vlookup(B86,'セッション実施状況管理'!$A:$U,20,false) -> 小針彩乃 | G86: =vlookup(B86,'セッション実施状況管理'!$A:$U,20,false) -> 小針彩乃 | H86: ='コーチング報酬管理'!G74 -> 0 | I86: =iferror(vlookup(B86,'セッション実施状況管理'!$A:$B,2,false),"") -> 卒業 | J86: 0 | K86: 0 | L86: =VLOOKUP(B86,'新 月次投稿数'!$A:$N,13,false) -> 9 | M86: =IF(L86>=100, 4, IF(L86>=81, 3, IF(L86>=56, 2, IF(L86>=31, 1, 0)))) -> 0 | N86: =IF(Q86>=540, 4, IF(Q86>=480, 3, IF(Q86>=420, 2, IF(Q86>=360, 1, IF(Q86>=300, 0, IF(Q86>=240, -1, -2)))))) -> -1 | O86: =IF(P86>=540, 4, IF(P86>=480, 3, IF(P86>=420, 2, IF(P86>=360, 1, IF(P86>=300, 0, IF(P86>=240, -1, -2)))))) -> 0 | P86: =sum(T86:Z86) -> 343 | Q86: =R86*6 -> 294 | R86: =iferror(P86/S86,"0") -> 49 | S86: =count(T86:Z86) -> 7 | T86: 40 | U86: 79 | V86: 78 | W86: 68 | X86: 42 | Y86: 30 | Z86: 6 | AA86: =Vlookup(B86,'セッション実施状況管理'!$A:$R,17,false) | AB86: =(YEAR(TODAY()) - YEAR($AA86)) * 12 + (MONTH(TODAY()) - MONTH($AA86)) -> 1514 | AC86: =IF( OR(AB86=3, AB86=4, AB86=5, AB86=6), "1", "2" ) -> 2
A87: 120投稿生 | B87: 69 | C87: =vlookup(B87,'セッション実施状況管理'!$A:$U,8,false) -> くろだまさあき | D87: =vlookup(B87,'セッション実施状況管理'!$A:$I,9,false) | E87: https://docs.google.com/spreadsheets/d/15cZeFocUbkMJxLRe_P2TxphXcj4IIPIoBJEGg3nPV0o/edit?usp=sharing | F87: =vlookup(B87,'セッション実施状況管理'!$A:$U,20,false) -> 野村佑佳 | G87: =vlookup(B87,'セッション実施状況管理'!$A:$U,20,false) -> 野村佑佳 | H87: ='コーチング報酬管理'!G75 -> 4 | I87: =iferror(vlookup(B87,'セッション実施状況管理'!$A:$B,2,false),"") -> 音不 | L87: =VLOOKUP(B87,'新 月次投稿数'!$A:$N,13,false) -> 0 | M87: =IF(L87>=100, 4, IF(L87>=81, 3, IF(L87>=56, 2, IF(L87>=31, 1, 0)))) -> 0 | N87: =IF(Q87>=540, 4, IF(Q87>=480, 3, IF(Q87>=420, 2, IF(Q87>=360, 1, IF(Q87>=300, 0, IF(Q87>=240, -1, -2)))))) -> -2 | O87: =IF(P87>=540, 4, IF(P87>=480, 3, IF(P87>=420, 2, IF(P87>=360, 1, IF(P87>=300, 0, IF(P87>=240, -1, -2)))))) -> -2 | P87: =sum(T87:Z87) -> 19 | Q87: =R87*6 -> 38 | R87: =iferror(P87/S87,"0") -> 6.3333333 | S87: =count(T87:Z87) -> 3 | T87: 19 | U87: 0 | V87: 0 | W87: ー | X87: ー | Y87: ー | Z87: ー | AA87: =Vlookup(B87,'セッション実施状況管理'!$A:$R,17,false) | AB87: =(YEAR(TODAY()) - YEAR($AA87)) * 12 + (MONTH(TODAY()) - MONTH($AA87)) -> 1514 | AC87: =IF( OR(AB87=3, AB87=4, AB87=5, AB87=6), "1", "2" ) -> 2
A88: 120投稿生 | B88: 70 | C88: =vlookup(B88,'セッション実施状況管理'!$A:$U,8,false) -> きべまき | D88: tumako_yuru_yakuzen | E88: https://docs.google.com/spreadsheets/d/1VPxy8N0wUV7l7xGB4mUhS7_HnqwwTDUYw_gZC1TgYvs/edit?usp=sharing | F88: =vlookup(B88,'セッション実施状況管理'!$A:$U,20,false) -> 久保山菜々恵 | G88: =vlookup(B88,'セッション実施状況管理'!$A:$U,20,false) -> 久保山菜々恵 | H88: ='コーチング報酬管理'!G76 -> 4 | I88: =iferror(vlookup(B88,'セッション実施状況管理'!$A:$B,2,false),"") -> 卒業 | J88: 0 | K88: 0 | L88: =VLOOKUP(B88,'新 月次投稿数'!$A:$N,13,false) -> 32 | M88: =IF(L88>=100, 4, IF(L88>=81, 3, IF(L88>=56, 2, IF(L88>=31, 1, 0)))) -> 1 | N88: =IF(Q88>=540, 4, IF(Q88>=480, 3, IF(Q88>=420, 2, IF(Q88>=360, 1, IF(Q88>=300, 0, IF(Q88>=240, -1, -2)))))) -> 4 | O88: =IF(P88>=540, 4, IF(P88>=480, 3, IF(P88>=420, 2, IF(P88>=360, 1, IF(P88>=300, 0, IF(P88>=240, -1, -2)))))) -> 4 | P88: =sum(T88:Z88) -> 641 | Q88: =R88*6 -> 549.42857 | R88: =iferror(P88/S88,"0") -> 91.571429 | S88: =count(T88:Z88) -> 7 | T88: 146 | U88: 115 | V88: 97 | W88: 101 | X88: 80 | Y88: 93 | Z88: 9 | AA88: =Vlookup(B88,'セッション実施状況管理'!$A:$R,17,false) | AB88: =(YEAR(TODAY()) - YEAR($AA88)) * 12 + (MONTH(TODAY()) - MONTH($AA88)) -> 1514 | AC88: =IF( OR(AB88=3, AB88=4, AB88=5, AB88=6), "1", "2" ) -> 2
A89: 120投稿生 | B89: 71 | C89: =vlookup(B89,'セッション実施状況管理'!$A:$U,8,false) -> きくちことの | D89: =vlookup(B89,'セッション実施状況管理'!$A:$I,9,false) -> pino.couple.dirt | E89: https://docs.google.com/spreadsheets/d/1Aj3fjxUX54cR1jlXRO0GAMuv_GFQGcrLy7WGZYfJ7xs/edit?usp=sharing | F89: =vlookup(B89,'セッション実施状況管理'!$A:$U,20,false) -> 須見浩人 | G89: =vlookup(B89,'セッション実施状況管理'!$A:$U,20,false) -> 須見浩人 | H89: ='コーチング報酬管理'!G77 -> 4 | I89: =iferror(vlookup(B89,'セッション実施状況管理'!$A:$B,2,false),"") -> 卒業 | L89: =VLOOKUP(B89,'新 月次投稿数'!$A:$N,13,false) -> 33 | M89: =IF(L89>=100, 4, IF(L89>=81, 3, IF(L89>=56, 2, IF(L89>=31, 1, 0)))) -> 1 | N89: =IF(Q89>=540, 4, IF(Q89>=480, 3, IF(Q89>=420, 2, IF(Q89>=360, 1, IF(Q89>=300, 0, IF(Q89>=240, -1, -2)))))) -> 1 | O89: =IF(P89>=540, 4, IF(P89>=480, 3, IF(P89>=420, 2, IF(P89>=360, 1, IF(P89>=300, 0, IF(P89>=240, -1, -2)))))) -> 0 | P89: =sum(T89:Z89) -> 338 | Q89: =R89*6 -> 405.6 | R89: =iferror(P89/S89,"0") -> 67.6 | S89: =count(T89:Z89) -> 5 | T89: 24 | U89: 130 | V89: 60 | W89: 62 | X89: 62 | Y89: ー | Z89: ー | AA89: =Vlookup(B89,'セッション実施状況管理'!$A:$R,17,false) | AB89: =(YEAR(TODAY()) - YEAR($AA89)) * 12 + (MONTH(TODAY()) - MONTH($AA89)) -> 1514 | AC89: =IF( OR(AB89=3, AB89=4, AB89=5, AB89=6), "1", "2" ) -> 2
A90: 120投稿生 | B90: 72 | C90: =vlookup(B90,'セッション実施状況管理'!$A:$U,8,false) -> さえきもえか（かぶしきがいしゃりんくさぽーと） | D90: =vlookup(B90,'セッション実施状況管理'!$A:$I,9,false) -> myariku.suke | E90: https://docs.google.com/spreadsheets/d/1ajQNqK6co2_DE_epsNJiBOlXiJ2cF_19klutwRAm2As/edit?gid=1837929075#gid=1837929075 | F90: =vlookup(B90,'セッション実施状況管理'!$A:$U,20,false) -> 宮田友理 | G90: =vlookup(B90,'セッション実施状況管理'!$A:$U,20,false) -> 宮田友理 | H90: ='コーチング報酬管理'!G78 -> 2 | I90: =iferror(vlookup(B90,'セッション実施状況管理'!$A:$B,2,false),"") -> 休会 | L90: =VLOOKUP(B90,'新 月次投稿数'!$A:$N,13,false) -> 1 | M90: =IF(L90>=100, 4, IF(L90>=81, 3, IF(L90>=56, 2, IF(L90>=31, 1, 0)))) -> 0 | N90: =IF(Q90>=540, 4, IF(Q90>=480, 3, IF(Q90>=420, 2, IF(Q90>=360, 1, IF(Q90>=300, 0, IF(Q90>=240, -1, -2)))))) -> -2 | O90: =IF(P90>=540, 4, IF(P90>=480, 3, IF(P90>=420, 2, IF(P90>=360, 1, IF(P90>=300, 0, IF(P90>=240, -1, -2)))))) -> -2 | P90: =sum(T90:Z90) -> 173 | Q90: =R90*6 -> 207.6 | R90: =iferror(P90/S90,"0") -> 34.6 | S90: =count(T90:Z90) -> 5 | T90: 86 | U90: 8 | V90: 9 | W90: 70 | X90: 0 | Y90: ー | Z90: ー | AA90: =Vlookup(B90,'セッション実施状況管理'!$A:$R,17,false) | AB90: =(YEAR(TODAY()) - YEAR($AA90)) * 12 + (MONTH(TODAY()) - MONTH($AA90)) -> 1514 | AC90: =IF( OR(AB90=3, AB90=4, AB90=5, AB90=6), "1", "2" ) -> 2
A91: 120投稿生 | B91: 73 | C91: =vlookup(B91,'セッション実施状況管理'!$A:$U,8,false) -> いわぶちあゆか | D91: =vlookup(B91,'セッション実施状況管理'!$A:$I,9,false) | E91: https://docs.google.com/spreadsheets/d/1BTbQ19mUAUv0-Fo-BaQq4-E3pf1YdI5UnaZckC9DJLQ/edit?gid=1837929075#gid=1837929075 | F91: =vlookup(B91,'セッション実施状況管理'!$A:$U,20,false) -> 宮田友理 | G91: =vlookup(B91,'セッション実施状況管理'!$A:$U,20,false) -> 宮田友理 | H91: ='コーチング報酬管理'!G79 -> 4 | I91: =iferror(vlookup(B91,'セッション実施状況管理'!$A:$B,2,false),"") -> 音不 | L91: =VLOOKUP(B91,'新 月次投稿数'!$A:$N,13,false) -> 0 | M91: =IF(L91>=100, 4, IF(L91>=81, 3, IF(L91>=56, 2, IF(L91>=31, 1, 0)))) -> 0 | N91: =IF(Q91>=540, 4, IF(Q91>=480, 3, IF(Q91>=420, 2, IF(Q91>=360, 1, IF(Q91>=300, 0, IF(Q91>=240, -1, -2)))))) -> 3 | O91: =IF(P91>=540, 4, IF(P91>=480, 3, IF(P91>=420, 2, IF(P91>=360, 1, IF(P91>=300, 0, IF(P91>=240, -1, -2)))))) -> -2 | P91: =sum(T91:Z91) -> 86 | Q91: =R91*6 -> 516 | R91: =iferror(P91/S91,"0") -> 86 | S91: =count(T91:Z91) -> 1 | T91: 86 | U91: ー | V91: ー | W91: ー | X91: ー | Y91: ー | Z91: ー | AA91: =Vlookup(B91,'セッション実施状況管理'!$A:$R,17,false) | AB91: =(YEAR(TODAY()) - YEAR($AA91)) * 12 + (MONTH(TODAY()) - MONTH($AA91)) -> 1514 | AC91: =IF( OR(AB91=3, AB91=4, AB91=5, AB91=6), "1", "2" ) -> 2
A92: 120投稿生 | B92: 74 | C92: =vlookup(B92,'セッション実施状況管理'!$A:$U,8,false) -> かとうともか | D92: =vlookup(B92,'セッション実施状況管理'!$A:$I,9,false) -> sazae_ryoushiyome | E92: https://docs.google.com/spreadsheets/d/1Gud3dsIpMUFLHWKszQ6m8HEVt5JAQBvcNaz0EI0WC0s/edit?gid=1837929075#gid=1837929075 | F92: =vlookup(B92,'セッション実施状況管理'!$A:$U,20,false) -> 今立なつみ | G92: =vlookup(B92,'セッション実施状況管理'!$A:$U,20,false) -> 今立なつみ | H92: ='コーチング報酬管理'!G80 -> 3 | I92: =iferror(vlookup(B92,'セッション実施状況管理'!$A:$B,2,false),"") -> 卒業 | J92: 0 | K92: 0 | L92: =VLOOKUP(B92,'新 月次投稿数'!$A:$N,13,false) -> 48 | M92: =IF(L92>=100, 4, IF(L92>=81, 3, IF(L92>=56, 2, IF(L92>=31, 1, 0)))) -> 1 | N92: =IF(Q92>=540, 4, IF(Q92>=480, 3, IF(Q92>=420, 2, IF(Q92>=360, 1, IF(Q92>=300, 0, IF(Q92>=240, -1, -2)))))) -> 0 | O92: =IF(P92>=540, 4, IF(P92>=480, 3, IF(P92>=420, 2, IF(P92>=360, 1, IF(P92>=300, 0, IF(P92>=240, -1, -2)))))) -> 1 | P92: =sum(T92:Z92) -> 398 | Q92: =R92*6 -> 341.14286 | R92: =iferror(P92/S92,"0") -> 56.857143 | S92: =count(T92:Z92) -> 7 | T92: 117 | U92: 101 | V92: 66 | W92: 19 | X92: 43 | Y92: 31 | Z92: 21 | AA92: =Vlookup(B92,'セッション実施状況管理'!$A:$R,17,false) | AB92: =(YEAR(TODAY()) - YEAR($AA92)) * 12 + (MONTH(TODAY()) - MONTH($AA92)) -> 1514 | AC92: =IF( OR(AB92=3, AB92=4, AB92=5, AB92=6), "1", "2" ) -> 2
A93: 120投稿生 | B93: 75 | C93: =vlookup(B93,'セッション実施状況管理'!$A:$U,8,false) -> ひらやまみか | D93: =vlookup(B93,'セッション実施状況管理'!$A:$I,9,false) -> mimi_kaigo | E93: https://docs.google.com/spreadsheets/d/1QRcHeZffB8htE0XcLlh2tZj_4_zlTln52pLTr_Add6Q/edit?usp=sharing | F93: =vlookup(B93,'セッション実施状況管理'!$A:$U,20,false) -> 久保山菜々恵 | G93: =vlookup(B93,'セッション実施状況管理'!$A:$U,20,false) -> 久保山菜々恵 | H93: ='コーチング報酬管理'!G81 -> 3 | I93: =iferror(vlookup(B93,'セッション実施状況管理'!$A:$B,2,false),"") -> 卒業 | J93: 0 | K93: 0 | L93: =VLOOKUP(B93,'新 月次投稿数'!$A:$N,13,false) -> 0 | M93: =IF(L93>=100, 4, IF(L93>=81, 3, IF(L93>=56, 2, IF(L93>=31, 1, 0)))) -> 0 | N93: =IF(Q93>=540, 4, IF(Q93>=480, 3, IF(Q93>=420, 2, IF(Q93>=360, 1, IF(Q93>=300, 0, IF(Q93>=240, -1, -2)))))) -> -2 | O93: =IF(P93>=540, 4, IF(P93>=480, 3, IF(P93>=420, 2, IF(P93>=360, 1, IF(P93>=300, 0, IF(P93>=240, -1, -2)))))) -> -2 | P93: =sum(T93:Z93) -> 0 | Q93: =R93*6 -> 0 | R93: =iferror(P93/S93,"0") -> 0 | S93: =count(T93:Z93) -> 7 | T93: 0 | U93: 0 | V93: 0 | W93: 0 | X93: 0 | Y93: 0 | Z93: 0 | AA93: =Vlookup(B93,'セッション実施状況管理'!$A:$R,17,false) | AB93: =(YEAR(TODAY()) - YEAR($AA93)) * 12 + (MONTH(TODAY()) - MONTH($AA93)) -> 1514 | AC93: =IF( OR(AB93=3, AB93=4, AB93=5, AB93=6), "1", "2" ) -> 2
A94: 120投稿生 | B94: 76 | C94: =vlookup(B94,'セッション実施状況管理'!$A:$U,8,false) -> おおしろにいな | D94: =vlookup(B94,'セッション実施状況管理'!$A:$I,9,false) -> nina_diet_recipe | E94: https://docs.google.com/spreadsheets/d/1dFZq9pYe_tqUGCOTpPmtuJzc2xn8TVeSmyzXattJwfc/edit?usp=sharing | F94: =vlookup(B94,'セッション実施状況管理'!$A:$U,20,false) -> 久保山菜々恵 | G94: =vlookup(B94,'セッション実施状況管理'!$A:$U,20,false) -> 久保山菜々恵 | H94: ='コーチング報酬管理'!G82 -> 3 | I94: =iferror(vlookup(B94,'セッション実施状況管理'!$A:$B,2,false),"") -> 卒業 | J94: 0 | K94: 0 | L94: =VLOOKUP(B94,'新 月次投稿数'!$A:$N,13,false) -> 65 | M94: =IF(L94>=100, 4, IF(L94>=81, 3, IF(L94>=56, 2, IF(L94>=31, 1, 0)))) -> 2 | N94: =IF(Q94>=540, 4, IF(Q94>=480, 3, IF(Q94>=420, 2, IF(Q94>=360, 1, IF(Q94>=300, 0, IF(Q94>=240, -1, -2)))))) -> 1 | O94: =IF(P94>=540, 4, IF(P94>=480, 3, IF(P94>=420, 2, IF(P94>=360, 1, IF(P94>=300, 0, IF(P94>=240, -1, -2)))))) -> 2 | P94: =sum(T94:Z94) -> 471 | Q94: =R94*6 -> 403.71429 | R94: =iferror(P94/S94,"0") -> 67.285714 | S94: =count(T94:Z94) -> 7 | T94: 107 | U94: 76 | V94: 64 | W94: 63 | X94: 60 | Y94: 79 | Z94: 22 | AA94: =Vlookup(B94,'セッション実施状況管理'!$A:$R,17,false) | AB94: =(YEAR(TODAY()) - YEAR($AA94)) * 12 + (MONTH(TODAY()) - MONTH($AA94)) -> 1514 | AC94: =IF( OR(AB94=3, AB94=4, AB94=5, AB94=6), "1", "2" ) -> 2
A95: 120投稿生 | B95: 77 | C95: =vlookup(B95,'セッション実施状況管理'!$A:$U,8,false) -> ひろたはるな | D95: =vlookup(B95,'セッション実施状況管理'!$A:$I,9,false) -> hiiro_no_hibi | E95: https://docs.google.com/spreadsheets/d/13M_VFTWCvsiTL__bpxSEPQMvSf2MLfia2LCEvLDKdp0/edit?usp=sharing | F95: =vlookup(B95,'セッション実施状況管理'!$A:$U,20,false) -> 正木千智 | G95: =vlookup(B95,'セッション実施状況管理'!$A:$U,20,false) -> 正木千智 | H95: ='コーチング報酬管理'!G83 -> 2 | I95: =iferror(vlookup(B95,'セッション実施状況管理'!$A:$B,2,false),"") -> 卒業 | L95: =VLOOKUP(B95,'新 月次投稿数'!$A:$N,13,false) -> 1 | M95: =IF(L95>=100, 4, IF(L95>=81, 3, IF(L95>=56, 2, IF(L95>=31, 1, 0)))) -> 0 | N95: =IF(Q95>=540, 4, IF(Q95>=480, 3, IF(Q95>=420, 2, IF(Q95>=360, 1, IF(Q95>=300, 0, IF(Q95>=240, -1, -2)))))) -> -2 | O95: =IF(P95>=540, 4, IF(P95>=480, 3, IF(P95>=420, 2, IF(P95>=360, 1, IF(P95>=300, 0, IF(P95>=240, -1, -2)))))) -> -2 | P95: =sum(T95:Z95) -> 111 | Q95: =R95*6 -> 133.2 | R95: =iferror(P95/S95,"0") -> 22.2 | S95: =count(T95:Z95) -> 5 | T95: 0 | U95: 48 | V95: 55 | W95: 8 | X95: 0 | Y95: ー | Z95: ー | AA95: =Vlookup(B95,'セッション実施状況管理'!$A:$R,17,false) | AB95: =(YEAR(TODAY()) - YEAR($AA95)) * 12 + (MONTH(TODAY()) - MONTH($AA95)) -> 1514 | AC95: =IF( OR(AB95=3, AB95=4, AB95=5, AB95=6), "1", "2" ) -> 2
A96: 120投稿生 | B96: 78 | C96: =vlookup(B96,'セッション実施状況管理'!$A:$U,8,false) -> たかぎみさき | D96: =vlookup(B96,'セッション実施状況管理'!$A:$I,9,false) -> takami_15recipe | E96: https://docs.google.com/spreadsheets/d/1_AveVJPogQ7464fTUPxOIQSfFdNtmoCu_y7POBmcCFo/edit?gid=0#gid=0 | F96: =vlookup(B96,'セッション実施状況管理'!$A:$U,20,false) -> 山見阪佳子 | G96: =vlookup(B96,'セッション実施状況管理'!$A:$U,20,false) -> 山見阪佳子 | H96: ='コーチング報酬管理'!G84 -> 0 | I96: =iferror(vlookup(B96,'セッション実施状況管理'!$A:$B,2,false),"") -> 卒業 | L96: =VLOOKUP(B96,'新 月次投稿数'!$A:$N,13,false) -> 32 | M96: =IF(L96>=100, 4, IF(L96>=81, 3, IF(L96>=56, 2, IF(L96>=31, 1, 0)))) -> 1 | N96: =IF(Q96>=540, 4, IF(Q96>=480, 3, IF(Q96>=420, 2, IF(Q96>=360, 1, IF(Q96>=300, 0, IF(Q96>=240, -1, -2)))))) -> 1 | O96: =IF(P96>=540, 4, IF(P96>=480, 3, IF(P96>=420, 2, IF(P96>=360, 1, IF(P96>=300, 0, IF(P96>=240, -1, -2)))))) -> 2 | P96: =sum(T96:Z96) -> 464 | Q96: =R96*6 -> 397.71429 | R96: =iferror(P96/S96,"0") -> 66.285714 | S96: =count(T96:Z96) -> 7 | T96: 40 | U96: 68 | V96: 68 | W96: 82 | X96: 75 | Y96: 91 | Z96: 40 | AA96: =Vlookup(B96,'セッション実施状況管理'!$A:$R,17,false) | AB96: =(YEAR(TODAY()) - YEAR($AA96)) * 12 + (MONTH(TODAY()) - MONTH($AA96)) -> 1514 | AC96: =IF( OR(AB96=3, AB96=4, AB96=5, AB96=6), "1", "2" ) -> 2
A97: 120投稿生 | B97: 79 | C97: =vlookup(B97,'セッション実施状況管理'!$A:$U,8,false) -> しむらまなぶ | D97: =vlookup(B97,'セッション実施状況管理'!$A:$I,9,false) | E97: https://docs.google.com/spreadsheets/d/1zI9wlzNnpkuUqrq6mqYfsEwdDWAmHz4Dw9NQJ8VCynw/edit?usp=sharing | F97: =vlookup(B97,'セッション実施状況管理'!$A:$U,20,false) -> 須見浩人 | G97: =vlookup(B97,'セッション実施状況管理'!$A:$U,20,false) -> 須見浩人 | H97: ='コーチング報酬管理'!G85 -> 1 | I97: =iferror(vlookup(B97,'セッション実施状況管理'!$A:$B,2,false),"") -> 卒業 | L97: =VLOOKUP(B97,'新 月次投稿数'!$A:$N,13,false) -> 0 | M97: =IF(L97>=100, 4, IF(L97>=81, 3, IF(L97>=56, 2, IF(L97>=31, 1, 0)))) -> 0 | N97: =IF(Q97>=540, 4, IF(Q97>=480, 3, IF(Q97>=420, 2, IF(Q97>=360, 1, IF(Q97>=300, 0, IF(Q97>=240, -1, -2)))))) -> -2 | O97: =IF(P97>=540, 4, IF(P97>=480, 3, IF(P97>=420, 2, IF(P97>=360, 1, IF(P97>=300, 0, IF(P97>=240, -1, -2)))))) -> -2 | P97: =sum(T97:Z97) -> 12 | Q97: =R97*6 -> 18 | R97: =iferror(P97/S97,"0") -> 3 | S97: =count(T97:Z97) -> 4 | T97: ー | U97: 10 | V97: 0 | W97: 2 | X97: 0 | Y97: ー | Z97: ー | AA97: =Vlookup(B97,'セッション実施状況管理'!$A:$R,17,false) | AB97: =(YEAR(TODAY()) - YEAR($AA97)) * 12 + (MONTH(TODAY()) - MONTH($AA97)) -> 1514 | AC97: =IF( OR(AB97=3, AB97=4, AB97=5, AB97=6), "1", "2" ) -> 2
A98: 120投稿生 | B98: 80 | C98: =vlookup(B98,'セッション実施状況管理'!$A:$U,8,false) -> ふじおかみすず | D98: =vlookup(B98,'セッション実施状況管理'!$A:$I,9,false) -> mirin_room_ | E98: https://docs.google.com/spreadsheets/d/1uvMv3FvFwe5-ongIRzVeSDbW2UTnSZ0ZBqtmVA4wq9g/edit?usp=sharing | F98: =vlookup(B98,'セッション実施状況管理'!$A:$U,20,false) -> 野村佑佳 | G98: =vlookup(B98,'セッション実施状況管理'!$A:$U,20,false) -> 野村佑佳 | H98: ='コーチング報酬管理'!G86 -> 2 | I98: =iferror(vlookup(B98,'セッション実施状況管理'!$A:$B,2,false),"") -> 卒業 | L98: =VLOOKUP(B98,'新 月次投稿数'!$A:$N,13,false) -> 26 | M98: =IF(L98>=100, 4, IF(L98>=81, 3, IF(L98>=56, 2, IF(L98>=31, 1, 0)))) -> 0 | N98: =IF(Q98>=540, 4, IF(Q98>=480, 3, IF(Q98>=420, 2, IF(Q98>=360, 1, IF(Q98>=300, 0, IF(Q98>=240, -1, -2)))))) -> 3 | O98: =IF(P98>=540, 4, IF(P98>=480, 3, IF(P98>=420, 2, IF(P98>=360, 1, IF(P98>=300, 0, IF(P98>=240, -1, -2)))))) -> 4 | P98: =sum(T98:Z98) -> 588 | Q98: =R98*6 -> 504 | R98: =iferror(P98/S98,"0") -> 84 | S98: =count(T98:Z98) -> 7 | T98: 51 | U98: 105 | V98: 93 | W98: 94 | X98: 94 | Y98: 88 | Z98: 63 | AA98: =Vlookup(B98,'セッション実施状況管理'!$A:$R,17,false) | AB98: =(YEAR(TODAY()) - YEAR($AA98)) * 12 + (MONTH(TODAY()) - MONTH($AA98)) -> 1514 | AC98: =IF( OR(AB98=3, AB98=4, AB98=5, AB98=6), "1", "2" ) -> 2
A99: 120投稿生 | B99: 81 | C99: =vlookup(B99,'セッション実施状況管理'!$A:$U,8,false) -> やまぐちちづる | D99: =vlookup(B99,'セッション実施状況管理'!$A:$I,9,false) -> odoru_ryokoumama40 | E99: https://docs.google.com/spreadsheets/d/1OyQILO3SIpSbD74ppDh-W6iLKXyP7__Jqw5lh7dbaWU/edit?gid=0#gid=0 | F99: =vlookup(B99,'セッション実施状況管理'!$A:$U,20,false) -> 青木千奈 | G99: =vlookup(B99,'セッション実施状況管理'!$A:$U,20,false) -> 青木千奈 | H99: ='コーチング報酬管理'!G87 -> 1 | I99: =iferror(vlookup(B99,'セッション実施状況管理'!$A:$B,2,false),"") -> 卒業 | L99: =VLOOKUP(B99,'新 月次投稿数'!$A:$N,13,false) -> 26 | M99: =IF(L99>=100, 4, IF(L99>=81, 3, IF(L99>=56, 2, IF(L99>=31, 1, 0)))) -> 0 | N99: =IF(Q99>=540, 4, IF(Q99>=480, 3, IF(Q99>=420, 2, IF(Q99>=360, 1, IF(Q99>=300, 0, IF(Q99>=240, -1, -2)))))) -> 4 | O99: =IF(P99>=540, 4, IF(P99>=480, 3, IF(P99>=420, 2, IF(P99>=360, 1, IF(P99>=300, 0, IF(P99>=240, -1, -2)))))) -> 4 | P99: =sum(T99:Z99) -> 875 | Q99: =R99*6 -> 875 | R99: =iferror(P99/S99,"0") -> 145.83333 | S99: =count(T99:Z99) -> 6 | T99: 100 | U99: 99 | V99: 139 | W99: 155 | X99: 201 | Y99: 181 | Z99: ー | AA99: =Vlookup(B99,'セッション実施状況管理'!$A:$R,17,false) | AB99: =(YEAR(TODAY()) - YEAR($AA99)) * 12 + (MONTH(TODAY()) - MONTH($AA99)) -> 1514 | AC99: =IF( OR(AB99=3, AB99=4, AB99=5, AB99=6), "1", "2" ) -> 2
A100: 120投稿生 | B100: 83 | C100: =vlookup(B100,'セッション実施状況管理'!$A:$U,8,false) -> のぶとうまさこ | D100: =vlookup(B100,'セッション実施状況管理'!$A:$I,9,false) -> mskn.christmas | E100: {のぶとうまさこ}_アクション管理表 のコピー | F100: =vlookup(B100,'セッション実施状況管理'!$A:$U,20,false) -> 高木千鶴 | G100: =vlookup(B100,'セッション実施状況管理'!$A:$U,20,false) -> 高木千鶴 | H100: ='コーチング報酬管理'!G88 -> 1 | I100: =iferror(vlookup(B100,'セッション実施状況管理'!$A:$B,2,false),"") -> 卒業 | J100: 0 | K100: 0 | L100: =VLOOKUP(B100,'新 月次投稿数'!$A:$N,13,false) -> 36 | M100: =IF(L100>=100, 4, IF(L100>=81, 3, IF(L100>=56, 2, IF(L100>=31, 1, 0)))) -> 1 | N100: =IF(Q100>=540, 4, IF(Q100>=480, 3, IF(Q100>=420, 2, IF(Q100>=360, 1, IF(Q100>=300, 0, IF(Q100>=240, -1, -2)))))) -> 0 | O100: =IF(P100>=540, 4, IF(P100>=480, 3, IF(P100>=420, 2, IF(P100>=360, 1, IF(P100>=300, 0, IF(P100>=240, -1, -2)))))) -> 0 | P100: =sum(T100:Z100) -> 321 | Q100: =R100*6 -> 321 | R100: =iferror(P100/S100,"0") -> 53.5 | S100: =count(T100:Z100) -> 6 | T100: ー | U100: 81 | V100: 67 | W100: 70 | X100: 44 | Y100: 29 | Z100: 30 | AA100: =Vlookup(B100,'セッション実施状況管理'!$A:$R,17,false) | AB100: =(YEAR(TODAY()) - YEAR($AA100)) * 12 + (MONTH(TODAY()) - MONTH($AA100)) -> 1514 | AC100: =IF( OR(AB100=3, AB100=4, AB100=5, AB100=6), "1", "2" ) -> 2
A101: 120投稿生 | B101: 84 | C101: =vlookup(B101,'セッション実施状況管理'!$A:$U,8,false) -> かげやまこゆき | D101: =vlookup(B101,'セッション実施状況管理'!$A:$I,9,false) -> yukiko_sologram koyuki_viewmap | E101: https://docs.google.com/spreadsheets/d/1rV8ti4qi4LOLKhZFXxoia7mV3C9GXaCSLwLJ-8ETza8/edit?gid=997181537#gid=997181537 | F101: =vlookup(B101,'セッション実施状況管理'!$A:$U,20,false) -> 青木千奈 | G101: =vlookup(B101,'セッション実施状況管理'!$A:$U,20,false) -> 青木千奈 | H101: ='コーチング報酬管理'!G89 -> 2 | I101: =iferror(vlookup(B101,'セッション実施状況管理'!$A:$B,2,false),"") -> 卒業 | L101: =VLOOKUP(B101,'新 月次投稿数'!$A:$N,13,false) -> 47 | M101: =IF(L101>=100, 4, IF(L101>=81, 3, IF(L101>=56, 2, IF(L101>=31, 1, 0)))) -> 1 | N101: =IF(Q101>=540, 4, IF(Q101>=480, 3, IF(Q101>=420, 2, IF(Q101>=360, 1, IF(Q101>=300, 0, IF(Q101>=240, -1, -2)))))) -> 0 | O101: =IF(P101>=540, 4, IF(P101>=480, 3, IF(P101>=420, 2, IF(P101>=360, 1, IF(P101>=300, 0, IF(P101>=240, -1, -2)))))) -> 0 | P101: =sum(T101:Z101) -> 349 | Q101: =R101*6 -> 349 | R101: =iferror(P101/S101,"0") -> 58.166667 | S101: =count(T101:Z101) -> 6 | T101: 64 | U101: 68 | V101: 71 | W101: 61 | X101: 62 | Y101: 23 | Z101: ー | AA101: =Vlookup(B101,'セッション実施状況管理'!$A:$R,17,false) | AB101: =(YEAR(TODAY()) - YEAR($AA101)) * 12 + (MONTH(TODAY()) - MONTH($AA101)) -> 1514 | AC101: =IF( OR(AB101=3, AB101=4, AB101=5, AB101=6), "1", "2" ) -> 2
A102: 120投稿生 | B102: 85 | C102: =vlookup(B102,'セッション実施状況管理'!$A:$U,8,false) -> こうごたかひろ | D102: =vlookup(B102,'セッション実施状況管理'!$A:$I,9,false) -> piro_yaseuma | E102: https://docs.google.com/spreadsheets/d/1Az7KfWqjgAMVBOS5fLPQJBPFGeJgcwQGf1_mhc_s54A/edit?gid=1837929075#gid=1837929075 | F102: =vlookup(B102,'セッション実施状況管理'!$A:$U,20,false) -> 中富智弘 | G102: =vlookup(B102,'セッション実施状況管理'!$A:$U,20,false) -> 中富智弘 | H102: ='コーチング報酬管理'!G90 -> 2 | I102: =iferror(vlookup(B102,'セッション実施状況管理'!$A:$B,2,false),"") -> 卒業 | J102: 0 | K102: 0 | L102: =VLOOKUP(B102,'新 月次投稿数'!$A:$N,13,false) -> 12 | M102: =IF(L102>=100, 4, IF(L102>=81, 3, IF(L102>=56, 2, IF(L102>=31, 1, 0)))) -> 0 | N102: =IF(Q102>=540, 4, IF(Q102>=480, 3, IF(Q102>=420, 2, IF(Q102>=360, 1, IF(Q102>=300, 0, IF(Q102>=240, -1, -2)))))) -> 0 | O102: =IF(P102>=540, 4, IF(P102>=480, 3, IF(P102>=420, 2, IF(P102>=360, 1, IF(P102>=300, 0, IF(P102>=240, -1, -2)))))) -> 0 | P102: =sum(T102:Z102) -> 341 | Q102: =R102*6 -> 341 | R102: =iferror(P102/S102,"0") -> 56.833333 | S102: =count(T102:Z102) -> 6 | T102: 124 | U102: 121 | V102: 86 | W102: 10 | X102: 0 | Y102: 0 | Z102: ー | AA102: =Vlookup(B102,'セッション実施状況管理'!$A:$R,17,false) | AB102: =(YEAR(TODAY()) - YEAR($AA102)) * 12 + (MONTH(TODAY()) - MONTH($AA102)) -> 1514 | AC102: =IF( OR(AB102=3, AB102=4, AB102=5, AB102=6), "1", "2" ) -> 2
A103: 120投稿生 | B103: 86 | C103: =vlookup(B103,'セッション実施状況管理'!$A:$U,8,false) -> かきのきまゆみ | D103: =vlookup(B103,'セッション実施状況管理'!$A:$I,9,false) -> mimi_kojirecipe | E103: https://www.notion.so/F-216f3b0fba85805fbe7bc87967cbb17a?source=copy_link | F103: =vlookup(B103,'セッション実施状況管理'!$A:$U,20,false) -> 今立なつみ | G103: =vlookup(B103,'セッション実施状況管理'!$A:$U,20,false) -> 今立なつみ | H103: ='コーチング報酬管理'!G91 -> 2 | I103: =iferror(vlookup(B103,'セッション実施状況管理'!$A:$B,2,false),"") -> 卒業 | L103: =VLOOKUP(B103,'新 月次投稿数'!$A:$N,13,false) -> 1 | M103: =IF(L103>=100, 4, IF(L103>=81, 3, IF(L103>=56, 2, IF(L103>=31, 1, 0)))) -> 0 | N103: =IF(Q103>=540, 4, IF(Q103>=480, 3, IF(Q103>=420, 2, IF(Q103>=360, 1, IF(Q103>=300, 0, IF(Q103>=240, -1, -2)))))) -> -2 | O103: =IF(P103>=540, 4, IF(P103>=480, 3, IF(P103>=420, 2, IF(P103>=360, 1, IF(P103>=300, 0, IF(P103>=240, -1, -2)))))) -> -2 | P103: =sum(T103:Z103) -> 8 | Q103: =R103*6 -> 6.8571429 | R103: =iferror(P103/S103,"0") -> 1.1428571 | S103: =count(T103:Z103) -> 7 | T103: 1 | U103: 0 | V103: 7 | W103: 0 | X103: 0 | Y103: 0 | Z103: 0 | AA103: =Vlookup(B103,'セッション実施状況管理'!$A:$R,17,false) | AB103: =(YEAR(TODAY()) - YEAR($AA103)) * 12 + (MONTH(TODAY()) - MONTH($AA103)) -> 1514 | AC103: =IF( OR(AB103=3, AB103=4, AB103=5, AB103=6), "1", "2" ) -> 2
...

Sheet 新 月次投稿数
C2: 今後：コミットプランの成約件数を増やすことを風花の達成目標にすべき 「どんな人でも、」 生徒に提案しにくい →結果が出るもの、 コミットプランを提案する コミットプランに入れることが生徒のプラスになることが営業にアピールできない 駒居さんくらい自信の溢れている生徒がいたら、もっと制約数を伸ばせるはず 結果を出すために ・目標設定を数字でさせる ・数字を達成できないのであれば、数字を達成するための目標再設定 ・0.0の目標は、今のままやっていれば達成できる→100% ベースの投稿数（61投稿以上）→コミットプランが120投稿を目指すプランなのに、風花の目標値を61投稿で100%目標、としておいているのはいいのか？ 月平均12投稿 各生徒に、何投稿させて、全体の平均を何投稿にするのか 具体的なアクションプラン ・スケジュールの立て方を変える ・できなかった原因を突き止めて、来週どうしていくのかを話すことができるのであれば達成できる | M2: 120達成：赤文字 80以上：黄 120達成：赤文字 61以下：赤 61以上：青文字 目標投稿数 目標以下は赤セル | O2: 120メンバー目標達成率(60) | P2: =IF(P7=0, "", P4 / P7 * 100) -> #VALUE! | Q2: =IF(Q7=0, "", Q4 / Q7 * 100) -> 393.87755 | R2: =IF(R7=0, "", R4 / R7 * 100) -> 100.76923 | S2: =IF(S7=0, "", S4 / S7 * 100) -> 100.80808 | T2: =IF(T7=0, "", T4 / T7 * 100) -> 96.596244 | U2: =IF(U7=0, "", U4 / U7 * 100) -> 86.993007 | V2: =IF(V7=0, "", V4 / V7 * 100) -> 60.13289
O3: 120メンバー目標達成率(120) | P3: =IF(P9=0, "", P4 / P9 * 100) -> 27.45098 | Q3: =IF(Q9=0, "", Q4 / Q9 * 100) -> 393.87755 | R3: =IF(R9=0, "", R4 / R9 * 100) -> 50.384615 | S3: =IF(S9=0, "", S4 / S9 * 100) -> 52.804233 | T3: =IF(T9=0, "", T4 / T9 * 100) -> 46.366197 | U3: =IF(U9=0, "", U4 / U9 * 100) -> 41.885522 | V3: =IF(V9=0, "", V4 / V9 * 100) -> 31.180017
G4: ⭐️月末の数字 として出す | O4: 平均投稿数（120メンバーのみ） | P4: =IFERROR(__xludf.DUMMYFUNCTION("AVERAGE(FILTER(P56:P200, ISNUMBER(P56:P200))) "),0.27450980392156865) -> 0.2745098 | Q4: =IFERROR(__xludf.DUMMYFUNCTION("AVERAGE(FILTER(Q56:Q200, ISNUMBER(Q56:Q200))) "),3.938775510204082) -> 3.9387755 | R4: =IFERROR(__xludf.DUMMYFUNCTION("AVERAGE(FILTER(R56:R200, ISNUMBER(R56:R200))) "),10.076923076923077) -> 10.076923 | S4: =IFERROR(__xludf.DUMMYFUNCTION("AVERAGE(FILTER(S56:S200, ISNUMBER(S56:S200))) "),11.088888888888889) -> 11.088889 | T4: =IFERROR(__xludf.DUMMYFUNCTION("AVERAGE(FILTER(T56:T200, ISNUMBER(T56:T200))) "),11.591549295774648) -> 11.591549 | U4: =IFERROR(__xludf.DUMMYFUNCTION("AVERAGE(FILTER(U56:U200, ISNUMBER(U56:U200))) "),11.309090909090909) -> 11.309091 | V4: =IFERROR(__xludf.DUMMYFUNCTION("AVERAGE(FILTER(V56:V200, ISNUMBER(V56:V200))) "),8.418604651162791) -> 8.4186047
G5: SP開始日から、月末の投稿数を見て、傾向を見ることはできるから分析には使える | O5: 120-全体 差 | P5: - | Q5: =Q4-Q6 -> -1.1683673 | R5: =R4-R6 -> -0.19426336 | S5: =S4-S6 -> 0.53074935 | T5: =T4-T6 -> 0.8992416 | U5: =U4-U6 -> -0.69090909 | V5: =V4-V6 -> -2.5813953
O6: 平均投稿数（在学生全体） | P6: =IFERROR(__xludf.DUMMYFUNCTION("AVERAGE(FILTER(P39:P201, ($C39:$C$201=""在学中"") * (P39:P201<>"""")))"),0.5) -> 0.5 | Q6: =IFERROR(__xludf.DUMMYFUNCTION("AVERAGE(FILTER(Q39:Q201, ($C39:$C$201=""在学中"") * (Q39:Q201<>"""")))"),5.107142857142857) -> 5.1071429 | R6: =IFERROR(__xludf.DUMMYFUNCTION("AVERAGE(FILTER(R39:R201, ($C39:$C$201=""在学中"") * (R39:R201<>"""")))"),10.271186440677965) -> 10.271186 | S6: =IFERROR(__xludf.DUMMYFUNCTION("AVERAGE(FILTER(S39:S201, ($C39:$C$201=""在学中"") * (S39:S201<>"""")))"),10.55813953488372) -> 10.55814 | T6: =IFERROR(__xludf.DUMMYFUNCTION("AVERAGE(FILTER(T39:T201, ($C39:$C$201=""在学中"") * (T39:T201<>"""")))"),10.692307692307692) -> 10.692308 | U6: =IFERROR(__xludf.DUMMYFUNCTION("AVERAGE(FILTER(U39:U201, ($C39:$C$201=""在学中"") * (U39:U201<>"""")))"),12.0) -> 12 | V6: =IFERROR(__xludf.DUMMYFUNCTION("AVERAGE(FILTER(V39:V201, ($C39:$C$201=""在学中"") * (V39:V201<>"""")))"),11.0) -> 11
O7: 単月目標 | P7: F | Q7: 1 | R7: 10 | S7: 11 | T7: 12 | U7: 13 | V7: 14 | W7: =SUM(P7:V7) -> 61
O8: 累計 | P8: 0 | Q8: =(P9+Q9)-2 -> 0 | R8: =R9+Q8 -> 20 | S8: =S9+R8 -> 41 | T8: =T9+S8 -> 66 | U8: =U9+T8 -> 93 | V8: =V9+U8 -> 120
D9: ※アカウントみ作成：本人の名前 | M9: 61 | N9: 120 | O9: 単月目標（120） | P9: 1 | Q9: 1 | R9: 20 | S9: 21 | T9: 25 | U9: 27 | V9: 27 | W9: 120 | X9: 分析用
D10: 関数 | E10: 関数 | F10: 関数 | G10: 関数 | K10: 手動入力 | L10: 手動入力 | N10: 手動入力 | P10: ▼投稿が始まってない場合は「ー」投稿始まってから0投稿：0 | X10: 関数 | Y10: 手動入力 | Z10: 手動入力 | AA10: 手動入力
A11: no. | B11: 万垢達成 | C11: 在学 | D11: user ID | E11: 生徒名 | F11: 担当MG | H11: 入会 | I11: ƒ | J11: 目標達成率 | K11: 卒業時フォロワー数 | L11: 投稿開始時投稿数 | M11: 現在投稿数合計 | N11: 卒業時投稿数 | O11: 個人平均月間投稿数 | P11: 0ヶ月目 | Q11: 1ヶ月目 | R11: 2ヶ月目 | S11: 3ヶ月目 | T11: 4ヶ月目 | U11: 5ヶ月目 | V11: 6ヶ月目 | X11: 講師 | Y11: ジャンル | Z11: 年齢 | AA11: 家族構成
A12: 1 | B12: =vlookup(A12,'セッション実施状況管理'!$A:$C,3,false) -> 0 | C12: =vlookup(A12,'セッション実施状況管理'!$A:$B,2,false) -> 例外 | D12: =vlookup(A12,'セッション実施状況管理'!$A:$I,9,false) -> koji_no_chie | E12: =vlookup(A12,'セッション実施状況管理'!$A:$I,8,false) -> おのまこと | F12: =vlookup(A12,'セッション実施状況管理'!$A:$U,19,false) -> - | G12: =vlookup(A12,'セッション実施状況管理'!$A:$U,20,false) -> 宮田友理 | H12: =vlookup(A12,'セッション実施状況管理'!$A$4:$S1004,17,false) -> - | I12: =(YEAR(TODAY()) - YEAR($H12)) * 12 + (MONTH(TODAY()) - MONTH($H12)) -> #VALUE! | K12: 34 | L12: 0 | M12: =sum(P12:V12) -> 0 | N12: 0 | O12: =M12/counta(P12:V12) -> 0 | P12: ー | Q12: ー | R12: ー | S12: ー | T12: ー | U12: ー | V12: 0 | X12: =iferror(VLOOKUP($E12,'セッション実施状況管理'!$H$10:$L$1028,4,FALSE),"") -> 駒居
A13: 2 | B13: =vlookup(A13,'セッション実施状況管理'!$A:$C,3,false) -> 1 | C13: =vlookup(A13,'セッション実施状況管理'!$A:$B,2,false) -> 卒業 | D13: =vlookup(A13,'セッション実施状況管理'!$A:$I,9,false) -> cya_kurashi | E13: =vlookup(A13,'セッション実施状況管理'!$A:$I,8,false) -> ただゆうすけ | F13: =vlookup(A13,'セッション実施状況管理'!$A:$U,19,false) -> 45460 | G13: =iferror(vlookup(D13,'セッション実施状況管理'!$I:$U,12,false),"-") -> 中村恵理 | H13: =vlookup(A13,'セッション実施状況管理'!$A$4:$S1004,17,false) -> - | I13: =(YEAR(TODAY()) - YEAR($H13)) * 12 + (MONTH(TODAY()) - MONTH($H13)) -> #VALUE! | K13: 70000 | L13: 0 | M13: =sum(P13:V13) -> 89 | N13: 96 | O13: =M13/counta(P13:V13) -> 12.714286 | P13: ー | Q13: 1 | R13: 6 | S13: 27 | T13: 28 | U13: 19 | V13: 8 | X13: =iferror(VLOOKUP($E13,'セッション実施状況管理'!$H$10:$L$1028,4,FALSE),"") -> 駒居 | Y13: 不明 | Z13: 不明 | AA13: 不明
A14: 3 | B14: =vlookup(A14,'セッション実施状況管理'!$A:$C,3,false) -> 0 | C14: =vlookup(A14,'セッション実施状況管理'!$A:$B,2,false) -> 卒業 | D14: =vlookup(A14,'セッション実施状況管理'!$A:$I,9,false) -> ta_ma_diet | E14: =vlookup(A14,'セッション実施状況管理'!$A:$I,8,false) -> ふじたなな | F14: =vlookup(A14,'セッション実施状況管理'!$A:$U,19,false) -> 45455 | G14: =iferror(vlookup(D14,'セッション実施状況管理'!$I:$U,12,false),"-") -> 森本風花 | H14: =vlookup(A14,'セッション実施状況管理'!$A$4:$S1004,17,false) | I14: =(YEAR(TODAY()) - YEAR($H14)) * 12 + (MONTH(TODAY()) - MONTH($H14)) -> 1514 | K14: 0 | L14: 0 | M14: =sum(P14:V14) -> 0 | N14: 0 | O14: =M14/counta(P14:V14) -> 0 | P14: ー | Q14: ー | R14: ー | S14: ー | T14: ー | U14: ー | V14: 0 | X14: =iferror(VLOOKUP($E14,'セッション実施状況管理'!$H$10:$L$1028,4,FALSE),"") -> 駒居 | Y14: スポット紹介 | Z14: 20〜29 | AA14: 家族子供あり
A15: 4 | B15: =vlookup(A15,'セッション実施状況管理'!$A:$C,3,false) -> 0 | C15: =vlookup(A15,'セッション実施状況管理'!$A:$B,2,false) -> 卒業 | D15: =vlookup(A15,'セッション実施状況管理'!$A:$I,9,false) -> adhd_nao | E15: =vlookup(A15,'セッション実施状況管理'!$A:$I,8,false) -> よしだむつみ | F15: =vlookup(A15,'セッション実施状況管理'!$A:$U,19,false) -> 45466 | G15: =iferror(vlookup(D15,'セッション実施状況管理'!$I:$U,12,false),"-") -> 野村佑佳 | H15: =vlookup(A15,'セッション実施状況管理'!$A$4:$S1004,17,false) | I15: =(YEAR(TODAY()) - YEAR($H15)) * 12 + (MONTH(TODAY()) - MONTH($H15)) -> 1514 | K15: 0 | L15: 0 | M15: =sum(P15:V15) -> 0 | N15: 0 | O15: =M15/counta(P15:V15) -> 0 | P15: ー | Q15: ー | R15: ー | S15: ー | T15: ー | U15: ー | V15: 0 | X15: =iferror(VLOOKUP($E15,'セッション実施状況管理'!$H$10:$L$1028,4,FALSE),"") -> 駒居 | Y15: 暮らし/DIY | Z15: 40〜49 | AA15: DINKS
A16: 5 | B16: =vlookup(A16,'セッション実施状況管理'!$A:$C,3,false) -> 0 | C16: =vlookup(A16,'セッション実施状況管理'!$A:$B,2,false) -> 卒業 | D16: =vlookup(A16,'セッション実施状況管理'!$A:$I,9,false) -> kcc_0113 | E16: =vlookup(A16,'セッション実施状況管理'!$A:$I,8,false) -> きたがわたかひろ | F16: =vlookup(A16,'セッション実施状況管理'!$A:$U,19,false) -> 45130 | G16: =iferror(vlookup(D16,'セッション実施状況管理'!$I:$U,12,false),"-") -> 豊榮信江 | H16: =vlookup(A16,'セッション実施状況管理'!$A$4:$S1004,17,false) | I16: =(YEAR(TODAY()) - YEAR($H16)) * 12 + (MONTH(TODAY()) - MONTH($H16)) -> 1514 | K16: 12 | L16: 0 | M16: =sum(P16:V16) -> 0 | N16: 0 | O16: =M16/counta(P16:V16) -> 0 | P16: ー | Q16: ー | R16: ー | S16: ー | T16: ー | U16: ー | V16: 0 | X16: =iferror(VLOOKUP($E16,'セッション実施状況管理'!$H$10:$L$1028,4,FALSE),"") -> けい | Y16: 不明 | Z16: 不明 | AA16: 不明
A17: 6 | B17: =vlookup(A17,'セッション実施状況管理'!$A:$C,3,false) -> 2 | C17: =vlookup(A17,'セッション実施状況管理'!$A:$B,2,false) -> 卒業 | D17: =vlookup(A17,'セッション実施状況管理'!$A:$I,9,false) -> uni_beer_ | E17: =vlookup(A17,'セッション実施状況管理'!$A:$I,8,false) -> ありやまゆうな | F17: =vlookup(A17,'セッション実施状況管理'!$A:$U,19,false) -> 45516 | G17: =iferror(vlookup(D17,'セッション実施状況管理'!$I:$U,12,false),"-") -> 野村佑佳 | H17: =vlookup(A17,'セッション実施状況管理'!$A$4:$S1004,17,false) | I17: =(YEAR(TODAY()) - YEAR($H17)) * 12 + (MONTH(TODAY()) - MONTH($H17)) -> 1514 | K17: 7241 | L17: 0 | M17: =sum(P17:V17) -> 102 | N17: 102 | O17: =M17/counta(P17:V17) -> 14.571429 | P17: ー | Q17: 0 | R17: 30 | S17: 30 | T17: 31 | U17: 11 | V17: ー | X17: =iferror(VLOOKUP($E17,'セッション実施状況管理'!$H$10:$L$1028,4,FALSE),"") -> 駒居 | Y17: レシピ/料理 | Z17: 30〜39 | AA17: 単身
A18: 7 | B18: =vlookup(A18,'セッション実施状況管理'!$A:$C,3,false) -> 0 | C18: =vlookup(A18,'セッション実施状況管理'!$A:$B,2,false) -> 卒業 | D18: =vlookup(A18,'セッション実施状況管理'!$A:$I,9,false) -> yukari_dekirumon | E18: =vlookup(A18,'セッション実施状況管理'!$A:$I,8,false) -> たけにしゆかり | F18: =vlookup(A18,'セッション実施状況管理'!$A:$U,19,false) -> 45503 | G18: =iferror(vlookup(D18,'セッション実施状況管理'!$I:$U,12,false),"-") -> 宮田友理 | H18: =vlookup(A18,'セッション実施状況管理'!$A$4:$S1004,17,false) | I18: =(YEAR(TODAY()) - YEAR($H18)) * 12 + (MONTH(TODAY()) - MONTH($H18)) -> 1514 | K18: 64 | L18: 0 | M18: =sum(P18:V18) -> 6 | N18: 6 | O18: =M18/counta(P18:V18) -> 0.85714286 | P18: ー | Q18: 1 | R18: 5 | S18: 0 | T18: 0 | U18: 0 | V18: ー | X18: =iferror(VLOOKUP($E18,'セッション実施状況管理'!$H$10:$L$1028,4,FALSE),"") -> 駒居 | Y18: クリエイティブ | Z18: 30〜39 | AA18: 家族子供あり
A19: 8 | B19: =vlookup(A19,'セッション実施状況管理'!$A:$C,3,false) -> 0 | C19: =vlookup(A19,'セッション実施状況管理'!$A:$B,2,false) -> 卒業 | D19: =vlookup(A19,'セッション実施状況管理'!$A:$I,9,false) -> くどうゆみこ | E19: =vlookup(A19,'セッション実施状況管理'!$A:$I,8,false) -> くどうゆみこ | F19: =vlookup(A19,'セッション実施状況管理'!$A:$U,19,false) -> 45521 | G19: =iferror(vlookup(D19,'セッション実施状況管理'!$I:$U,12,false),"-") -> 野村佑佳 | H19: =vlookup(A19,'セッション実施状況管理'!$A$4:$S1004,17,false) | I19: =(YEAR(TODAY()) - YEAR($H19)) * 12 + (MONTH(TODAY()) - MONTH($H19)) -> 1514 | K19: 75 | L19: 0 | M19: =sum(P19:V19) -> 45 | N19: 45 | O19: =M19/counta(P19:V19) -> 6.4285714 | P19: ー | Q19: 5 | R19: 13 | S19: 9 | T19: 7 | U19: 11 | V19: ー | X19: =iferror(VLOOKUP($E19,'セッション実施状況管理'!$H$10:$L$1028,4,FALSE),"") -> しらゆき | Y19: 暮らし/DIY | Z19: 50〜59 | AA19: 単身
A20: 9 | B20: =vlookup(A20,'セッション実施状況管理'!$A:$C,3,false) -> 0 | C20: =vlookup(A20,'セッション実施状況管理'!$A:$B,2,false) -> 卒業 | D20: =vlookup(A20,'セッション実施状況管理'!$A:$I,9,false) -> negi_mamalife | E20: =vlookup(A20,'セッション実施状況管理'!$A:$I,8,false) -> たわらかずみ | F20: =vlookup(A20,'セッション実施状況管理'!$A:$U,19,false) -> 45515 | G20: =iferror(vlookup(D20,'セッション実施状況管理'!$I:$U,12,false),"-") -> 中村恵理 | I20: =(YEAR(TODAY()) - YEAR($H20)) * 12 + (MONTH(TODAY()) - MONTH($H20)) -> 1514 | K20: 127 | L20: 0 | M20: =sum(P20:V20) -> 109 | N20: 109 | O20: =M20/counta(P20:V20) -> 15.571429 | P20: ー | Q20: 3 | R20: 17 | S20: 27 | T20: 31 | U20: 31 | V20: ー | X20: =iferror(VLOOKUP($E20,'セッション実施状況管理'!$H$10:$L$1028,4,FALSE),"") -> ソウタ | Y20: 不明 | Z20: 不明 | AA20: 不明
A21: 10 | B21: =vlookup(A21,'セッション実施状況管理'!$A:$C,3,false) -> 0 | C21: =vlookup(A21,'セッション実施状況管理'!$A:$B,2,false) -> 卒業 | D21: =vlookup(A21,'セッション実施状況管理'!$A:$I,9,false) -> tewofuru_woodjewelry | E21: =vlookup(A21,'セッション実施状況管理'!$A:$I,8,false) -> やまぐちしんいちろう | F21: =vlookup(A21,'セッション実施状況管理'!$A:$U,19,false) -> 45514 | G21: =iferror(vlookup(D21,'セッション実施状況管理'!$I:$U,12,false),"-") -> 森本風花 | H21: =vlookup(A21,'セッション実施状況管理'!$A$4:$S1004,17,false) | I21: =(YEAR(TODAY()) - YEAR($H21)) * 12 + (MONTH(TODAY()) - MONTH($H21)) -> 1514 | K21: 128 | L21: 0 | M21: 128 | N21: 0 | O21: =M21/counta(P21:V21) -> 18.285714 | P21: ー | Q21: 0 | R21: 0 | S21: 0 | T21: 0 | U21: 0 | V21: 0 | X21: =iferror(VLOOKUP($E21,'セッション実施状況管理'!$H$10:$L$1028,4,FALSE),"") -> ソウタ | Y21: クリエイティブ | Z21: 60〜69 | AA21: 不明
A22: 11 | B22: =vlookup(A22,'セッション実施状況管理'!$A:$C,3,false) -> 0 | C22: =vlookup(A22,'セッション実施状況管理'!$A:$B,2,false) -> 卒業 | D22: =vlookup(A22,'セッション実施状況管理'!$A:$I,9,false) -> satojitan_recipe | E22: =vlookup(A22,'セッション実施状況管理'!$A:$I,8,false) -> かわかみまさと | F22: =vlookup(A22,'セッション実施状況管理'!$A:$U,19,false) -> 45520 | G22: =iferror(vlookup(D22,'セッション実施状況管理'!$I:$U,12,false),"-") -> 野村佑佳 | H22: =vlookup(A22,'セッション実施状況管理'!$A$4:$S1004,17,false) | I22: =(YEAR(TODAY()) - YEAR($H22)) * 12 + (MONTH(TODAY()) - MONTH($H22)) -> 1514 | K22: 354 | L22: 0 | M22: =sum(P22:V22) -> 14 | N22: 14 | O22: =M22/counta(P22:V22) -> 2 | P22: ー | Q22: 3 | R22: 2 | S22: 4 | T22: 4 | U22: 1 | V22: 0 | X22: =iferror(VLOOKUP($E22,'セッション実施状況管理'!$H$10:$L$1028,4,FALSE),"") -> しらゆき | Y22: レシピ/料理 | Z22: 20〜29 | AA22: その他
A23: 12 | B23: =vlookup(A23,'セッション実施状況管理'!$A:$C,3,false) -> 0 | C23: =vlookup(A23,'セッション実施状況管理'!$A:$B,2,false) -> 卒業 | D23: =vlookup(A23,'セッション実施状況管理'!$A:$I,9,false) -> richan_hair | E23: =vlookup(A23,'セッション実施状況管理'!$A:$I,8,false) -> すどうえり | F23: =vlookup(A23,'セッション実施状況管理'!$A:$U,19,false) -> 45514 | G23: =iferror(vlookup(D23,'セッション実施状況管理'!$I:$U,12,false),"-") -> 宮田友理 | H23: =vlookup(A23,'セッション実施状況管理'!$A$4:$S1004,17,false) | I23: =(YEAR(TODAY()) - YEAR($H23)) * 12 + (MONTH(TODAY()) - MONTH($H23)) -> 1514 | K23: 347 | L23: 0 | M23: =sum(P23:V23) -> 0 | N23: 0 | O23: =M23/counta(P23:V23) -> 0 | P23: ー | Q23: 0 | R23: 0 | S23: 0 | T23: 0 | U23: 0 | V23: 0 | X23: =iferror(VLOOKUP($E23,'セッション実施状況管理'!$H$10:$L$1028,4,FALSE),"") -> ソウタ | Y23: 美容/健康 | Z23: 30〜39 | AA23: 家族子供あり
A24: 13 | B24: =vlookup(A24,'セッション実施状況管理'!$A:$C,3,false) -> 0 | C24: =vlookup(A24,'セッション実施状況管理'!$A:$B,2,false) -> 卒業 | D24: =vlookup(A24,'セッション実施状況管理'!$A:$I,9,false) -> aya_travel_europe | E24: =vlookup(A24,'セッション実施状況管理'!$A:$I,8,false) -> なかのあや | F24: =vlookup(A24,'セッション実施状況管理'!$A:$U,19,false) -> 45527 | G24: =iferror(vlookup(D24,'セッション実施状況管理'!$I:$U,12,false),"-") -> 清原三和子 | H24: =vlookup(A24,'セッション実施状況管理'!$A$4:$S1004,17,false) | I24: =(YEAR(TODAY()) - YEAR($H24)) * 12 + (MONTH(TODAY()) - MONTH($H24)) -> 1514 | K24: 46 | L24: 0 | M24: =sum(P24:V24) -> 19 | N24: 19 | O24: =M24/counta(P24:V24) -> 2.7142857 | P24: ー | Q24: 0 | R24: 14 | S24: 4 | T24: 0 | U24: 1 | V24: 0 | X24: =iferror(VLOOKUP($E24,'セッション実施状況管理'!$H$10:$L$1028,4,FALSE),"") -> しらゆき | Y24: 不明 | Z24: 不明 | AA24: 不明
A25: 14 | B25: =vlookup(A25,'セッション実施状況管理'!$A:$C,3,false) -> 1 | C25: =vlookup(A25,'セッション実施状況管理'!$A:$B,2,false) -> 卒業 | D25: =vlookup(A25,'セッション実施状況管理'!$A:$I,9,false) -> uchiko_gohan | E25: =vlookup(A25,'セッション実施状況管理'!$A:$I,8,false) -> うちだあやみ | F25: =vlookup(A25,'セッション実施状況管理'!$A:$U,19,false) -> 45526 | G25: =iferror(vlookup(D25,'セッション実施状況管理'!$I:$U,12,false),"-") -> 清原三和子 | H25: =vlookup(A25,'セッション実施状況管理'!$A$4:$S1004,17,false) | I25: =(YEAR(TODAY()) - YEAR($H25)) * 12 + (MONTH(TODAY()) - MONTH($H25)) -> 1514 | K25: 48000 | L25: 0 | M25: =sum(P25:V25) -> 63 | N25: 63 | O25: =M25/counta(P25:V25) -> 9 | P25: ー | Q25: 0 | R25: 0 | S25: 7 | T25: 31 | U25: 25 | V25: 0 | X25: =iferror(VLOOKUP($E25,'セッション実施状況管理'!$H$10:$L$1028,4,FALSE),"") -> けいいち | Y25: 不明 | Z25: 不明 | AA25: 不明
A26: 15 | B26: =vlookup(A26,'セッション実施状況管理'!$A:$C,3,false) -> 0 | C26: =vlookup(A26,'セッション実施状況管理'!$A:$B,2,false) -> 卒業 | D26: =vlookup(A26,'セッション実施状況管理'!$A:$I,9,false) -> hiroyukichan_renai | E26: =vlookup(A26,'セッション実施状況管理'!$A:$I,8,false) -> さかもとなみこ | F26: =vlookup(A26,'セッション実施状況管理'!$A:$U,19,false) -> 45520 | G26: =iferror(vlookup(D26,'セッション実施状況管理'!$I:$U,12,false),"-") -> 山見阪佳子 | H26: =vlookup(A26,'セッション実施状況管理'!$A$4:$S1004,17,false) | I26: =(YEAR(TODAY()) - YEAR($H26)) * 12 + (MONTH(TODAY()) - MONTH($H26)) -> 1514 | K26: 2505 | L26: 0 | M26: =sum(P26:V26) -> 108 | N26: 108 | O26: =M26/counta(P26:V26) -> 15.428571 | P26: ー | Q26: 11 | R26: 29 | S26: 30 | T26: 29 | U26: 9 | V26: 0 | X26: =iferror(VLOOKUP($E26,'セッション実施状況管理'!$H$10:$L$1028,4,FALSE),"") -> ふみや | Y26: その他 | Z26: 30〜39 | AA26: 家族子供あり
A27: 16 | B27: =vlookup(A27,'セッション実施状況管理'!$A:$C,3,false) -> 0 | C27: =vlookup(A27,'セッション実施状況管理'!$A:$B,2,false) -> 卒業 | D27: =vlookup(A27,'セッション実施状況管理'!$A:$I,9,false) -> okumi_mind | E27: =vlookup(A27,'セッション実施状況管理'!$A:$I,8,false) -> あいざわくみこ | F27: =vlookup(A27,'セッション実施状況管理'!$A:$U,19,false) -> 45531 | G27: =iferror(vlookup(D27,'セッション実施状況管理'!$I:$U,12,false),"-") -> 清原三和子 | H27: =vlookup(A27,'セッション実施状況管理'!$A$4:$S1004,17,false) | I27: =(YEAR(TODAY()) - YEAR($H27)) * 12 + (MONTH(TODAY()) - MONTH($H27)) -> 1514 | K27: 1147 | L27: 0 | M27: =sum(P27:V27) -> 57 | N27: 57 | O27: =M27/counta(P27:V27) -> 8.1428571 | P27: ー | Q27: 7 | R27: 16 | S27: 21 | T27: 8 | U27: 5 | V27: 0 | X27: =iferror(VLOOKUP($E27,'セッション実施状況管理'!$H$10:$L$1028,4,FALSE),"") -> ふみや | Y27: 不明 | Z27: 20〜29 | AA27: 不明
A28: 17 | B28: =vlookup(A28,'セッション実施状況管理'!$A:$C,3,false) -> 0 | C28: =vlookup(A28,'セッション実施状況管理'!$A:$B,2,false) -> 卒業 | D28: =vlookup(A28,'セッション実施状況管理'!$A:$I,9,false) -> satousanni_kokuhaku | E28: =vlookup(A28,'セッション実施状況管理'!$A:$I,8,false) -> よこやまあいと | F28: =vlookup(A28,'セッション実施状況管理'!$A:$U,19,false) -> 45540 | G28: =iferror(vlookup(D28,'セッション実施状況管理'!$I:$U,12,false),"-") -> 福田康裕 | H28: =vlookup(A28,'セッション実施状況管理'!$A$4:$S1004,17,false) | I28: =(YEAR(TODAY()) - YEAR($H28)) * 12 + (MONTH(TODAY()) - MONTH($H28)) -> 1514 | K28: 3243 | L28: 0 | M28: =sum(P28:V28) -> 52 | N28: 52 | O28: =M28/counta(P28:V28) -> 7.4285714 | P28: ー | Q28: 2 | R28: 10 | S28: 14 | T28: 12 | U28: 14 | V28: 0 | X28: =iferror(VLOOKUP($E28,'セッション実施状況管理'!$H$10:$L$1028,4,FALSE),"") -> ふみや | Y28: 美容/健康 | Z28: 20〜29 | AA28: 家族子供あり
